Workbook

Sheet Input sheet
C1: Input cell | E1: Calculated cell
A3: Date of valuation | B3: 44592 | C3: Important: Before you run this spreadsheet, go into preferences in Excel and check under Calculation options
A4: Company name | B4: TEST (StockInsight test ticker) | C4: There should be a check against the iteration box. If there is not, you will get circular reasoning errors.
A5: Numbers from your base year below ( in consistent units, i.e., if you enter numbers in millions, stay with millions all the way through, including on share count.
A6: If you don't understand an input, turn on comemnts and you should see my suggestions on that input.
A7: Country of incorporation | B7: United States | F7: If you want a guide through this spreadsheet, try this YouTube video that takes you through each input cell: https://youtu.be/kyKfJ_7-mdg?si=FIeHhnLH2_2brag3
A8: Industry (US) | B8: Advertising
A9: Industry (Global) | B9: Advertising
B10: Most Recent 12 months | C10: Last 10K before LTM | D10: Years since last 10K
A11: Revenues | B11: 10000000 | C11: 9000000 | D11: 1
A12: Operating income or EBIT | B12: 1000000 | C12: 900000
A13: Interest expense | B13: 10000000 | C13: 9000000
A14: Book value of equity | B14: 10000000 | C14: 9000000
A15: Book value of debt | B15: 10000000 | C15: 9000000
A16: Do you have R&D expenses to capitalize? | B16: No | C16: If you want to capitalize R&D, you have to input the numbers into the R&D worksheet.
A17: Do you have operating lease commitments? | B17: No | C17: If you lease or other contractual commitments that have not been converteed to debt already, say yes to this option and do the conversion.
A18: Cash and Marketable Securities | B18: 10000000 | C18: 9000000
A19: Cross holdings and other non-operating assets | B19: 0 | C19: 0
A20: Minority interests | B20: 0 | C20: 0
A21: Number of shares outstanding = | B21: 10000000 | E21: Computed numbers: Here is what your company's numbers look like, relative to industry.
A22: Current stock price = | B22: 100 | E22: If you are not working in US dollars, you should add the inflation differential to the industry averages.
A23: Effective tax rate = | B23: 0.175 | J23: Industry (US) | K23: Industry (Global) | L23: Global Distribution Stats
A24: Marginal tax rate = | B24: 0.25 | I24: Company | J24: Average | K24: Average | L24: 1st Quartile | M24: Median | N24: 3rd Quartile
A25: The value drivers below: | E25: Revenue growth in the most recent year = | I25: =IF(C11>0,(B11/C11)^(1/D11)-1, "NA") | J25: =VLOOKUP(B8,'Industry Averages(US)'!A2:S95,3) | K25: =VLOOKUP(B9,'Industry Averages (Global)'!A2:N95,3) | L25: =VLOOKUP($B$9,'Input Stat Distributioons'!$A$3:$T$96,3,FALSE) | M25: =VLOOKUP($B$9,'Input Stat Distributioons'!$A$3:$T$96,4,FALSE) | N25: =VLOOKUP($B$9,'Input Stat Distributioons'!$A$3:$T$96,5,FALSE)
A26: Revenue growth rate for next year | B26: 0.1 | C26: Growth Lever - Next year | E26: Pre-tax operating margin in the most recent year = | I26: ='Valuation output'!B4 | J26: =VLOOKUP(B8,'Industry Averages(US)'!A2:AA95,4) | K26: =VLOOKUP(B9,'Industry Averages (Global)'!A2:N95,4) | L26: =VLOOKUP($B$9,'Input Stat Distributioons'!$A$3:$T$96,6,FALSE) | M26: =VLOOKUP($B$9,'Input Stat Distributioons'!$A$3:$T$96,7,FALSE) | N26: =VLOOKUP($B$9,'Input Stat Distributioons'!$A$3:$T$96,8,FALSE)
A27: Operating Margin for next year | B27: 0.1 | C27: Profitability Lever - Next year | E27: Sales to capital ratio in most recent year = | I27: =B11/'Valuation output'!B39 | J27: =VLOOKUP(B8,'Industry Averages(US)'!A2:S95,14) | K27: =VLOOKUP(B9,'Industry Averages (Global)'!A2:N95,14) | L27: =VLOOKUP($B$9,'Input Stat Distributioons'!$A$3:$T$96,9,FALSE) | M27: =VLOOKUP($B$9,'Input Stat Distributioons'!$A$3:$T$96,10,FALSE) | N27: =VLOOKUP($B$9,'Input Stat Distributioons'!$A$3:$T$96,11,FALSE)
A28: Compounded annual revenue growth rate - years 2-5 = | B28: 0.1 | C28: Growth Lever - Long term | E28: Marginal sales to capital ratio = | I28: =IF(('Input sheet'!B11-'Input sheet'!C11)/(('Input sheet'!B14+'Input sheet'!B15-'Input sheet'!B18)-('Input sheet'!C14+'Input sheet'!C15-'Input sheet'!C18))>0,('Input sheet'!B11-'Input sheet'!C11)/(('Input sheet'!B14+'Input sheet'!B15-'Input sheet'!B18)-('Input sheet'!C14+'Input sheet'!C15-'Input sheet'!C18)),"NA")
A29: Target pre-tax operating margin = | B29: 0.1 | C29: Profitability Lever - Long term | E29: Return on invested capital in most recent year= | I29: ='Valuation output'!B7/'Valuation output'!B39 | J29: =VLOOKUP(B8,'Industry Averages(US)'!A2:S95,5) | K29: =VLOOKUP(B9,'Industry Averages (Global)'!A2:N95,5)
A30: Year of convergence for margin | B30: 5 | C30: Speed of convergence level | E30: Standard deviation in stock prices = | J30: =VLOOKUP(B8,'Industry Averages(US)'!A2:S95,10) | K30: =VLOOKUP(B8,'Industry Averages (Global)'!A2:Z95,10)
A31: Sales to capital ratio (for years 1-5) | B31: 2 | C31: Efficency of Growth Lever (first 5 years) | E31: Cost of capital = | I31: =B35 | J31: =VLOOKUP(B8,'Industry Averages(US)'!A2:S95,13) | K31: =VLOOKUP(B8,'Industry Averages (Global)'!A2:Z95,13) | L31: =VLOOKUP($B$9,'Input Stat Distributioons'!$A$3:$T$96,12,FALSE) | M31: =VLOOKUP($B$9,'Input Stat Distributioons'!$A$3:$T$96,13,FALSE) | N31: =VLOOKUP($B$9,'Input Stat Distributioons'!$A$3:$T$96,14,FALSE)
A32: Sales to capital ratio (for years 6-10) | B32: 2 | C32: Efficency of Growth Lever (years 6-10)
A33: Market numbers | E33: Valuation Output Feedback (for you to use to fine tune your inputs, if you want)
A34: Riskfree rate | B34: 0.04 | E34: Revenues in year 10, based on your revenue growth = | J34: ='Valuation output'!M3
A35: Initial cost of capital = | B35: ='Cost of capital worksheet'!B13 | C35: Do not input. Go to cost of capital sheet. | E35: Pre-tax Operating Income in year 10, based on your operating margin = | J35: ='Valuation output'!M5
A36: Other inputs | E36: Return on invested capital in year 10, based on your sales/capital ratio = | J36: ='Valuation output'!L40
A37: Do you have employee options outstanding? | B37: No | E37: Check the Diagnostics worksheet for more details.
A38: Number of options outstanding = | B38: 7.72
A39: Average strike price = | B39: 1.29
A40: Average maturity = | B40: 7
A41: Standard deviation on stock price = | B41: 0.45
A43: Default assumptions.
A44: In stable growth, I will assume that your firm will have a cost of capital similar to that of typical mature companies (riskfree rate + 4.5%)
A45: Do you want to override this assumption = | B45: No | C45: Mature companies generally see their risk levels approach the average
A46: If yes, enter the cost of capital after year 10 = | B46: =B35 | C46: Though some sectors, even in stable growth, may have higher risk. If you change your risk free rate after year 10 (see cell B57 & 58), you should incorporate the change into your stable cost of capital estimate.
A47: I will assume that your firm will earn a return on capital equal to its cost of capital after year 10. I am assuming that whatever competitive advantages you have today will fade over time.
A48: Do you want to override this assumption = | B48: No | C48: Mature companies find it difficult to generate returns that exceed the cost of capital
A49: If yes, enter the return on capital you expect after year 10 | B49: 0.15 | C49: But there are significant exceptions among companies with long-lasting competitive advantages.
A50: I will assume that your firm has no chance of failure over the foreseeable future.
A51: Do you want to override this assumption = | B51: No | C51: Many young, growth companies fail, especially if they have trouble raising cash. Many distressed companies fail, because they have trouble making debt payments.
A52: If yes, enter the probability of failure = | B52: 0.12 | C52: Tough to estimate but a key input. Use the failure rate worksheet, if necessary.
A53: What do you want to tie your proceeds in failure to? | B53: V | C53: B: Book value of capital, V= Estimated fair value for the company
A54: Enter the distress proceeds as percentage of book or fair value | B54: 0.5 | C54: This can be zero, if the assets will be worth nothing if the firm fails.
A55: I assume that reinvestment in a year translates into growth in the next year, i.e., there is a one year lag between reinvesting and generating growth from that reinvestment.
A56: Do you want override this assumption = | B56: No
A57: If yes, enter a different lag (0 = no lag to 3 = lag of 3 years) | B57: 1
A58: I will assume that your effective tax rate will adjust to your marginal tax rate by your terminal year. If you override this assumption, I will leave the tax rate at your effective tax rate.
A59: Do you want to override this assumption = | B59: No
A60: I will assume that you have no losses carried forward from prior years ( NOL) coming into the valuation. If you have a money losing company, you may want to override tis.
A61: Do you want to override this assumption = | B61: No | C61: Check the financial statements.
A62: If yes, enter the NOL that you are carrying over into year 1 | B62: =474.8+256.6 | C62: An NOL will shield your income from taxes, even after you start making money.
A63: I will asssume that today's risk free rate will prevail in perpetuity. If you override this assumption, I will change the riskfree rate after year 10.
A64: Do you want to override this assumption = | B64: No | C64: If yes, you will be asked to enter a normal risk free rate and your growth in perpetuity will be adjusted accordingly.
A65: If yes, enter the riskfree rate after year 10 | B65: 0.02 | C65: Enter your estimate of what the riskfree rate (in your currency of choice) will be after year 10
A66: I will assume that the growth rate in perpetuity will be equal to the risk free rate. This allows for both valuation consistency and prevents "impossible" growth rates.
A67: Do you want to override this assumption = | B67: No | C67: This is an option to let you use a negative growth rate in perpetuity or to even liquidate the firm.
A68: If yes, enter the growth rate in perpetuity | B68: -0.05 | C68: This can be negative, if you feel the company will decline (and disappear) after growth is done. If you let it exceed the risk free rate, you are on your own in uncharted territory.
A69: I have assumed that none of the cash is trapped (in foreign countries) and that there is no additional tax liability coming due and that cash is a neutral asset.
A70: Do you want to override this assumption | B70: No
A71: If yes, enter trapped cash (if taxes) or entire balance (if mistrust) | B71: 140000 | C71: Cash that is trapped in foreign markets (and subject to additoinal tax) or cash that is being discounted by the market (because of management mistrust)
A72: & Average tax rate of the foreign markets where the cash is trapped | B72: 0.15 | C72: Additional tax rate due on trapped cash or discount being applied to cash balance because of mistrust.

Sheet Valuation output
B1: Base year | C1: 1 | D1: 2 | E1: 3 | F1: 4 | G1: 5 | H1: 6 | I1: 7 | J1: 8 | K1: 9 | L1: 10 | M1: Terminal year
A2: Revenue growth rate | C2: ='Input sheet'!B26 | D2: ='Input sheet'!B28 | E2: =D2 | F2: =E2 | G2: =F2 | H2: =G2-((G2-$M$2)/5) | I2: =G2-((G2-$M$2)/5)*2 | J2: =G2-((G2-$M$2)/5)*3 | K2: =G2-((G2-$M$2)/5)*4 | L2: =G2-((G2-$M$2)/5)*5 | M2: =IF('Input sheet'!B67="Yes",'Input sheet'!B68,IF('Input sheet'!B64="Yes",'Input sheet'!B65,'Input sheet'!B34))
A3: Revenues | B3: ='Input sheet'!B11 | C3: =B3*(1+C2) | D3: =C3*(1+D2) | E3: =D3*(1+E2) | F3: =E3*(1+F2) | G3: =F3*(1+G2) | H3: =G3*(1+H2) | I3: =H3*(1+I2) | J3: =I3*(1+J2) | ... M3: =L3*(1+M2)
A4: EBIT (Operating) margin | B4: =B5/B3 | C4: ='Input sheet'!B27 | D4: =IF(D1>'Input sheet'!$B$30,'Input sheet'!$B$29,'Input sheet'!$B$29-(('Input sheet'!$B$29-$C$4)/'Input sheet'!$B$30)*('Input sheet'!$B$30-D1)) | E4: =IF(E1>'Input sheet'!$B$30,'Input sheet'!$B$29,'Input sheet'!$B$29-(('Input sheet'!$B$29-$C$4)/'Input sheet'!$B$30)*('Input sheet'!$B$30-E1)) | F4: =IF(F1>'Input sheet'!$B$30,'Input sheet'!$B$29,'Input sheet'!$B$29-(('Input sheet'!$B$29-$C$4)/'Input sheet'!$B$30)*('Input sheet'!$B$30-F1)) | G4: =IF(G1>'Input sheet'!$B$30,'Input sheet'!$B$29,'Input sheet'!$B$29-(('Input sheet'!$B$29-$C$4)/'Input sheet'!$B$30)*('Input sheet'!$B$30-G1)) | H4: =IF(H1>'Input sheet'!$B$30,'Input sheet'!$B$29,'Input sheet'!$B$29-(('Input sheet'!$B$29-$C$4)/'Input sheet'!$B$30)*('Input sheet'!$B$30-H1)) | I4: =IF(I1>'Input sheet'!$B$30,'Input sheet'!$B$29,'Input sheet'!$B$29-(('Input sheet'!$B$29-$C$4)/'Input sheet'!$B$30)*('Input sheet'!$B$30-I1)) | J4: =IF(J1>'Input sheet'!$B$30,'Input sheet'!$B$29,'Input sheet'!$B$29-(('Input sheet'!$B$29-$C$4)/'Input sheet'!$B$30)*('Input sheet'!$B$30-J1)) | K4: =IF(K1>'Input sheet'!$B$30,'Input sheet'!$B$29,'Input sheet'!$B$29-(('Input sheet'!$B$29-$C$4)/'Input sheet'!$B$30)*('Input sheet'!$B$30-K1)) | L4: =IF(L1>'Input sheet'!$B$30,'Input sheet'!$B$29,'Input sheet'!$B$29-(('Input sheet'!$B$29-$C$4)/'Input sheet'!$B$30)*('Input sheet'!$B$30-L1)) | M4: =L4
A5: EBIT (Operating income) | B5: =IF('Input sheet'!B17="Yes",IF('Input sheet'!B16="Yes",'Input sheet'!B12+'Operating lease converter'!F32+'R& D converter'!D39,'Input sheet'!B12+'Operating lease converter'!F32),IF('Input sheet'!B16="Yes",'Input sheet'!B12+'R& D converter'!D39,'Input sheet'!B12)) | C5: =C4*C3 | D5: =D4*D3 | E5: =E4*E3 | F5: =F4*F3 | G5: =G4*G3 | H5: =H4*H3 | I5: =I4*I3 | J5: =J4*J3 | ... M5: =M4*M3 | N5: =M5-B5
A6: Tax rate | B6: ='Input sheet'!B23 | C6: =B6 | D6: =C6 | E6: =D6 | F6: =E6 | G6: =F6 | H6: =G6+($M$6-$G$6)/5 | I6: =H6+($M$6-$G$6)/5 | J6: =I6+($M$6-$G$6)/5 | K6: =J6+($M$6-$G$6)/5 | L6: =K6+($M$6-$G$6)/5 | M6: =IF('Input sheet'!B59="Yes",'Input sheet'!B23,'Input sheet'!B24)
A7: EBIT(1-t) | B7: =IF(B5>0,B5*(1-B6),B5) | C7: =IF(C5>0,IF(C5<B10,C5,C5-(C5-B10)*C6),C5) | D7: =IF(D5>0,IF(D5<C10,D5,D5-(D5-C10)*D6),D5) | E7: =IF(E5>0,IF(E5<D10,E5,E5-(E5-D10)*E6),E5) | F7: =IF(F5>0,IF(F5<E10,F5,F5-(F5-E10)*F6),F5) | G7: =IF(G5>0,IF(G5<F10,G5,G5-(G5-F10)*G6),G5) | H7: =IF(H5>0,IF(H5<G10,H5,H5-(H5-G10)*H6),H5) | I7: =IF(I5>0,IF(I5<H10,I5,I5-(I5-H10)*I6),I5) | J7: =IF(J5>0,IF(J5<I10,J5,J5-(J5-I10)*J6),J5) | ... L7: =IF(L5>0,IF(L5<K10,L5,L5-(L5-K10)*L6),L5) | M7: =M5*(1-M6)
A8: - Reinvestment | C8: =IF('Input sheet'!$B$56="No",(D3-C3)/C38,IF('Input sheet'!$B$57=0,(C3-B3)/C38,IF('Input sheet'!$B$57=2,(E3-D3)/C38,IF('Input sheet'!$B$57=3,(F3-E3)/C38,(D3-C3)/C38)))) | D8: =IF('Input sheet'!$B$56="No",(E3-D3)/D38,IF('Input sheet'!$B$57=0,(D3-C3)/D38,IF('Input sheet'!$B$57=2,(F3-E3)/D38,IF('Input sheet'!$B$57=3,(G3-F3)/D38,(E3-D3)/D38)))) | E8: =IF('Input sheet'!$B$56="No",(F3-E3)/E38,IF('Input sheet'!$B$57=0,(E3-D3)/E38,IF('Input sheet'!$B$57=2,(G3-F3)/E38,IF('Input sheet'!$B$57=3,(H3-G3)/E38,(F3-E3)/E38)))) | F8: =IF('Input sheet'!$B$56="No",(G3-F3)/F38,IF('Input sheet'!$B$57=0,(F3-E3)/F38,IF('Input sheet'!$B$57=2,(H3-G3)/F38,IF('Input sheet'!$B$57=3,(I3-H3)/F38,(G3-F3)/F38)))) | G8: =IF('Input sheet'!$B$56="No",(H3-G3)/G38,IF('Input sheet'!$B$57=0,(G3-F3)/G38,IF('Input sheet'!$B$57=2,(I3-H3)/G38,IF('Input sheet'!$B$57=3,(J3-I3)/G38,(H3-G3)/G38)))) | H8: =IF('Input sheet'!$B$56="No",(I3-H3)/H38,IF('Input sheet'!$B$57=0,(H3-G3)/H38,IF('Input sheet'!$B$57=2,(J3-I3)/H38,IF('Input sheet'!$B$57=3,(K3-J3)/H38,(I3-H3)/H38)))) | I8: =IF('Input sheet'!$B$56="No",(J3-I3)/I38,IF('Input sheet'!$B$57=0,(I3-H3)/I38,IF('Input sheet'!$B$57=2,(K3-J3)/I38,IF('Input sheet'!$B$57=3,(L3-K3)/I38,(J3-I3)/I38)))) | J8: =IF('Input sheet'!$B$56="No",(K3-J3)/J38,IF('Input sheet'!$B$57=0,(J3-I3)/J38,IF('Input sheet'!$B$57=2,(L3-K3)/J38,IF('Input sheet'!$B$57=3,(M3-L3)/J38,(K3-J3)/J38)))) | K8: =IF('Input sheet'!$B$56="No",(L3-K3)/K38,IF('Input sheet'!$B$57=0,(K3-J3)/K38,IF('Input sheet'!$B$57=2,L3*L2/K38,IF('Input sheet'!$B$57=3,M3*M2/K38,(L3-K3)/K38)))) | L8: =IF('Input sheet'!$B$56="No",(M3-L3)/L38,IF('Input sheet'!$B$57=0,(L3-K3)/L38,IF('Input sheet'!$B$57=2,M3*M2/L38,IF('Input sheet'!$B$57=3,K8*(1+M2),(M3-L3)/L38)))) | M8: =IF(M2>0,(M2/M40)*M7,0) | N8: =SUM(C8:M8)
A9: FCFF | C9: =C7-C8 | D9: =D7-D8 | E9: =E7-E8 | F9: =F7-F8 | G9: =G7-G8 | H9: =H7-H8 | I9: =I7-I8 | J9: =J7-J8 | ... M9: =M7-M8
A10: NOL | B10: =IF('Input sheet'!B61="Yes",'Input sheet'!B62,0) | C10: =IF(C5<0,B10-C5,IF(B10>C5,B10-C5,0)) | D10: =IF(D5<0,C10-D5,IF(C10>D5,C10-D5,0)) | E10: =IF(E5<0,D10-E5,IF(D10>E5,D10-E5,0)) | F10: =IF(F5<0,E10-F5,IF(E10>F5,E10-F5,0)) | G10: =IF(G5<0,F10-G5,IF(F10>G5,F10-G5,0)) | H10: =IF(H5<0,G10-H5,IF(G10>H5,G10-H5,0)) | I10: =IF(I5<0,H10-I5,IF(H10>I5,H10-I5,0)) | J10: =IF(J5<0,I10-J5,IF(I10>J5,I10-J5,0)) | ... M10: =IF(M5<0,L10-M5,IF(L10>M5,L10-M5,0))
A12: Cost of capital | C12: ='Input sheet'!B35 | D12: =C12 | E12: =D12 | F12: =E12 | G12: =F12 | H12: =G12-($G$12-$M$12)/5 | I12: =H12-($G$12-$M$12)/5 | J12: =I12-($G$12-$M$12)/5 | K12: =J12-($G$12-$M$12)/5 | L12: =K12-($G$12-$M$12)/5 | M12: =IF('Input sheet'!B45="Yes",'Input sheet'!B46,IF('Input sheet'!B64="Yes",'Input sheet'!B65+'Country equity risk premiums'!B1,'Input sheet'!B34+'Country equity risk premiums'!B1))
A13: Cumulated discount factor | C13: =1/(1+C12) | D13: =C13*(1/(1+D12)) | E13: =D13*(1/(1+E12)) | F13: =E13*(1/(1+F12)) | G13: =F13*(1/(1+G12)) | H13: =G13*(1/(1+H12)) | I13: =H13*(1/(1+I12)) | J13: =I13*(1/(1+J12)) | K13: =J13*(1/(1+K12)) | L13: =K13*(1/(1+L12))
A14: PV(FCFF) | C14: =C9*C13 | D14: =D9*D13 | E14: =E9*E13 | F14: =F9*F13 | G14: =G9*G13 | H14: =H9*H13 | I14: =I9*I13 | J14: =J9*J13 | ... L14: =L9*L13
A16: Terminal cash flow | B16: =M9
A17: Terminal cost of capital | B17: =M12
A18: Terminal value | B18: =B16/(B17-M2)
A19: PV(Terminal value) | B19: =B18*L13
A20: PV (CF over next 10 years) | B20: =SUM(C14:L14)
A21: Sum of PV | B21: =B19+B20
A22: Probability of failure = | B22: =IF('Input sheet'!B51="Yes",'Input sheet'!B52,0)
A23: Proceeds if firm fails = | B23: =IF('Input sheet'!B53="B",('Input sheet'!B14+'Input sheet'!B15)*'Input sheet'!B54,'Valuation output'!B21*'Input sheet'!B54)
A24: Value of operating assets = | B24: =B21*(1-B22)+B23*B22
A25: - Debt | B25: =IF('Input sheet'!B17="Yes",'Input sheet'!B15+'Operating lease converter'!C28,'Input sheet'!B15)
A26: - Minority interests | B26: ='Input sheet'!B20
A27: + Cash | B27: =IF('Input sheet'!B70="YES",'Input sheet'!B18-'Input sheet'!B71*('Input sheet'!B24-'Input sheet'!B72),'Input sheet'!B18) | D27: If you get Value Errors all over, it is usually because your option worksheet has gone haywire. The fix is very low tech. Go into the option value worksheet, and in cell B17 of that worksheet (adjusted S), enter any number (say 5) and then undo what you did. Voila!
A28: + Non-operating assets | B28: ='Input sheet'!B19
A29: Value of equity | B29: =B24-B25-B26+B27+B28
A30: - Value of options | B30: =IF('Input sheet'!B37="No",0,'Option value'!B29)
A31: Value of equity in common stock | B31: =B29-B30
A32: Number of shares | B32: ='Input sheet'!B21
A33: Estimated value /share | B33: =B31/B32
A34: Price | B34: ='Input sheet'!B22
A35: Price as % of value | B35: =B34/B33
A37: Implied variables | M37: After year 10
A38: Sales to capital ratio | C38: ='Input sheet'!B31 | D38: ='Input sheet'!B31 | E38: =D38 | F38: =E38 | G38: =F38 | H38: ='Input sheet'!B32 | I38: =H38 | J38: =I38 | K38: =J38 | L38: =K38
A39: Invested capital | B39: =IF('Input sheet'!B17="Yes",IF('Input sheet'!B16="Yes",'Input sheet'!B14+'Input sheet'!B15-'Input sheet'!B18+'Operating lease converter'!F33+'R& D converter'!D35,'Input sheet'!B14+'Input sheet'!B15-'Input sheet'!B18+'Operating lease converter'!F33),IF('Input sheet'!B16="Yes",'Input sheet'!B14+'Input sheet'!B15-'Input sheet'!B18+'R& D converter'!D35,'Input sheet'!B14+'Input sheet'!B15-'Input sheet'!B18)) | C39: =B39+C8 | D39: =C39+D8 | E39: =D39+E8 | F39: =E39+F8 | G39: =F39+G8 | H39: =G39+H8 | I39: =H39+I8 | J39: =I39+J8 | ... L39: =K39+L8
A40: ROIC | B40: =B7/B39 | C40: =C7/B39 | D40: =D7/C39 | E40: =E7/D39 | F40: =F7/E39 | G40: =G7/F39 | H40: =H7/G39 | I40: =I7/H39 | J40: =J7/I39 | ... L40: =L7/K39 | M40: =IF('Input sheet'!B48="Yes",'Input sheet'!B49,'Valuation output'!L12)

Sheet Stories to Numbers
A1: ='Input sheet'!B4 | G1: ='Input sheet'!B3
A2: The Disruption Platform Rolls on
A3: Amazon continues on its transformation from online retailer to disruption platform, willling to enter any business that it perceives as inefficiently run, and changing it. Along the way, it will invest large amounts of capital and wait for long periods to attain profitability. | H3: Tell your story about the company. Keep it focuses on the company's businesses and tie it into the three key levers of value: cash flows, growth and risk
A7: The Assumptions
B8: Base year | C8: Next year | D8: Years 2-5 | E8: Years 6-10 | F8: After year 10 | G8: Link to story
A9: Revenues (a) | B9: ='Valuation output'!B3 | C9: ='Input sheet'!B26 | D9: ='Input sheet'!B28 | E9: Changes to | F9: ='Valuation output'!M2 | G9: Disruption platform in multiple businesses | H9: Tie each assumption to the part of your story that relates to it.
A10: Operating margin (b) | B10: ='Valuation output'!B4 | C10: ='Input sheet'!B27 | D10: Moves to | E10: ='Valuation output'!G4 | F10: ='Valuation output'!M4 | G10: Margins improve, aided by cloud business & continued economies of scale.
A11: Tax rate | B11: ='Valuation output'!B6 | D11: =B11 | E11: Changes to | F11: ='Valuation output'!M6 | G11: Global/US marginal tax rate over time
A12: Sales to Capital (c ) | C12: ='Input sheet'!B31 | D12: ='Input sheet'!B31 | E12: ='Input sheet'!B32 | F12: ='Valuation output'!M2/'Valuation output'!M40 | G12: Maintained at Amazon's current level
A13: Return on capital | B13: ='Valuation output'!B40 | C13: Marginal ROIC = | D13: =Diagnostics!C27 | F13: ='Valuation output'!M40 | G13: Strong competitive edges
A14: Cost of capital (d) | D14: ='Valuation output'!C12 | F14: ='Valuation output'!M12 | G14: Cost of capital close to median company
A15: The Cash Flows
B16: Revenues | C16: Operating Margin | D16: EBIT | E16: EBIT (1-t) | F16: Reinvestment | G16: FCFF | H16: These are the numbers that come from your assumptions. The revenues over time reflect your revenue growth, the operating margins evolve towards your target margin and your tax rate will change, if you have set it to. The reinvestment is estimated using the sales to capital ratio for the first 10 years and based on a reinvestment rate in stable growth (g/ ROC).
A17: 1 | B17: ='Valuation output'!C3 | C17: ='Valuation output'!C4 | D17: =B17*C17 | E17: ='Valuation output'!C7 | F17: ='Valuation output'!C8 | G17: =E17-F17
A18: 2 | B18: ='Valuation output'!D3 | C18: ='Valuation output'!D4 | D18: =B18*C18 | E18: ='Valuation output'!D7 | F18: ='Valuation output'!D8 | G18: =E18-F18
A19: 3 | B19: ='Valuation output'!E3 | C19: ='Valuation output'!E4 | D19: =B19*C19 | E19: ='Valuation output'!E7 | F19: ='Valuation output'!E8 | G19: =E19-F19
A20: 4 | B20: ='Valuation output'!F3 | C20: ='Valuation output'!F4 | D20: =B20*C20 | E20: ='Valuation output'!F7 | F20: ='Valuation output'!F8 | G20: =E20-F20
A21: 5 | B21: ='Valuation output'!G3 | C21: ='Valuation output'!G4 | D21: =B21*C21 | E21: ='Valuation output'!G7 | F21: ='Valuation output'!G8 | G21: =E21-F21
A22: 6 | B22: ='Valuation output'!H3 | C22: ='Valuation output'!H4 | D22: =B22*C22 | E22: ='Valuation output'!H7 | F22: ='Valuation output'!H8 | G22: =E22-F22
A23: 7 | B23: ='Valuation output'!I3 | C23: ='Valuation output'!I4 | D23: =B23*C23 | E23: ='Valuation output'!I7 | F23: ='Valuation output'!I8 | G23: =E23-F23
A24: 8 | B24: ='Valuation output'!J3 | C24: ='Valuation output'!J4 | D24: =B24*C24 | E24: ='Valuation output'!J7 | F24: ='Valuation output'!J8 | G24: =E24-F24
A25: 9 | B25: ='Valuation output'!K3 | C25: ='Valuation output'!K4 | D25: =B25*C25 | E25: ='Valuation output'!K7 | F25: ='Valuation output'!K8 | G25: =E25-F25
A26: 10 | B26: ='Valuation output'!L3 | C26: ='Valuation output'!L4 | D26: =B26*C26 | E26: ='Valuation output'!L7 | F26: ='Valuation output'!L8 | G26: =E26-F26
A27: Terminal year | B27: ='Valuation output'!M3 | C27: ='Valuation output'!M4 | D27: =B27*C27 | E27: ='Valuation output'!M7 | F27: ='Valuation output'!M8 | G27: =E27-F27
A28: The Value
A29: Terminal value | D29: ='Valuation output'!B18 | H29: This is the output from your valuation. It reflects your cash flows being discounted back at the cost of capital to get to your operating asset value, which then gets adjusted for the likelihood that your firm will not make it. We add cash and non-operating assets, subtract out debt and minority interests to get to value of equity.
A30: PV(Terminal value) | D30: ='Valuation output'!B19
A31: PV (CF over next 10 years) | D31: ='Valuation output'!B20
A32: Value of operating assets = | D32: ='Valuation output'!B21
A33: Adjustment for distress | D33: =D32-'Valuation output'!B24 | E33: Probability of failure = | G33: ='Valuation output'!B22
A34: - Debt & Minority Interests | D34: ='Valuation output'!B25+'Valuation output'!B26
A35: + Cash & Other Non-operating assets | D35: ='Valuation output'!B27+'Valuation output'!B28
A36: Value of equity | D36: =D32-D33-D34+D35
A37: - Value of equity options | D37: ='Valuation output'!B30
A38: Number of shares | D38: ='Valuation output'!B32
A39: Value per share | D39: =(D36-D37)/D38 | E39: Stock was trading at = | G39: ='Input sheet'!B22

Sheet Valuation as picture
A1: You can modify this picture and bring in relevant details to back up your cost of capital and other details that you think flesh out your company's valuation story.
A3: ='Input sheet'!B4 | O3: ='Input sheet'!B3
A5: Base Year and Comparison | E5: Growth Story | H5: Profitability Story | K5: Growth Efficiency Story
B6: Company | C6: Industry | E6: ='Stories to Numbers'!G9 | H6: ='Stories to Numbers'!G10 | K6: ='Stories to Numbers'!G12 | O6: Terminal Value
A7: Revenue Growth | B7: ='Input sheet'!I25 | C7: ='Input sheet'!K25 | O7: Growth Rate | P7: =O16
A8: Revenue | B8: ='Valuation output'!B3 | O8: Cost of capital | P8: ='Valuation output'!M12
A9: Operating Margin | B9: ='Valuation output'!B4 | C9: ='Input sheet'!K26 | O9: Return on capital | P9: ='Valuation output'!M40
A10: Operating Income | B10: ='Valuation output'!B5 | O10: Reinvestment Rate | P10: =P7/P9
A11: EBIT (1-t) | B11: ='Valuation output'!B7
A15: ='Valuation output'!A19 | B15: ='Valuation output'!B19 | E15: ='Valuation output'!C1 | F15: ='Valuation output'!D1 | G15: ='Valuation output'!E1 | H15: ='Valuation output'!F1 | I15: ='Valuation output'!G1 | J15: ='Valuation output'!H1 | K15: ='Valuation output'!I1 | L15: ='Valuation output'!J1 | ... O15: ='Valuation output'!M1
A16: ='Valuation output'!A20 | B16: ='Valuation output'!B20 | D16: Revenue Growth | E16: ='Valuation output'!C2 | F16: ='Valuation output'!D2 | G16: ='Valuation output'!E2 | H16: ='Valuation output'!F2 | I16: ='Valuation output'!G2 | J16: ='Valuation output'!H2 | K16: ='Valuation output'!I2 | L16: ='Valuation output'!J2 | ... O16: ='Valuation output'!M2
A17: ='Valuation output'!A22 | B17: ='Valuation output'!B22 | D17: Revenue | E17: ='Valuation output'!C3 | F17: ='Valuation output'!D3 | G17: ='Valuation output'!E3 | H17: ='Valuation output'!F3 | I17: ='Valuation output'!G3 | J17: ='Valuation output'!H3 | K17: ='Valuation output'!I3 | L17: ='Valuation output'!J3 | ... O17: ='Valuation output'!M3
A18: ='Valuation output'!A24 | B18: ='Valuation output'!B24 | D18: Operating Margin | E18: ='Valuation output'!C4 | F18: ='Valuation output'!D4 | G18: ='Valuation output'!E4 | H18: ='Valuation output'!F4 | I18: ='Valuation output'!G4 | J18: ='Valuation output'!H4 | K18: ='Valuation output'!I4 | L18: ='Valuation output'!J4 | ... O18: ='Valuation output'!M4
A19: ='Valuation output'!A25 | B19: ='Valuation output'!B25 | D19: Operating Income | E19: ='Valuation output'!C5 | F19: ='Valuation output'!D5 | G19: ='Valuation output'!E5 | H19: ='Valuation output'!F5 | I19: ='Valuation output'!G5 | J19: ='Valuation output'!H5 | K19: ='Valuation output'!I5 | L19: ='Valuation output'!J5 | ... O19: ='Valuation output'!M5
A20: ='Valuation output'!A26 | B20: ='Valuation output'!B26 | D20: EBIT (1-t) | E20: ='Valuation output'!C7 | F20: ='Valuation output'!D7 | G20: ='Valuation output'!E7 | H20: ='Valuation output'!F7 | I20: ='Valuation output'!G7 | J20: ='Valuation output'!H7 | K20: ='Valuation output'!I7 | L20: ='Valuation output'!J7 | ... O20: ='Valuation output'!M7
A21: ='Valuation output'!A27 | B21: ='Valuation output'!B27 | D21: Reinvestment | E21: ='Valuation output'!C8 | F21: ='Valuation output'!D8 | G21: ='Valuation output'!E8 | H21: ='Valuation output'!F8 | I21: ='Valuation output'!G8 | J21: ='Valuation output'!H8 | K21: ='Valuation output'!I8 | L21: ='Valuation output'!J8 | ... O21: ='Valuation output'!M8
A22: ='Valuation output'!A28 | B22: ='Valuation output'!B28 | D22: FCFF | E22: ='Valuation output'!C9 | F22: ='Valuation output'!D9 | G22: ='Valuation output'!E9 | H22: ='Valuation output'!F9 | I22: ='Valuation output'!G9 | J22: ='Valuation output'!H9 | K22: ='Valuation output'!I9 | L22: ='Valuation output'!J9 | ... O22: ='Valuation output'!M9
A23: ='Valuation output'!A29 | B23: ='Valuation output'!B29 | N23: ='Valuation output'!B18
A24: ='Valuation output'!A30 | B24: ='Valuation output'!B30
A25: ='Valuation output'!A31 | B25: ='Valuation output'!B31 | D25: Cost of Capital | E25: ='Valuation output'!C12 | F25: ='Valuation output'!D12 | G25: ='Valuation output'!E12 | H25: ='Valuation output'!F12 | I25: ='Valuation output'!G12 | J25: ='Valuation output'!H12 | K25: ='Valuation output'!I12 | L25: ='Valuation output'!J12 | ... N25: ='Valuation output'!L12
A26: ='Valuation output'!A32 | B26: ='Valuation output'!B32 | D26: Cumulated WACC | E26: ='Valuation output'!C13 | F26: ='Valuation output'!D13 | G26: ='Valuation output'!E13 | H26: ='Valuation output'!F13 | I26: ='Valuation output'!G13 | J26: ='Valuation output'!H13 | K26: ='Valuation output'!I13 | L26: ='Valuation output'!J13 | ... N26: ='Valuation output'!L13
A27: ='Valuation output'!A33 | B27: ='Valuation output'!B33
D28: Sales to Capital | E28: ='Valuation output'!C38 | F28: ='Valuation output'!D38 | G28: ='Valuation output'!E38 | H28: ='Valuation output'!F38 | I28: ='Valuation output'!G38 | J28: ='Valuation output'!H38 | K28: ='Valuation output'!I38 | L28: ='Valuation output'!J38 | ... N28: ='Valuation output'!L38
A29: Price per share | B29: ='Stories to Numbers'!G39 | D29: ROIC | E29: ='Valuation output'!C40 | F29: ='Valuation output'!D40 | G29: ='Valuation output'!E40 | H29: ='Valuation output'!F40 | I29: ='Valuation output'!G40 | J29: ='Valuation output'!H40 | K29: ='Valuation output'!I40 | L29: ='Valuation output'!J40 | ... O29: ='Valuation output'!M40
A30: % Under or Over Valued | B30: =B29/B27-1
D32: Risk Story | G32: Competitive Advantages
D33: ='Stories to Numbers'!G14 | G33: ='Stories to Numbers'!G13

Sheet Diagnostics
A1: Step 1: Check revenue growth rate | D1: Your forecasts | G1: Questions to ask
B2: Industry Average | C2: Most Recent year | D2: Next year | E2: Years 2-5 | G2: 1. If you are forecasting a revenue growth rate > industry average, is your company small?
A3: Annual Revenue Growth Rate | B3: ='Input sheet'!J25 | C3: ='Input sheet'!I25 | D3: ='Valuation output'!C2 | E3: ='Valuation output'!D2 | G3: 2. If your forecasted revenue growth rate is very different from your company's most recent year of growth, what is the reason?
A5: Step 2: Check dollar revenues
B6: Most Recent year | C6: Next year | D6: Year 5 | E6: Year 10 | G6: 1. How big is the total market today?
A7: Revenues | B7: ='Valuation output'!B3 | C7: ='Valuation output'!C3 | D7: ='Valuation output'!G3 | E7: ='Valuation output'!L3 | G7: 2. How much revenues do the biggest companies in that market make today?
G8: 3. How much growth is there in the total market?
G9: 4. What type of market share are you forecasting for your company in year 10?
A11: Step 3: Check your margins | B11: Most Recent year | C11: Next year | D11: Year 5 | E11: Year 10 | G11: 1. What are the margins of the industry that the company is in?
A12: Operating Margin | B12: ='Valuation output'!B4 | C12: ='Valuation output'!C4 | D12: ='Valuation output'!G4 | E12: ='Valuation output'!M4 | G12: 2. What are the unit economics of the business? (How much does it cost you to make the extra unit that you sell?
G13: 3. What does the competition in this business look like?
A15: Step 4: Check how much you are reinvesting
B16: Most Recent year | C16: Next year | D16: Year 5 | E16: Year 10 | G16: 1. is the growth that you are forecasting bounce-back growth or new growth?
A17: Sales to Capital | B17: ='Input sheet'!I27 | C17: ='Valuation output'!C38 | D17: ='Valuation output'!G38 | E17: ='Valuation output'!L38 | G17: 2. How much excess capacity do you have to service near term growth?
G18: 3. Does investment efficiency in this business change as companies get bigger?
A19: Reinvestment effect on cash flows
B20: $ Value | C20: As % of value
A21: PV of after-tax operating income for next 10 yearas | B21: ='Valuation output'!C7*'Valuation output'!C13+'Valuation output'!D7*'Valuation output'!D13+'Valuation output'!E7*'Valuation output'!E13+'Valuation output'!F7*'Valuation output'!F13+'Valuation output'!G7*'Valuation output'!G13+'Valuation output'!H7*'Valuation output'!H13+'Valuation output'!I7*'Valuation output'!I13+'Valuation output'!J7*'Valuation output'!J13+'Valuation output'!K7*'Valuation output'!K13+'Valuation output'!L7*'Valuation output'!L13 | C21: =B21/B21 | G21: 1. Is your reinvestment consitent with your revenue growth forecast?
A22: Value effect of reinvestment for next 10 years | B22: =B21-B23 | C22: =B22/B21 | G22: 2. Are you comfortable with your return on capital in year 10?
A23: PV of FCFF for next ten years | B23: ='Valuation output'!B20 | C23: =C21-C22
A25: Return on capital effects
B26: Most recent year | C26: Marginal (1-10) | D26: ROC in year 10 | E26: Stable ROC
A27: Return on capital | B27: ='Valuation output'!B40 | C27: =('Valuation output'!L7-'Valuation output'!B7)/('Valuation output'!L39-'Valuation output'!B39) | D27: ='Valuation output'!L40 | E27: ='Valuation output'!M40
A29: Step 5: Risk Metrics
B30: Industry Average | C30: Compounded | D30: Year 1-5 | E30: Stable Growth | G30: 1. How does your cost of capital compare to the industry average?
A31: Cost of capital | B31: ='Input sheet'!J31 | C31: =(1/'Valuation output'!L13)^(1/10)-1 | D31: ='Valuation output'!C12 | E31: ='Valuation output'!M12 | G31: 2. What is happenign to your cost of capital over time? Why?
G32: 3. Is your failure rate consistent with your company's characteristics?
A33: Failure Rate | B33: ='Valuation output'!B22
A35: Step 6: Price versus Value
A36: Your calculated value as a percent of current price | B36: ='Valuation output'!B33/'Valuation output'!B34
B37: =IF(B36="NA","Value is negative. See below",IF(B36>2,"Value seems high. See below",IF(B36<0.5,"Value seems low. See below"," ")))
A38: Inputs | B38: If calculated value is negative or looks too low | C38: If calculated value looks too high
A39: Revenue growth rate (input cell B25, B27) | B39: Increase revenue growth rate | C39: Decrease revenue growth rate
A40: Operating margin (B26, B28) | B40: Increase the target pre-tax operating margin | C40: Decrease the target pre-tax operating margin
A41: Sales to Capital (B30-B32) | B41: Increase the sales/capital ratio | C41: Decrease the sales/capital ratio
A42: Return on capital in perpetuity (B48, B49) | B42: Increase relative to your cost of capital | C42: If higher than your cost of capital, lower towards your cost of capital | D42: T

Sheet Option value
A1: Note: This worksheet is the most finicky of all of the worksheets in this spreadsheet. If you start to get errors, here is a quick fix. Go into cell B12 and replace the contents with a number (say 5), and then undo your action. The spreadsheet will fix itself magically.
A3: Valuing Options or Warrants
A4: Enter the current stock price = | B4: ='Input sheet'!B22
A5: Enter the strike price on the option = | B5: ='Input sheet'!B39
A6: Enter the expiration of the option = | B6: ='Input sheet'!B40
A7: Enter the standard deviation in stock prices = | B7: ='Input sheet'!B41 | C7: (volatility)
A8: Enter the annualized dividend yield on stock = | B8: 0
A9: Enter the treasury bond rate = | B9: ='Input sheet'!B34
A10: Enter the number of warrants (options) outstanding = | B10: ='Input sheet'!B38
A11: Enter the number of shares outstanding = | B11: ='Input sheet'!B21
A13: Do not input any numbers below this line
A14: Dilution-adjusted Black-Scholes
A15: Stock Price= | B15: =B4 | C15: # Warrants issued= | D15: =B10
A16: Strike Price= | B16: =B5 | C16: # Shares outstanding= | D16: =B11
A17: Adjusted S = | B17: =(B15*D16+B28*D15)/(D16+D15) | C17: T.Bond rate= | D17: =B9
A18: Adjusted K = | B18: =B16 | C18: Variance= | D18: =B7^2
A19: Expiration (in years) = | B19: =B6 | C19: Annualized dividend yield= | D19: =B8
C20: Div. Adj. interest rate= | D20: =D17-D19
A22: d1 = | B22: =(LN(B17/B18)+(D20+(D18/2))*B19)/(((D18)^(0.5))*(B19^0.5))
A23: N (d1) = | B23: =NORMSDIST(B22)
A25: d2 = | B25: =B22-((D18^0.5)*(B19^(0.5)))
A26: N (d2) = | B26: =NORMSDIST(B25)
A28: Value per option = | B28: =((EXP((0-D19)*B19))*B17*B23-B18*(EXP((0-D17)*B19))*B26)
A29: Value of all options outstanding = | B29: =B28*B10

Sheet Synthetic rating
A1: If you have negative operating income, this spreadsheet will offer you a D rating. Do not use that rating as your cost of debt for a going concern. Insread give your company a low, but going concern rating like BB and use that cost of debt.
A4: Inputs for synthetic rating estimation
A5: Please read the special cases worksheet (see below) before you use this spreadsheet.
A6: Before you use this spreadsheet, make sure that the iteration box (under calculation options in excel) is checked.
A7: Enter the type of firm = | C7: ='Cost of capital worksheet'!B36
A8: Enter current Earnings before interest and taxes (EBIT) = | F8: =IF('Input sheet'!B17="Yes",'Input sheet'!B12+'Operating lease converter'!F32,'Input sheet'!B12) | G8: (Add back only long term interest expense for financial firms)
A9: Enter current interest expenses = | F9: =IF('Input sheet'!B17="Yes",'Cost of capital worksheet'!B31+'Operating lease converter'!C28*'Operating lease converter'!C15,'Cost of capital worksheet'!B31) | G9: (Use only long term interest expense for financial firms)
A10: Enter long term risk free rate = | F10: ='Input sheet'!B34
A11: Output
A12: Interest coverage ratio = | D12: =IF(F9=0,1000000,IF(F8<0,-100000,F8/F9))
A13: Estimated Bond Rating = | D13: =IF(C7=1,VLOOKUP(D12,A22:D36,3),(IF(C7=2,VLOOKUP(D12,A41:D55,3),VLOOKUP(D12,F22:I36,3)))) | F13: Note: If you get REF! All over the place, set the operating lease commitment question in cell F5
A14: Estimated Company Default Spread = | D14: =IF(C7=1,VLOOKUP(D12,A22:D36,4),(IF(C7=2,VLOOKUP(D12,A41:D55,4),VLOOKUP(D12,F22:I36,4)))) | F14: to No, and then reset it to Yes. It should work.
A15: Estimated County Default Spread (if any) = | D15: =VLOOKUP('Input sheet'!B7,'Country equity risk premiums'!A5:C196,3)
A16: Estimated Cost of Debt = | D16: =F10+D14+D15
A18: If you want to update the spreads listed below, please visit http://www.bondsonline.com
A19: For large manufacturing firms | J19: Default Probabilities over time (1 - 10 year time horizons)
A20: If interest coverage ratio is | J20: Rating | K20: 1 | L20: 2 | M20: 3 | N20: 4 | O20: 5 | P20: 6 | Q20: 7 | R20: 8 | S20: 9 | T20: 10
A21: > | B21: ≤ to | C21: Rating is | D21: Spread is | J21: AAA | K21: 0 | L21: 0.0003 | M21: 0.0013 | N21: 0.0024 | O21: 0.0035 | P21: 0.0045 | Q21: 0.0051 | R21: 0.0059 | S21: 0.0064 | T21: 0.007
A22: -100000 | B22: 0.199999 | C22: D2/D | D22: 0.19 | J22: AA | K22: 0.0002 | L22: 0.0006 | M22: 0.0012 | N22: 0.0021 | O22: 0.0031 | P22: 0.0042 | Q22: 0.005 | R22: 0.0058 | S22: 0.0065 | T22: 0.0072
A23: 0.2 | B23: 0.649999 | C23: C2/C | D23: 0.16 | J23: A | K23: 0.0005 | L23: 0.0014 | M23: 0.0023 | N23: 0.0035 | O23: 0.0047 | P23: 0.0062 | Q23: 0.0079 | R23: 0.0093 | S23: 0.0108 | T23: 0.0124
A24: 0.65 | B24: 0.799999 | C24: Ca2/CC | D24: 0.126101 | J24: BBB | K24: 0.0016 | L24: 0.0045 | M24: 0.0078 | N24: 0.0117 | O24: 0.0158 | P24: 0.0198 | Q24: 0.0233 | R24: 0.0267 | S24: 0.03 | T24: 0.0332
A25: 0.8 | B25: 1.249999 | C25: Caa/CCC | D25: 0.0885 | J25: BB | K25: 0.0061 | L25: 0.0192 | M25: 0.0348 | N25: 0.0505 | O25: 0.0652 | P25: 0.0785 | Q25: 0.0901 | R25: 0.1004 | S25: 0.1097 | T25: 0.1178
A26: 1.25 | B26: 1.499999 | C26: B3/B- | D26: 0.050899 | J26: B | K26: 0.0333 | L26: 0.0771 | M26: 0.1155 | N26: 0.1458 | O26: 0.1693 | P26: 0.1883 | Q26: 0.2036 | R26: 0.216 | S26: 0.227 | T26: 0.2374
A27: 1.5 | B27: 1.749999 | C27: B2/B | D27: 0.032098 | J27: CCC/C | K27: 0.2708 | L27: 0.3664 | M27: 0.4141 | N27: 0.441 | O27: 0.4619 | P27: 0.4709 | Q27: 0.4826 | R27: 0.4905 | S27: 0.4976 | T27: 0.5038
A28: 1.75 | B28: 1.999999 | C28: B1/B+ | D28: 0.027531
A29: 2 | B29: 2.2499999 | C29: Ba2/BB | D29: 0.018395
A30: 2.25 | B30: 2.49999 | C30: Ba1/BB+ | D30: 0.013828
A31: 2.5 | B31: 2.999999 | C31: Baa2/BBB | D31: 0.011113
A32: 3 | B32: 4.249999 | C32: A3/A- | D32: 0.008872
A33: 4.25 | B33: 5.499999 | C33: A2/A | D33: 0.007751
A34: 5.5 | B34: 6.499999 | C34: A1/A+ | D34: 0.007003
A35: 6.5 | B35: 8.499999 | C35: Aa2/AA | D35: 0.005506
A36: 8.5 | B36: 100000 | C36: Aaa/AAA | D36: 0.004
A38: For smaller and riskier firms
A39: If interest coverage ratio is
A40: greater than | B40: ≤ to | C40: Rating is | D40: Spread is
A41: -100000 | B41: 0.499999 | C41: D2/D | D41: 0.19 | G41: Rating is | H41: Spread is
A42: 0.5 | B42: 0.799999 | C42: C2/C | D42: 0.16 | G42: A1/A+ | H42: 0.007003
A43: 0.8 | B43: 1.249999 | C43: Ca2/CC | D43: 0.126101 | G43: A2/A | H43: 0.007751
A44: 1.25 | B44: 1.499999 | C44: Caa/CCC | D44: 0.0885 | G44: A3/A- | H44: 0.008872
A45: 1.5 | B45: 1.999999 | C45: B3/B- | D45: 0.050899 | G45: Aa2/AA | H45: 0.005506
A46: 2 | B46: 2.499999 | C46: B2/B | D46: 0.032098 | G46: Aaa/AAA | H46: 0.004
A47: 2.5 | B47: 2.999999 | C47: B1/B+ | D47: 0.027531 | G47: B1/B+ | H47: 0.027531
A48: 3 | B48: 3.499999 | C48: Ba2/BB | D48: 0.018395 | G48: B2/B | H48: 0.032098
A49: 3.5 | B49: 3.9999999 | C49: Ba1/BB+ | D49: 0.013828 | G49: B3/B- | H49: 0.050899
A50: 4 | B50: 4.499999 | C50: Baa2/BBB | D50: 0.011113 | G50: Ba1/BB+ | H50: 0.013828
A51: 4.5 | B51: 5.999999 | C51: A3/A- | D51: 0.008872 | G51: Ba2/BB | H51: 0.018395
A52: 6 | B52: 7.499999 | C52: A2/A | D52: 0.007751 | G52: Baa2/BBB | H52: 0.011113
A53: 7.5 | B53: 9.499999 | C53: A1/A+ | D53: 0.007003 | G53: C2/C | H53: 0.16
... A55: 12.5 | B55: 100000 | C55: Aaa/AAA | D55: 0.004 | G55: Caa/CCC | H55: 0.0885
G56: D2/D | H56: 0.19

Sheet R& D converter
A1: R & D Converter
A2: This spreadsheet converts R&D expenses from operating to capital expenses. It makes the appropriate adjustments to operating income, net
A3: income, the book value of assets and the book value of equity.
A5: Inputs
A6: Over how many years do you want to amortize R&D expenses | F6: 3 | G6: ! If in doubt, use the lookup table below
A7: Enter the current year's R&D expense = | F7: 85622 | G7: The maximum allowed is ten years
A8: Enter R& D expenses for past years: the number of years that you will need to enter will be determined by the amortization period
A9: Do not input numbers in the first column (Year). It will get automatically updated based on the input above.
A10: Year | B10: R& D Expenses
A11: -1 | B11: 73213 | C11: ! Year -1 is the year prior to the most recent 12 months
A12: =IF((0-A11)<$F$6,IF(A11>-1,,A11-1),) | B12: 56052 | C12: ! Year -2 is the two years prior to the most recent 12 months
A13: =IF((0-A12)<$F$6,IF(A12>-1,,A12-1),) | B13: 42740
A14: =IF((0-A13)<$F$6,IF(A13>-1,,A13-1),)
A15: =IF((0-A14)<$F$6,IF(A14>-1,,A14-1),)
A16: =IF((0-A15)<$F$6,IF(A15>-1,,A15-1),)
A17: =IF((0-A16)<$F$6,IF(A16>-1,,A16-1),)
A18: =IF((0-A17)<$F$6,IF(A17>-1,,A17-1),)
A19: =IF((0-A18)<$F$6,IF(A18>-1,,A18-1),)
A20: =IF((0-A19)<$F$6,IF(A19>-1,,A19-1),)
A22: Output
A23: Year | B23: R&D Expense | C23: Unamortized portion | E23: Amortization this year
A24: Current | B24: =F7 | C24: =1 | D24: =B24*C24
A25: =A11 | B25: =B11 | C25: =IF(A25<0,($F$6+A25)/$F$6,0) | D25: =B25*C25 | E25: =IF(A25<0,B25/$F$6,0)
A26: =A12 | B26: =B12 | C26: =IF(A26<0,($F$6+A26)/$F$6,0) | D26: =B26*C26 | E26: =IF(A26<0,B26/$F$6,0)
A27: =A13 | B27: =B13 | C27: =IF(A27<0,($F$6+A27)/$F$6,0) | D27: =B27*C27 | E27: =IF(A27<0,B27/$F$6,0)
A28: =A14 | B28: =B14 | C28: =IF(A28<0,($F$6+A28)/$F$6,0) | D28: =B28*C28 | E28: =IF(A28<0,B28/$F$6,0)
A29: =A15 | B29: =B15 | C29: =IF(A29<0,($F$6+A29)/$F$6,0) | D29: =B29*C29 | E29: =IF(A29<0,B29/$F$6,0)
A30: =A16 | B30: =B16 | C30: =IF(A30<0,($F$6+A30)/$F$6,0) | D30: =B30*C30 | E30: =IF(A30<0,B30/$F$6,0)
A31: =A17 | B31: =B17 | C31: =IF(A31<0,($F$6+A31)/$F$6,0) | D31: =B31*C31 | E31: =IF(A31<0,B31/$F$6,0)
A32: =A18 | B32: =B18 | C32: =IF(A32<0,($F$6+A32)/$F$6,0) | D32: =B32*C32 | E32: =IF(A32<0,B32/$F$6,0)
A33: =A19 | B33: =B19 | C33: =IF(A33<0,($F$6+A33)/$F$6,0) | D33: =B33*C33 | E33: =IF(A33<0,B33/$F$6,0)
A34: =A20 | B34: =B20 | C34: =IF(A34<0,($F$6+A34)/$F$6,0) | D34: =B34*C34 | E34: =IF(A34<0,B34/$F$6,0)
A35: Value of Research Asset = | D35: =SUM(D24:D34) | E35: =SUM(E25:E34)
A37: Amortization of asset for current year = | D37: =E35
A39: Adjustment to Operating Income = | D39: =F7-D37 | E39: ! A positive number indicates an increase in operating income (add to reported EBIT)
A40: Tax Effect of R&D Expensing | D40: =D39*'Input sheet'!B24
A42: Lookup Table for Amortizable Lives
A43: Industry Name | B43: Amortization Period
A44: Advertising | B44: 2
A45: Aerospace/Defense | B45: 10
A46: Air Transport | B46: 10
A47: Aluminum | B47: 5
A48: Apparel | B48: 3
A49: Auto & Truck | B49: 10
A50: Auto Parts (OEM) | B50: 5
A51: Auto Parts (Replacement) | B51: 5
A52: Bank | B52: 2
A53: Bank (Canadian) | B53: 2
A54: Bank (Foreign) | B54: 2
A55: Bank (Midwest) | B55: 2
... A141: Water Utility | B141: 10

Sheet Operating lease converter
A1: Operating Lease Converter
A2: The yellow cells are input cells. Please enter them.
A3: Inputs | H3: Until 2019, this worksheet had to be used for every firm with operating lease commitments, since accountants treated operating lease expenses as operating expenses. In 2019, IFRS and GAAP made the long-overdue change to treat leases as debt, and for firms that follow these standards, the conversion that I am doing on this spreadsheet is being done by accountants, with lease debt and operating income already adjusted. If that is the case, and you showed the lease debt as part of debt in the input page, please do not use this spreadsheet, since you will be double counting.
A4: Operating lease expense in current year = | E4: 295
A5: Operating Lease Commitments (From footnote to financials)
A6: Year | B6: Commitment | C6: ! Year 1 is next year, ….
A7: 1 | B7: 287
A8: 2 | B8: 235
A9: 3 | B9: 194
A10: 4 | B10: 151
A11: 5 | B11: 98
A12: 6 and beyond | B12: 605
A14: Output
A15: Pre-tax Cost of Debt = | C15: ='Cost of capital worksheet'!B37 | D15: ! If you do not have a cost of debt, use the synthetic rating estimator
A18: Number of years embedded in yr 6 estimate = | D18: =IF(B12>0,ROUND(B12/AVERAGE(B7:B11),0),0) | E18: ! I use the average lease expense over the first five years
E19: to estimate the number of years of expenses in yr 6
A20: Converting Operating Leases into debt
A21: Year | B21: Commitment | C21: Present Value
A22: =A7 | B22: =B7 | C22: =B22/(1+$C$15)^A22
A23: =A8 | B23: =B8 | C23: =B23/(1+$C$15)^A23
A24: =A9 | B24: =B9 | C24: =B24/(1+$C$15)^A24
A25: =A10 | B25: =B10 | C25: =B25/(1+$C$15)^A25
A26: =A11 | B26: =B11 | C26: =B26/(1+$C$15)^A26
A27: =A12 | B27: =IF(B12>0,IF(D18>0,B12/D18,B12),0) | C27: =IF(D18>0,(B27*(1-(1+C15)^(-D18))/C15)/(1+$C$15)^5,B27/(1+C15)^6) | D27: ! Commitment beyond year 6 converted into an annuity for ten years
A28: Debt Value of leases = | C28: =SUM(C22:C27)
A30: Restated Financials
A31: Depreciation on Operating Lease Asset = | F31: =C28/(5+D18) | G31: ! I use straight line depreciation
A32: Adjustment to Operating Earnings = | F32: =E4-F31 | G32: ! Add this amount to pre-tax operating income
A33: Adjustment to Total Debt outstanding = | F33: =C28 | G33: ! Add this amount to debt
A34: Adjustment to Depreciation = | F34: =C28/(5+D18)

Sheet Cost of capital worksheet
A1: You can use this spreadsheet to compute your cost of capital. You can either use the built-in data to compute key inputs (beta, equity risk premium, default spread) or enter them directly. If you choose to use the built in ERP data, you can update the ERP numbers to reflect a more current mature market premuum (since the spreadsheet uses the start of the year numbers).
A3: Estimation of Current Cost of Capital | G3: Operating Countries ERP calculator
A4: There are four ways in whch you can estimate your cost of capital. In the first, you can directly input a cost of captial. In the second, you can work through your company's cost of capital inputs in detail, entering business, geogaphical mix and debt, and I will help you estimate a cost of capital. In the third, you can look up the cost of capital for the industry or industries your firm belongs to and in the fourth, you can use a crosssectional distribution of costs of capital for companies at the start of the year to make your estimate. | G4: Country | H4: Revenues | I4: ERP | J4: Weight | K4: Weighted ERP
G5: United States | H5: 193636 | I5: =IF(H5=0,0,VLOOKUP(G5,'Country equity risk premiums'!$A$5:$D$196,4)) | J5: =IF(H5>0,H5/$H$18,) | K5: =IF(J5=0,0,I5*J5) | M5: The last two rows in each of country/region risk premium tables is set aside for your input to provide you with flexibility to enter some numbers directly. For instance, assume that you have a company that breaks its revenues down into three countries and then puts the rest into "Rest of the World". You can enter the "Rest of the World" in one of these two rows and enter an equity risk premium for the rest of the world. The easiest way to do that is to go into the country equity risk premium worksheet and change the GDP for the three countries that you have data for to zero and compute the global weighted average ERP for the remaining countries. With the regional worksheet, you can use the last two rows to enter the data for an individual country (usually the domestic country) that might be broken out though the rest of the revenues are broken down by region. You can look up the ERP for the country in the country ERP worksheet.
G6: China | H6: 500 | I6: =IF(H6=0,0,VLOOKUP(G6,'Country equity risk premiums'!$A$5:$D$196,4)) | J6: =IF(H6>0,H6/$H$18,) | K6: =IF(J6=0,0,I6*J6)
I7: =IF(H7=0,0,VLOOKUP(G7,'Country equity risk premiums'!$A$5:$D$196,4)) | J7: =IF(H7>0,H7/$H$18,) | K7: =IF(J7=0,0,I7*J7)
I8: =IF(H8=0,0,VLOOKUP(G8,'Country equity risk premiums'!$A$5:$D$196,4)) | J8: =IF(H8>0,H8/$H$18,) | K8: =IF(J8=0,0,I8*J8)
I9: =IF(H9=0,0,VLOOKUP(G9,'Country equity risk premiums'!$A$5:$D$196,4)) | J9: =IF(H9>0,H9/$H$18,) | K9: =IF(J9=0,0,I9*J9)
I10: =IF(H10=0,0,VLOOKUP(G10,'Country equity risk premiums'!$A$5:$D$196,4)) | J10: =IF(H10>0,H10/$H$18,) | K10: =IF(J10=0,0,I10*J10)
A11: Which approach will you be using? | B11: Detailed | I11: =IF(H11=0,0,VLOOKUP(G11,'Country equity risk premiums'!$A$5:$D$196,4)) | J11: =IF(H11>0,H11/$H$18,) | K11: =IF(J11=0,0,I11*J11)
A12: If direct input, enter cost of capital to use | B12: 0.09 | I12: =IF(H12=0,0,VLOOKUP(G12,'Country equity risk premiums'!$A$5:$D$196,4)) | J12: =IF(H12>0,H12/$H$18,) | K12: =IF(J12=0,0,I12*J12)
A13: Cost of capital based upon approach = | B13: =IF(B11="I will input",B12,IF(B11="Detailed",E62,IF(B11="Industry Average",B67,B72))) | I13: =IF(H13=0,0,VLOOKUP(G13,'Country equity risk premiums'!$A$5:$D$196,4)) | J13: =IF(H13>0,H13/$H$18,) | K13: =IF(J13=0,0,I13*J13)
I14: =IF(H14=0,0,VLOOKUP(G14,'Country equity risk premiums'!$A$5:$D$196,4)) | J14: =IF(H14>0,H14/$H$18,) | K14: =IF(J14=0,0,I14*J14)
A15: Approach 1: Detailed Cost of Capital | I15: =IF(H15=0,0,VLOOKUP(G15,'Country equity risk premiums'!$A$5:$D$196,4)) | J15: =IF(H15>0,H15/$H$18,) | K15: =IF(J15=0,0,I15*J15)
A16: Inputs | G16: Rest of the World | H16: 31335 | I16: 0.0641 | J16: =IF(H16>0,H16/$H$18,) | K16: =IF(J16=0,0,I16*J16)
A17: Equity | J17: =IF(H17>0,H17/$H$18,) | K17: =IF(J17=0,0,I17*J17)
A18: Number of Shares outstanding = | B18: ='Input sheet'!B21 | G18: Total | H18: =SUM(H5:H17) | J18: =SUM(J5:J17) | K18: =SUM(K5:K17)
A19: Current Market Price per share = | B19: ='Input sheet'!B22 | G19: Operating Regions ERP calculator
G20: Region | H20: Revenues | I20: ERP | J20: Weight | K20: Weighted ERP
A21: Approach for estimating beta | B21: Single Business(US) | G21: ='Country equity risk premiums'!A201 | I21: ='Country equity risk premiums'!B201 | J21: =H21/$H$32 | K21: =I21*J21
A22: If direct input, enter levered beta (or regression beta) | B22: 1.2 | G22: ='Country equity risk premiums'!A202 | H22: 5455 | I22: ='Country equity risk premiums'!B202 | J22: =H22/$H$32 | K22: =I22*J22
A23: Unlevered beta = | B23: =IF(B21="Single Business(US)",VLOOKUP('Input sheet'!B8,'Industry Averages(US)'!A2:G95,7),IF(B21="Multibusiness(US)",K48,IF(B21="Single Business(Global)",VLOOKUP('Input sheet'!B9,'Industry Averages (Global)'!A2:G95,7),'Cost of capital worksheet'!K64))) | G23: ='Country equity risk premiums'!A203 | I23: ='Country equity risk premiums'!B203 | J23: =H23/$H$32 | K23: =I23*J23
A24: Riskfree Rate = | B24: ='Input sheet'!B34 | G24: ='Country equity risk premiums'!A204 | I24: ='Country equity risk premiums'!B204 | J24: =H24/$H$32 | K24: =I24*J24
A25: What approach do you want to use to input ERP? | B25: Will Input | G25: ='Country equity risk premiums'!A205 | H25: 5830 | I25: ='Country equity risk premiums'!B205 | J25: =H25/$H$32 | K25: =I25*J25
A26: Direct input for ERP (if you choose "will input" | B26: 0.05 | G26: ='Country equity risk premiums'!A206 | I26: ='Country equity risk premiums'!B206 | J26: =H26/$H$32 | K26: =I26*J26
A27: Equity Risk Premium used in cost of equity = | B27: =IF(B25="Will Input",B26,IF(B25="Country of Incorporation",VLOOKUP('Input sheet'!B7,'Country equity risk premiums'!A5:E195,4),IF(B25="Operating regions",'Cost of capital worksheet'!K32,'Cost of capital worksheet'!K18))) | G27: ='Country equity risk premiums'!A207 | I27: ='Country equity risk premiums'!B207 | J27: =H27/$H$32 | K27: =I27*J27
G28: ='Country equity risk premiums'!A208 | H28: 16774 | I28: ='Country equity risk premiums'!B208 | J28: =H28/$H$32 | K28: =I28*J28
A29: Debt | G29: ='Country equity risk premiums'!A209 | I29: ='Country equity risk premiums'!B209 | J29: =H29/$H$32 | K29: =I29*J29
A30: Book Value of Straight Debt = | B30: ='Input sheet'!B15 | G30: EMEA | H30: 8078 | I30: 0.0587 | J30: =H30/$H$32 | K30: =I30*J30
A31: Interest Expense on Debt = | B31: ='Input sheet'!B13 | G31: Rest of the World | H31: 10924 | I31: 0.055 | J31: =H31/$H$32 | K31: =I31*J31
A32: Average Maturity = | B32: 3 | G32: Total | H32: =SUM(H21:H31) | J32: =SUM(J21:J31) | K32: =SUM(K21:K31)
A33: Approach for estimating pre-tax cost of debt | B33: Actual rating
A34: If direct input, input the pre-tax cost of debt | B34: 0.04 | G34: Multi Business (US Industry Averages)
A35: If actual rating, input the rating | B35: Aaa/AAA | G35: Business | H35: Revenues | I35: EV/Sales | J35: Estimated Value | K35: Unlevered Beta | L35: Cost of capital
A36: If synethetic rating, input the type of company | B36: 2 | G36: Computers/Peripherals | H36: 195010 | I36: =IF(G36=0,,VLOOKUP(G36,'Industry Averages(US)'!$A$2:$S$95,15)) | J36: =H36*I36 | K36: =IF(I36=0,0,VLOOKUP(G36,'Industry Averages(US)'!$A$2:$S$95,7)) | L36: =IF(I36=0,0,VLOOKUP(G36,'Industry Averages(US)'!$A$2:$S$95,13))
A37: Pre-tax Cost of Debt = | B37: =IF(B33="Direct Input",B34,IF(B33="Synthetic Rating",'Synthetic rating'!D16,B24+VLOOKUP('Cost of capital worksheet'!B35,'Synthetic rating'!G42:H56,2))) | G37: Electronics (General) | H37: 43000 | I37: =IF(G37=0,,VLOOKUP(G37,'Industry Averages(US)'!$A$2:$S$95,15)) | J37: =H37*I37 | K37: =IF(I37=0,0,VLOOKUP(G37,'Industry Averages(US)'!$A$2:$S$95,7)) | L37: =IF(I37=0,0,VLOOKUP(G37,'Industry Averages(US)'!$A$2:$S$95,13))
A38: Tax Rate = | B38: ='Input sheet'!B24 | G38: Entertainment | H38: 15000 | I38: =IF(G38=0,,VLOOKUP(G38,'Industry Averages(US)'!$A$2:$S$95,15)) | J38: =H38*I38 | K38: =IF(I38=0,0,VLOOKUP(G38,'Industry Averages(US)'!$A$2:$S$95,7)) | L38: =IF(I38=0,0,VLOOKUP(G38,'Industry Averages(US)'!$A$2:$S$95,13))
I39: =IF(G39=0,,VLOOKUP(G39,'Industry Averages(US)'!$A$2:$S$95,15)) | J39: =H39*I39 | K39: =IF(I39=0,0,VLOOKUP(G39,'Industry Averages(US)'!$A$2:$S$95,7)) | L39: =IF(I39=0,0,VLOOKUP(G39,'Industry Averages(US)'!$A$2:$S$95,13))
A40: Book Value of Convertible Debt = | B40: 0 | I40: =IF(G40=0,,VLOOKUP(G40,'Industry Averages(US)'!$A$2:$S$95,15)) | J40: =H40*I40 | K40: =IF(I40=0,0,VLOOKUP(G40,'Industry Averages(US)'!$A$2:$S$95,7)) | L40: =IF(I40=0,0,VLOOKUP(G40,'Industry Averages(US)'!$A$2:$S$95,13))
A41: Interest Expense on Convertible = | B41: 0 | I41: =IF(G41=0,,VLOOKUP(G41,'Industry Averages(US)'!$A$2:$S$95,15)) | J41: =H41*I41 | K41: =IF(I41=0,0,VLOOKUP(G41,'Industry Averages(US)'!$A$2:$S$95,7)) | L41: =IF(I41=0,0,VLOOKUP(G41,'Industry Averages(US)'!$A$2:$S$95,13))
A42: Maturity of Convertible Bond = | B42: 0 | I42: =IF(G42=0,,VLOOKUP(G42,'Industry Averages(US)'!$A$2:$S$95,15)) | J42: =H42*I42 | K42: =IF(I42=0,0,VLOOKUP(G42,'Industry Averages(US)'!$A$2:$S$95,7)) | L42: =IF(I42=0,0,VLOOKUP(G42,'Industry Averages(US)'!$A$2:$S$95,13))
A43: Market Value of Convertible = | B43: 0 | I43: =IF(G43=0,,VLOOKUP(G43,'Industry Averages(US)'!$A$2:$S$95,15)) | J43: =H43*I43 | K43: =IF(I43=0,0,VLOOKUP(G43,'Industry Averages(US)'!$A$2:$S$95,7)) | L43: =IF(I43=0,0,VLOOKUP(G43,'Industry Averages(US)'!$A$2:$S$95,13))
I44: =IF(G44=0,,VLOOKUP(G44,'Industry Averages(US)'!$A$2:$S$95,15)) | J44: =H44*I44 | K44: =IF(I44=0,0,VLOOKUP(G44,'Industry Averages(US)'!$A$2:$S$95,7)) | L44: =IF(I44=0,0,VLOOKUP(G44,'Industry Averages(US)'!$A$2:$S$95,13)) | M44: The costt of capital is in US dollars, using the riskfree rate at the start of the year. It will be adjusted for the difference in riskfree rates to make it more current and to change currencies.
A45: Debt value of operating leases = | B45: =IF('Input sheet'!B17="Yes",'Operating lease converter'!F33,0) | I45: =IF(G45=0,,VLOOKUP(G45,'Industry Averages(US)'!$A$2:$S$95,15)) | J45: =H45*I45 | K45: =IF(I45=0,0,VLOOKUP(G45,'Industry Averages(US)'!$A$2:$S$95,7)) | L45: =IF(I45=0,0,VLOOKUP(G45,'Industry Averages(US)'!$A$2:$S$95,13))
I46: =IF(G46=0,,VLOOKUP(G46,'Industry Averages(US)'!$A$2:$S$95,15)) | J46: =H46*I46 | K46: =IF(I46=0,0,VLOOKUP(G46,'Industry Averages(US)'!$A$2:$S$95,7)) | L46: =IF(I46=0,0,VLOOKUP(G46,'Industry Averages(US)'!$A$2:$S$95,13))
A47: Preferred Stock | I47: =IF(G47=0,,VLOOKUP(G47,'Industry Averages(US)'!$A$2:$S$95,15)) | J47: =H47*I47 | K47: =IF(I47=0,0,VLOOKUP(G47,'Industry Averages(US)'!$A$2:$S$95,7)) | L47: =IF(I47=0,0,VLOOKUP(G47,'Industry Averages(US)'!$A$2:$S$95,13))
A48: Number of Preferred Shares = | B48: 0 | G48: Company | H48: =SUM(H36:H47) | J48: =SUM(J36:J47) | K48: =K36*(J36/J48)+K37*J37/J48+K38*J38/J48+K39*J39/J48+K40*J40/J48+K41*J41/J48+K42*J42/J48+K43*J43/J48+K44*J44/J48+K45*J45/J48+K46*J46/J48+K47*J47/J48 | L48: =L36*(J36/J48)+L37*J37/J48+L38*J38/J48+L39*J39/J48+L40*J40/J48+L41*J41/J48+L42*J42/J48+L43*J43/J48+L44*J44/J48+L45*J45/J48+L46*J46/J48+L47*J47/J48
A49: Current Market Price per Share= | B49: 70
A50: Annual Dividend per Share = | B50: 5 | G50: Multi Business (Global Industry Averages)
G51: Business | H51: Revenues | I51: EV/Sales | J51: Estimated Value | K51: Unlevered Beta | L51: Cost of capital
A52: Output | G52: Electronics (General) | H52: 81363 | I52: =IF(G52=0,,VLOOKUP(G52,'Industry Averages (Global)'!$A$2:$O$95,15)) | J52: =H52*I52 | K52: =IF(G52=0,,VLOOKUP(G52,'Industry Averages (Global)'!$A$2:$O$95,7)) | L52: =IF(I52=0,0,VLOOKUP(G52,'Industry Averages (Global)'!$A$2:$M$95,13))
A53: Estimating Market Value of Straight Debt = | C53: =B31*(1-(1+B37)^(-B32))/B37+B30/(1+B37)^B32 | I53: =IF(G53=0,,VLOOKUP(G53,'Industry Averages (Global)'!$A$2:$O$95,15)) | J53: =H53*I53 | K53: =IF(G53=0,,VLOOKUP(G53,'Industry Averages (Global)'!$A$2:$O$95,7)) | L53: =IF(I53=0,0,VLOOKUP(G53,'Industry Averages (Global)'!$A$2:$M$95,13))
A54: Estimated Value of Straight Debt in Convertible = | C54: =B41*(1-(1+B37)^(-B42))/B37+B40/(1+B37)^B42 | I54: =IF(G54=0,,VLOOKUP(G54,'Industry Averages (Global)'!$A$2:$O$95,15)) | J54: =H54*I54 | K54: =IF(G54=0,,VLOOKUP(G54,'Industry Averages (Global)'!$A$2:$O$95,7)) | L54: =IF(I54=0,0,VLOOKUP(G54,'Industry Averages (Global)'!$A$2:$M$95,13))
A55: Value of Debt in Operating leases = | C55: =B45 | I55: =IF(G55=0,,VLOOKUP(G55,'Industry Averages (Global)'!$A$2:$O$95,15)) | J55: =H55*I55 | K55: =IF(G55=0,,VLOOKUP(G55,'Industry Averages (Global)'!$A$2:$O$95,7)) | L55: =IF(I55=0,0,VLOOKUP(G55,'Industry Averages (Global)'!$A$2:$M$95,13))
A56: Estimated Value of Equity in Convertible = | C56: =B43-C54 | I56: =IF(G56=0,,VLOOKUP(G56,'Industry Averages (Global)'!$A$2:$O$95,15)) | J56: =H56*I56 | K56: =IF(G56=0,,VLOOKUP(G56,'Industry Averages (Global)'!$A$2:$O$95,7)) | L56: =IF(I56=0,0,VLOOKUP(G56,'Industry Averages (Global)'!$A$2:$M$95,13))
A57: Levered Beta for equity = | C57: =IF(B21="Direct Input",B22,B23*(1+(1-B38)*(C60/B60))) | I57: =IF(G57=0,,VLOOKUP(G57,'Industry Averages (Global)'!$A$2:$O$95,15)) | J57: =H57*I57 | K57: =IF(G57=0,,VLOOKUP(G57,'Industry Averages (Global)'!$A$2:$O$95,7)) | L57: =IF(I57=0,0,VLOOKUP(G57,'Industry Averages (Global)'!$A$2:$M$95,13))
I58: =IF(G58=0,,VLOOKUP(G58,'Industry Averages (Global)'!$A$2:$O$95,15)) | J58: =H58*I58 | K58: =IF(G58=0,,VLOOKUP(G58,'Industry Averages (Global)'!$A$2:$O$95,7)) | L58: =IF(I58=0,0,VLOOKUP(G58,'Industry Averages (Global)'!$A$2:$M$95,13))
B59: Equity | C59: Debt | D59: Preferred Stock | E59: Capital | I59: =IF(G59=0,,VLOOKUP(G59,'Industry Averages (Global)'!$A$2:$O$95,15)) | J59: =H59*I59 | K59: =IF(G59=0,,VLOOKUP(G59,'Industry Averages (Global)'!$A$2:$O$95,7)) | L59: =IF(I59=0,0,VLOOKUP(G59,'Industry Averages (Global)'!$A$2:$M$95,13))
A60: Market Value | B60: =B18*B19 | C60: =C53+C54+C55 | D60: =B48*B49 | E60: =SUM(B60:D60) | I60: =IF(G60=0,,VLOOKUP(G60,'Industry Averages (Global)'!$A$2:$O$95,15)) | J60: =H60*I60 | K60: =IF(G60=0,,VLOOKUP(G60,'Industry Averages (Global)'!$A$2:$O$95,7)) | L60: =IF(I60=0,0,VLOOKUP(G60,'Industry Averages (Global)'!$A$2:$M$95,13)) | M60: The cost of capital is in US dollars, using the riskfree rate at the start of the year. It will be adjusted for the difference in riskfree rates to make it more current and to change currencies.
A61: Weight in Cost of Capital | B61: =B60/$E$60 | C61: =C60/$E$60 | D61: =D60/$E$60 | E61: =SUM(B61:D61) | I61: =IF(G61=0,,VLOOKUP(G61,'Industry Averages (Global)'!$A$2:$O$95,15)) | J61: =H61*I61 | K61: =IF(G61=0,,VLOOKUP(G61,'Industry Averages (Global)'!$A$2:$O$95,7)) | L61: =IF(I61=0,0,VLOOKUP(G61,'Industry Averages (Global)'!$A$2:$M$95,13))
A62: Cost of Component | B62: =B24+C57*B27 | C62: =B37*(1-B38) | D62: =B50/B49 | E62: =B61*B62+C61*C62+D61*D62 | I62: =IF(G62=0,,VLOOKUP(G62,'Industry Averages (Global)'!$A$2:$O$95,15)) | J62: =H62*I62 | K62: =IF(G62=0,,VLOOKUP(G62,'Industry Averages (Global)'!$A$2:$O$95,7)) | L62: =IF(I62=0,0,VLOOKUP(G62,'Industry Averages (Global)'!$A$2:$M$95,13))
I63: =IF(G63=0,,VLOOKUP(G63,'Industry Averages (Global)'!$A$2:$O$95,15)) | J63: =H63*I63 | K63: =IF(G63=0,,VLOOKUP(G63,'Industry Averages (Global)'!$A$2:$O$95,7)) | L63: =IF(I63=0,0,VLOOKUP(G63,'Industry Averages (Global)'!$A$2:$M$95,13))
G64: Company | H64: =SUM(H52:H63) | J64: =SUM(J52:J63) | K64: =K52*(J52/J64)+K53*J53/J64+K54*J54/J64+K55*J55/J64+K56*J56/J64+K57*J57/J64+K58*J58/J64+K59*J59/J64+K60*J60/J64+K61*J61/J64+K62*J62/J64+K63*J63/J64 | L64: =L52*(J52/J64)+L53*J53/J64+L54*J54/J64+L55*J55/J64+L56*J56/J64+L57*J57/J64+L58*J58/J64+L59*J59/J64+L60*J60/J64+L61*J61/J64+L62*J62/J64+L63*J63/J64
A65: Approach 2: industry average cost of capital, adjusted for riskfre rate differences
A66: Industry | B66: Multibusiness(US)
A67: Cost of capital, adjusted for riskfree rate difference | B67: =IF(B66="Single Business(US)",(VLOOKUP('Input sheet'!B8,'Industry Averages(US)'!A2:M95,13)+('Input sheet'!B34-4.58%)),IF(B66="Multibusiness(US)",L48+('Input sheet'!B34-4.58%),IF(B66="Single Business(Global)",(VLOOKUP('Input sheet'!B8,'Industry Averages (Global)'!A2:M95,13)+('Input sheet'!B34-4.58%)),L64+('Input sheet'!B34-4.58%))))
A69: Approach 3: Uae histogram of costs of capital of all publicly traded firms
A70: Which grouping (US, Emerging Markets, Global) | B70: US
A71: Which risk grouping does your company fall in? | B71: Median
A72: Cost of capital based upon decile/group chosen | B72: =VLOOKUP(B70,A75:F79,IF(B71="First Decile",2,IF(B71="First Quartile",3,IF(B71="Median",4,IF(B71="Third Quartile",5,6)))))
A74: Region | B74: First Decile | C74: First Quartile | D74: Median | E74: Third Quartile | F74: Ninth Decile
A75: Emerging | B75: 0.066532333 | C75: 0.07628704 | D75: 0.08954341 | E75: 0.10692342 | F75: 0.12549414
A76: Europe | B76: 0.059919385 | C76: 0.068285774 | D76: 0.082225394 | E76: 0.095713877 | F76: 0.11024115
A77: Global | B77: 0.062822262 | C77: 0.072448826 | D77: 0.086508899 | E77: 0.10028731 | F77: 0.11663146
A78: Japan | B78: 0.062956794 | C78: 0.070738069 | D78: 0.082379348 | E78: 0.094346984 | F78: 0.1073197
A79: US | B79: 0.052600788 | C79: 0.064110341 | D79: 0.077903913 | E79: 0.091622586 | F79: 0.098770423
A80: These costs of capital are all in US dollars and reflect the US dollar riskfree rate at the start of the year. Once you make your choice, though, I will adjust the rate by the difference in riskfree rates, effectively converting currency and bringing it up to date.

Sheet Failure Rate worksheet
A1: Estimating the likelihood of failure
A2: Approach 1: Using a corporate bond rating
A4: Default Probabilities over time (1 - 10 year time horizons)
A5: Rating | B5: 1 | C5: 2 | D5: 3 | E5: 4 | F5: 5 | G5: 6 | H5: 7 | I5: 8 | J5: 9 | K5: 10
A6: AAA | B6: 0 | C6: 0.0003 | D6: 0.0013 | E6: 0.0024 | F6: 0.0035 | G6: 0.0045 | H6: 0.0051 | I6: 0.0059 | J6: 0.0064 | K6: 0.007
A7: AA | B7: 0.0002 | C7: 0.0006 | D7: 0.0012 | E7: 0.0021 | F7: 0.0031 | G7: 0.0042 | H7: 0.005 | I7: 0.0058 | J7: 0.0065 | K7: 0.0072
A8: A | B8: 0.0005 | C8: 0.0014 | D8: 0.0023 | E8: 0.0035 | F8: 0.0047 | G8: 0.0062 | H8: 0.0079 | I8: 0.0093 | J8: 0.0108 | K8: 0.0124
A9: BBB | B9: 0.0016 | C9: 0.0045 | D9: 0.0078 | E9: 0.0117 | F9: 0.0158 | G9: 0.0198 | H9: 0.0233 | I9: 0.0267 | J9: 0.03 | K9: 0.0332
A10: BB | B10: 0.0061 | C10: 0.0192 | D10: 0.0348 | E10: 0.0505 | F10: 0.0652 | G10: 0.0785 | H10: 0.0901 | I10: 0.1004 | J10: 0.1097 | K10: 0.1178
A11: B | B11: 0.0333 | C11: 0.0771 | D11: 0.1155 | E11: 0.1458 | F11: 0.1693 | G11: 0.1883 | H11: 0.2036 | I11: 0.216 | J11: 0.227 | K11: 0.2374
A12: CCC/C | B12: 0.2708 | C12: 0.3664 | D12: 0.4141 | E12: 0.441 | F12: 0.4619 | G12: 0.4709 | H12: 0.4826 | I12: 0.4905 | J12: 0.4976 | K12: 0.5038
A14: Thus, if you use the 10-year likelihood of failure, the chance of failure for a BB rated firm is 11.78%.
A16: Approach 2: Using corporate age (for young companies)
O17: Survial Rate Data from Bureau of Labor Statistics (2022)
C18: Agriculture | D18: Mining | E18: Utilities | F18: Construction | G18: Manufacturing | H18: Retail | I18: Transportation | J18: Information | K18: Health Care | L18: All Sectors | O18: Agriculture | P18: Mining | Q18: Utilities | R18: Construction | S18: Manufacturing | T18: Retail | U18: Transportation | V18: Information | W18: Health Care | X18: All Sectors
A19: Failure Rate given age | B19: 0 | C19: =1-O28 | D19: =1-P28 | E19: =1-Q28 | F19: =1-R28 | G19: =1-S28 | H19: =1-T28 | I19: =1-U28 | J19: =1-V28 | ... L19: =1-X28 | N19: 1 | O19: 0.823 | P19: 0.818 | Q19: 0.84 | R19: 0.743 | S19: 0.828 | T19: 0.831 | U19: 0.769 | V19: 0.752 | W19: 0.814 | X19: 0.783
B20: 1 | C20: =O19-O$28 | D20: =P19-P$28 | E20: =Q19-Q$28 | F20: =R19-R$28 | G20: =S19-S$28 | H20: =T19-T$28 | I20: =U19-U$28 | J20: =V19-V$28 | ... L20: =X19-X$28 | N20: 2 | O20: 0.748 | P20: 0.712 | Q20: 0.735 | R20: 0.598 | S20: 0.724 | T20: 0.724 | U20: 0.636 | V20: 0.627 | W20: 0.722 | X20: 0.662
B21: 2 | C21: =O20-O$28 | D21: =P20-P$28 | E21: =Q20-Q$28 | F21: =R20-R$28 | G21: =S20-S$28 | H21: =T20-T$28 | I21: =U20-U$28 | J21: =V20-V$28 | ... L21: =X20-X$28 | N21: 3 | O21: 0.661 | P21: 0.629 | Q21: 0.67 | R21: 0.456 | S21: 0.622 | T21: 0.631 | U21: 0.523 | V21: 0.533 | W21: 0.674 | X21: 0.566
B22: 3 | C22: =O21-O$28 | D22: =P21-P$28 | E22: =Q21-Q$28 | F22: =R21-R$28 | G22: =S21-S$28 | H22: =T21-T$28 | I22: =U21-U$28 | J22: =V21-V$28 | ... L22: =X21-X$28 | N22: 4 | O22: 0.612 | P22: 0.538 | Q22: 0.629 | R22: 0.371 | S22: 0.541 | T22: 0.565 | U22: 0.45 | V22: 0.464 | W22: 0.613 | X22: 0.498
B23: 4 | C23: =O22-O$28 | D23: =P22-P$28 | E23: =Q22-Q$28 | F23: =R22-R$28 | G23: =S22-S$28 | H23: =T22-T$28 | I23: =U22-U$28 | J23: =V22-V$28 | ... L23: =X22-X$28 | N23: 5 | O23: 0.574 | P23: 0.512 | Q23: 0.565 | R23: 0.332 | S23: 0.494 | T23: 0.521 | U23: 0.411 | V23: 0.419 | W23: 0.559 | X23: 0.454
B24: 5 | C24: =O23-O$28 | D24: =P23-P$28 | E24: =Q23-Q$28 | F24: =R23-R$28 | G24: =S23-S$28 | H24: =T23-T$28 | I24: =U23-U$28 | J24: =V23-V$28 | ... L24: =X23-X$28 | N24: 6 | O24: 0.541 | P24: 0.472 | Q24: 0.556 | R24: 0.306 | S24: 0.463 | T24: 0.485 | U24: 0.377 | V24: 0.372 | W24: 0.548 | X24: 0.423
B25: 6 | C25: =O24-O$28 | D25: =P24-P$28 | E25: =Q24-Q$28 | F25: =R24-R$28 | G25: =S24-S$28 | H25: =T24-T$28 | I25: =U24-U$28 | J25: =V24-V$28 | ... L25: =X24-X$28 | N25: 7 | O25: 0.516 | P25: 0.429 | Q25: 0.516 | R25: 0.284 | S25: 0.438 | T25: 0.457 | U25: 0.349 | V25: 0.34 | W25: 0.529 | X25: 0.396
B26: 7 | C26: =O25-O$28 | D26: =P25-P$28 | E26: =Q25-Q$28 | F26: =R25-R$28 | G26: =S25-S$28 | H26: =T25-T$28 | I26: =U25-U$28 | J26: =V25-V$28 | ... L26: =X25-X$28 | N26: 8 | O26: 0.495 | P26: 0.405 | Q26: 0.503 | R26: 0.271 | S26: 0.415 | T26: 0.433 | U26: 0.324 | V26: 0.314 | W26: 0.484 | X26: 0.371
B27: 8 | C27: =O26-O$28 | D27: =P26-P$28 | E27: =Q26-Q$28 | F27: =R26-R$28 | G27: =S26-S$28 | H27: =T26-T$28 | I27: =U26-U$28 | J27: =V26-V$28 | ... L27: =X26-X$28 | N27: 9 | O27: 0.465 | P27: 0.371 | Q27: 0.476 | R27: 0.258 | S27: 0.4 | T27: 0.41 | U27: 0.305 | V27: 0.274 | W27: 0.455 | X27: 0.348
B28: 9 | C28: =O27-O$28 | D28: =P27-P$28 | E28: =Q27-Q$28 | F28: =R27-R$28 | G28: =S27-S$28 | H28: =T27-T$28 | I28: =U27-U$28 | J28: =V27-V$28 | ... L28: =X27-X$28 | N28: 10 | O28: 0.449 | P28: 0.323 | Q28: 0.449 | R28: 0.247 | S28: 0.381 | T28: 0.39 | U28: 0.284 | V28: 0.255 | W28: 0.425 | X28: 0.328
B29: 10 | C29: =O28-O$28 | D29: =P28-P$28 | E29: =Q28-Q$28 | F29: =R28-R$28 | G29: =S28-S$28 | H29: =T28-T$28 | I29: =U28-U$28 | J29: =V28-V$28 | ... L29: =X28-X$28
A30: Source; Bureau of Labor Statistics
A31: Thus, if you are valuing a technology firm that is 6 years old, the chance of failure is 11.70%.
A33: Factors to consider
A34: 1. The likelihood of failure decreases for larger firms.
A35: 2. The likelihood of failure decreases with access to capital, and is thus lower for publicly traded firms or firms with multiple high profile VCs
A36: 3. The likelihood of failure decreases as revenue growth increases, since hope for future growth will sustain the firm.
A37: 4. The likelihood of failure decreases with better unit economics, higher gross margins on the additional units sold

Sheet Country equity risk premiums
A1: Mature Market ERP + | B1: 0.0423 | C1: Updated January 1, 2026
A2: Changing this number will update all your country equity risk premiums.
A4: Country | B4: Moody's rating | C4: Adj. Default Spread | D4: Equity Risk Premium | E4: Country Risk Premium | F4: Corporate Tax Rate
A5: Abu Dhabi | B5: Aa2 | C5: 0.0042 | D5: =$B$1+E5 | E5: 0.0064 | F5: 0.09
A6: Albania | B6: Ba3 | C6: 0.0306 | D6: =$B$1+E6 | E6: 0.0466 | F6: 0.15
A7: Algeria | B7: NR | C7: 0.0383 | D7: =$B$1+E7 | E7: 0.0583 | F7: 0.1007
A8: Andorra (Principality of) | B8: Baa1 | C8: 0.0136 | D8: =$B$1+E8 | E8: 0.0207 | F8: 0.1
A9: Angola | B9: B3 | C9: 0.0552 | D9: =$B$1+E9 | E9: 0.0841 | F9: 0.25
A10: Anguilla | B10: NR | C10: 0.04915183 | D10: =$B$1+E10 | E10: 0.074876823 | F10: 0.26526548
A11: Antigua & Barbuda | B11: NR | C11: 0.027785942 | D11: =$B$1+E11 | E11: 0.042328496 | F11: 0.31546691
A12: Argentina | B12: Caa1 | C12: 0.0637 | D12: =$B$1+E12 | E12: 0.0971 | F12: 0.35
A13: Armenia | B13: Ba3 | C13: 0.0306 | D13: =$B$1+E13 | E13: 0.0466 | F13: 0.18
A14: Aruba | B14: Baa3 | C14: 0.0187 | D14: =$B$1+E14 | E14: 0.0285 | F14: 0.22
A15: Australia | B15: Aaa | C15: 0 | D15: =$B$1+E15 | E15: 0 | F15: 0.3
A16: Austria | B16: Aa1 | C16: 0.0023 | D16: =$B$1+E16 | E16: 0.0036 | F16: 0.23
... A196: Zimbabwe | B196: NR | C196: 0.0765 | D196: =$B$1+E196 | E196: 0.1166 | F196: 0.159
A200: Region | B200: ERP | C200: Weighted Average: Default Spread | D200: Tax Rate | E200: Weighted Average: CRP | F200: Total GDP (in $ millions)
A201: Africa | B201: =$B$1+E201 | C201: 0.050672304 | D201: 0.27390174 | E201: 0.077193081 | F201: 2340875.2
A202: Asia | B202: =$B$1+E202 | C202: 0.0097961467 | D202: 0.25654535 | E202: 0.014923236 | F202: 34731689
A203: Australia & New Zealand | B203: =$B$1+E203 | C203: 2.6796848e-05 | D203: 0.29735221 | E203: 4.0821732e-05 | F203: 2018608.8
A204: Caribbean | B204: =$B$1+E204 | C204: 0.04915183 | D204: 0.26526548 | E204: 0.074876823 | F204: 347814.13
A205: Central and South America | B205: =$B$1+E205 | C205: 0.027785942 | D205: 0.31546691 | E205: 0.042328496 | F205: 6538486.9
A206: Eastern Europe | B206: =$B$1+E206 | C206: 0.021975562 | D206: 0.1763748 | E206: 0.033477091 | F206: 3491477.2
A207: Middle East | B207: =$B$1+E207 | C207: 0.013172609 | D207: 0.16120226 | E207: 0.020066864 | F207: 3565018.3
A208: North America | B208: =$B$1+E208 | C208: 0.0021647488 | D208: 0.25082522 | E208: 0.0021647488 | F208: 30994593
A209: Western Europe | B209: =$B$1+E209 | C209: 0.0068042645 | D209: 0.25557231 | E209: 0.010365468 | F209: 23561726
A210: Global | B210: =$B$1+E210 | C210: 0.0093761768 | D210: 0.25367576 | E210: 0.013957073 | F210: 1.0759029e+08
B213: ERP | C213: Default Spread | D213: Tax rate | E213: CRP
A214: Africa & Mid East | B214: =$B$1+E214 | C214: 0.028036085 | D214: 0.20587211 | E214: =C214*1.52
A215: Australia, NZ & Canada | B215: =$B$1+E215 | C215: 1.2691046e-05 | D215: 0.27842705 | E215: =C215*1.52
A216: Latin America & Caribbean | B216: =$B$1+E216 | C216: 0.028865093 | D216: 0.31293133 | E216: =C216*1.52
A217: Japan | B217: =$B$1+E217 | C217: 0.0059929264 | D217: 0.2974 | E217: =C217*1.52
A218: US | B218: =$B$1+E218 | C218: 0.0023336792 | D218: 0.25 | E218: =C218*1.52
A219: Europe | B219: =$B$1+E219 | C219: 0.0068042645 | D219: 0.25557231 | E219: =C219*1.52
A220: Emerging Markets | B220: =$B$1+E220 | C220: 0.015739699 | D220: 0.25110147 | E220: =C220*1.52
A221: Small Asia (No India, China & Japan) | B221: =$B$1+E221 | C221: 0.01624027 | D221: 0.25726349 | E221: =C221*1.52
A222: India | B222: =$B$1+E222 | C222: 0.018677954 | D222: 0.3 | E222: =C222*1.52
A223: China | B223: =$B$1+E223 | C223: 0.0059929264 | D223: 0.25 | E223: =C223*1.52
A224: Global | B224: =$B$1+E224 | C224: 0.0093761768 | D224: 0.25367576 | E224: =C224*1.52
A226: For other regional groupings
B227: ERP | C227: Default Spread | D227: Tax rate | E227: CRP
A228: EMEA | B228: =B1+E228 | C228: 0.01106 | D228: 0.2486 | E228: =C228*1.52

Sheet Industry Averages(US)
A1: Industry Name | B1: Number of firms | C1: Annual Average Revenue growth - Last 5 years | D1: Pre-tax Operating Margin (Unadjusted) | E1: After-tax ROC | F1: Average effective tax rate | G1: Unlevered Beta | H1: Equity (Levered) Beta | I1: Cost of equity | J1: Std deviation in stock prices | K1: Pre-tax cost of debt | L1: Market Debt/Capital | M1: Cost of capital | N1: Sales/Capital | O1: EV/Sales | P1: EV/EBITDA | Q1: EV/EBIT | R1: Price/Book | S1: Trailing PE | T1: Non-cash WC as % of Revenues | U1: Cap Ex as % of Revenues | V1: Net Cap Ex as % of Revenues | W1: Reinvestment Rate | X1: ROE | Y1: Dividend Payout Ratio | Z1: Equity Reinvestment Rate | AA1: Pre-tax Operating Margin (Lease & R&D adjusted)
A2: Advertising | B2: 52 | C2: 0.17674522 | D2: 0.10065799 | E2: 0.27722691 | F2: 0.2807582 | G2: 1.0080099 | H2: 1.210507 | I2: 0.093488611 | J2: 0.62914804 | K2: 0.052913 | L2: 0.28673358 | M2: 0.078061237 | N2: 3.8532841 | O2: 2.1248945 | P2: 11.998645 | Q2: 20.908716 | R2: 4.551215 | S2: 44.433353 | T2: 0.038339247 | U2: 0.019128564 | V2: -0.015213125 | W2: -0.20502082 | X2: -0.013422566 | Y2: 0.0027465943 | Z2: 0.0027465943 | AA2: 0.10190391
A3: Aerospace/Defense | B3: 79 | C3: 0.11099881 | D3: 0.08654589 | E3: 0.16012361 | F3: 0.17112254 | G3: 0.86937728 | H3: 0.94549148 | I3: 0.08166892 | J3: 0.464523 | K3: 0.052913 | L3: 0.13466812 | M3: 0.076014991 | N3: 2.7434104 | O3: 3.5707066 | P3: 21.583913 | Q3: 34.787926 | R3: 7.8804605 | S3: 92.800315 | T3: 0.41210226 | U3: 0.029962295 | V3: 0.0081800791 | W3: 0.67917262 | X3: 0.15268987 | Y3: 0.50152341 | Z3: 0.50152341 | AA3: 0.087653716
A4: Air Transport | B4: 23 | C4: 0.47786154 | D4: 0.0532118 | E4: 0.079293125 | F4: 0.2262844 | G4: 0.75790382 | H4: 1.1854651 | I4: 0.092371743 | J4: 0.59004326 | K4: 0.052913 | L4: 0.47690693 | M4: 0.067244951 | N4: 1.7998837 | O4: 1.0259549 | P4: 7.5752577 | Q4: 19.31869 | R4: 2.8414228 | S4: 18.321547 | T4: 0.0045173792 | U4: 0.082971993 | V4: 0.036065731 | W4: 0.83754413 | X4: 0.14194841 | Y4: 0.13207154 | Z4: 0.13207154 | AA4: 0.048990642
A5: Apparel | B5: 35 | C5: 0.081020435 | D5: 0.091100597 | E5: 0.15768516 | F5: 0.22113579 | G5: 0.7945635 | H5: 0.93587446 | I5: 0.081240001 | J5: 0.46263737 | K5: 0.052913 | L5: 0.23834056 | M5: 0.071335699 | N5: 1.768667 | O5: 1.5942098 | P5: 10.304886 | Q5: 16.086522 | R5: 3.8939528 | S5: 37.827986 | T5: 0.24379365 | U5: 0.024179706 | V5: 0.02076544 | W5: 0.31473571 | X5: 0.10420771 | Y5: 0.50093168 | Z5: 0.50093168 | AA5: 0.098736467
A6: Auto & Truck | B6: 33 | C6: 0.0864 | D6: 0.023182133 | E6: 0.022474129 | F6: 0.21930681 | G6: 1.3081652 | H6: 1.4564933 | I6: 0.1044596 | J6: 0.61834605 | K6: 0.052913 | L6: 0.16454936 | M6: 0.093800941 | N6: 1.0752957 | O6: 3.8830204 | P6: 47.755842 | Q6: 160.31626 | R6: 7.7247318 | S6: 64.320311 | T6: -0.029612109 | U6: 0.05943957 | V6: 0.020963184 | W6: -0.38556791 | X6: 0.031593225 | Y6: 0.58308529 | Z6: 0.58308529 | AA6: 0.025282982
A7: Auto Parts | B7: 35 | C7: 0.15909478 | D7: 0.056737587 | E7: 0.089759483 | F7: 0.31646842 | G7: 1.1283051 | H7: 1.3394464 | I7: 0.099239308 | J7: 0.4987204 | K7: 0.052913 | L7: 0.29310639 | M7: 0.081783486 | N7: 2.3891597 | O7: 0.82283598 | P7: 6.428094 | Q7: 12.382869 | R7: 1.8654554 | S7: 28.072977 | T7: 0.15854921 | U7: 0.029845679 | V7: 0.020125587 | W7: 0.38991609 | X7: 0.021741488 | Y7: 1.0954685 | Z7: 1.0954685 | AA7: 0.059639005
A8: Bank (Money Center) | B8: 15 | C8: 0.090564286 | D8: 0 | E8: NA | F8: 0.17380473 | G8: 0.44389138 | H8: 0.76104618 | I8: 0.07344266 | J8: 0.22738718 | K8: 0.047306 | L8: 0.62148406 | M8: 0.049849161 | N8: 0.190638 | O8: 8.3095573 | P8: NA | Q8: NA | R8: 1.6223296 | S8: 14.951036 | T8: NA | U8: 0.017805534 | V8: 0.017948244 | W8: 0.049849161 | X8: 0.12860334 | Y8: 0.28110834 | Z8: 0.28110834 | AA8: 0.00077508014
A9: Banks (Regional) | B9: 568 | C9: 0.080465436 | D9: 4.9066906e-08 | E9: NA | F9: 0.20777645 | G9: 0.37443924 | H9: 0.39847656 | I9: 0.057272054 | J9: 0.22682558 | K9: 0.047306 | L9: 0.34254771 | M9: 0.049807065 | N9: 0.32878811 | O9: 4.2762723 | P9: NA | Q9: NA | R9: 1.1380354 | S9: 33.601518 | T9: NA | U9: 0.022892274 | V9: -0.013024347 | W9: NA | X9: 0.097543188 | Y9: 0.36088813 | Z9: 0.36088813 | AA9: -0.0012057021
A10: Beverage (Alcoholic) | B10: 14 | C10: 0.0342775 | D10: 0.22763344 | E10: 0.15744766 | F10: 0.24732206 | G10: 0.62804664 | H10: 0.81247563 | I10: 0.075736413 | J10: 0.55961937 | K10: 0.052913 | L10: 0.30235028 | M10: 0.064836183 | N10: 0.78831058 | O10: 2.4539199 | P10: 8.6054795 | Q10: 10.752355 | R10: 1.9141066 | S10: 28.296299 | T10: 0.14639965 | U10: 0.067204997 | V10: 0.037359648 | W10: 0.22017928 | X10: 0.0056819181 | Y10: 0.0022415452 | Z10: 0.0022415452 | AA10: 0.22787293
A11: Beverage (Soft) | B11: 27 | C11: 0.085835 | D11: 0.20525115 | E11: 0.29025635 | F11: 0.19573515 | G11: 0.57546483 | H11: 0.64146871 | I11: 0.068109504 | J11: 0.57886898 | K11: 0.052913 | L11: 0.17072403 | M11: 0.063256716 | N11: 1.5441786 | O11: 4.1561135 | P11: 16.904245 | Q11: 20.14057 | R11: 6.8690605 | S11: 47.76376 | T11: -0.060032721 | U11: 0.045890536 | V11: 0.046903159 | W11: 0.33933783 | X11: 0.30915585 | Y11: 0.72668055 | Z11: 0.72668055 | AA11: 0.20632057
A12: Broadcasting | B12: 24 | C12: 0.084101053 | D12: 0.12333893 | E12: 0.14567295 | F12: 0.25536809 | G12: 0.31529257 | H12: 0.47075205 | I12: 0.060495541 | J12: 0.4662307 | K12: 0.052913 | L12: 0.46194409 | M12: 0.050882119 | N12: 1.278665 | O12: 1.3951404 | P12: 7.8470146 | Q12: 11.158397 | R12: 1.6647216 | S12: 44.75922 | T12: 0.10455213 | U12: 0.018236573 | V12: -0.022588756 | W12: 1.8876238 | X12: 0.039852497 | Y12: 0.60828155 | Z12: 0.60828155 | AA12: 0.123501
A13: Brokerage & Investment Banking | B13: 32 | C13: 0.35515652 | D13: -1.7915897e-05 | E13: NA | F13: 0.20451763 | G13: 0.67940308 | H13: 1.1714571 | I13: 0.091746985 | J13: 0.3660856 | K13: 0.050672 | L13: 0.57550426 | M13: 0.060817668 | N13: 0.27486794 | O13: 5.7822604 | P13: NA | Q13: NA | R13: 2.8085919 | S13: 86.541909 | T13: NA | U13: 0.021111275 | V13: 0.016386115 | W13: NA | X13: 0.17767908 | Y13: 0.27613076 | Z13: 0.27613076 | AA13: -0.0010225863
A14: Building Materials | B14: 41 | C14: 0.041387419 | D14: 0.12636827 | E14: 0.20164569 | F14: 0.28356854 | G14: 0.96052756 | H14: 1.1115322 | I14: 0.089074335 | J14: 0.35282101 | K14: 0.050672 | L14: 0.20633852 | M14: 0.078536557 | N14: 2.0607977 | O14: 2.0460612 | P14: 11.607041 | Q14: 15.974601 | R14: 3.6163269 | S14: 32.798464 | T14: 0.18435837 | U14: 0.035512084 | V14: 0.027684617 | W14: 0.38226087 | X14: 0.15997618 | Y14: 0.25553673 | Z14: 0.25553673 | AA14: 0.1284574
A15: Business & Consumer Services | B15: 155 | C15: 0.058026914 | D15: 0.12272432 | E15: 0.28297691 | F15: 0.22457358 | G15: 0.80602493 | H15: 0.88797853 | I15: 0.079103843 | J15: 0.41106992 | K15: 0.050672 | L15: 0.16469046 | M15: 0.07233509 | N15: 2.7985106 | O15: 2.5297327 | P15: 14.257164 | Q15: 20.145573 | R15: 5.2994154 | S15: 36.396625 | T15: 0.14518985 | U15: 0.026055677 | V15: 0.033591319 | W15: 0.44385906 | X15: 0.18195762 | Y15: 0.42604327 | Z15: 0.42604327 | AA15: 0.12376381
A16: Cable TV | B16: 9 | C16: 0.26942857 | D16: 0.18485746 | E16: 0.12062121 | F16: 0.18964768 | G16: 0.36287691 | H16: 0.74074441 | I16: 0.072537201 | J16: 0.44040714 | K16: 0.050672 | L16: 0.59504243 | M16: 0.051988481 | N16: 0.74339755 | O16: 2.0554855 | P16: 6.2077664 | Q16: 11.267463 | R16: 1.3131997 | S16: 6.1047952 | T16: 0.018977296 | U16: 0.1232855 | V16: -0.0077895713 | W16: -0.068238761 | X16: 0.11059819 | Y16: 0.33464436 | Z16: 0.33464436 | AA16: 0.18218073
A17: Chemical (Basic) | B17: 29 | C17: 0.13884706 | D17: 0.026737181 | E17: 0.037245953 | F17: 0.35148313 | G17: 0.63678307 | H17: 1.0122472 | I17: 0.084646223 | J17: 0.45809707 | K17: 0.052913 | L17: 0.49837971 | M17: 0.062238337 | N17: 1.4901604 | O17: 0.84521902 | P17: 8.5673406 | Q17: 28.976526 | R17: 1.1171922 | S17: 24.42051 | T17: 0.16205831 | U17: 0.062281829 | V17: 0.039430872 | W17: 1.5865275 | X17: -0.082898887 | Y17: 0.00413163 | Z17: 0.00413163 | AA17: 0.028322849
A18: Chemical (Diversified) | B18: 4 | C18: 0.01438 | D18: 0.032913267 | E18: 0.040542645 | F18: #DIV/0! | G18: 0.40614323 | H18: 0.85070286 | I18: 0.077441347 | J18: 0.390352 | K18: 0.050672 | L18: 0.63782549 | M18: 0.052287202 | N18: 1.2651792 | O18: 0.84169043 | P18: 8.3850601 | Q18: 24.686652 | R18: 1.0834548 | S18: #DIV/0! | T18: 0.16693656 | U18: 0.043299126 | V18: -0.011810238 | W18: -0.45735483 | X18: -0.15302086 | Y18: #DIV/0! | Z18: #DIV/0! | AA18: 0.034353996
A19: Chemical (Specialty) | B19: 59 | C19: 0.080353488 | D19: 0.12171997 | E19: 0.10949444 | F19: 0.24738526 | G19: 0.82447066 | H19: 0.96978288 | I19: 0.082752317 | J19: 0.42305161 | K19: 0.050672 | L19: 0.23007608 | M19: 0.072456799 | N19: 1.1054194 | O19: 2.6476145 | P19: 13.359261 | Q19: 21.300042 | R19: 2.4497397 | S19: 196.77409 | T19: 0.23796513 | U19: 0.08475369 | V19: 0.040548599 | W19: 0.5161404 | X19: 0.034987854 | Y19: 1.3000936 | Z19: 1.3000936 | AA19: 0.12453894
A20: Coal & Related Energy | B20: 16 | C20: 0.19238571 | D20: -0.040171813 | E20: -0.04759627 | F20: 0.09671848 | G20: 1.1824382 | H20: 1.0709932 | I20: 0.087266296 | J20: 0.64314909 | K20: 0.052913 | L20: 0.066667778 | M20: 0.08409414 | N20: 1.2912284 | O20: 2.5369157 | P20: 10.368996 | Q20: NA | R20: 2.2473251 | S20: 17.007589 | T20: 0.10176223 | U20: 0.093624405 | V20: -0.031172028 | W20: NA | X20: -0.025132407 | Y20: 0.00081724138 | Z20: 0.00081724138 | AA20: -0.038444728
A21: Computer Services | B21: 64 | C21: 0.27099842 | D21: 0.074093347 | E21: 0.26348563 | F21: 0.22563711 | G21: 0.961701 | H21: 1.0878559 | I21: 0.088018373 | J21: 0.53425303 | K21: 0.052913 | L21: 0.20064027 | M21: 0.078320702 | N21: 5.1898907 | O21: 1.4770942 | P21: 14.09505 | Q21: 19.251985 | R21: 4.7282653 | S21: 51.599295 | T21: 0.13400222 | U21: 0.0095097704 | V21: 0.019117502 | W21: 0.44407781 | X21: 0.18250592 | Y21: 0.50992051 | Z21: 0.50992051 | AA21: 0.078105531
A22: Computers/Peripherals | B22: 36 | C22: 0.067108696 | D22: 0.22484875 | E22: 0.44760353 | F22: 0.15354539 | G22: 1.324587 | H22: 1.3503292 | I22: 0.099724683 | J22: 0.54576795 | K22: 0.052913 | L22: 0.044203104 | M22: 0.097070731 | N22: 3.6197887 | O22: 6.6298032 | P22: 25.424492 | Q22: 29.358881 | R22: 34.082061 | S22: 81.131988 | T22: -0.047057419 | U22: 0.02947135 | V22: 0.028994372 | W22: 0.213689 | X22: -0.001741316 | Y22: 0.16030215 | Z22: 0.16030215 | AA22: 0.2292366
A23: Construction Supplies | B23: 40 | C23: 0.13703929 | D23: 0.15228588 | E23: 0.16706063 | F23: 0.2254751 | G23: 1.0468297 | H23: 1.1503561 | I23: 0.09080588 | J23: 0.35513321 | K23: 0.050672 | L23: 0.14981855 | M23: 0.082895179 | N23: 1.4469464 | O23: 3.2317777 | P23: 16.81867 | Q23: 21.145402 | R23: 5.4556033 | S23: 42.74757 | T23: 0.22558523 | U23: 0.055364628 | V23: 0.066163121 | W23: 0.63007613 | X23: 0.22855657 | Y23: 0.3349261 | Z23: 0.3349261 | AA23: 0.15219467
A24: Diversified | B24: 20 | C24: 0.08903 | D24: 0.22729327 | E24: 0.14821357 | F24: 0.17556675 | G24: 0.84309626 | H24: 0.88095518 | I24: 0.078790601 | J24: 0.28411724 | K24: 0.047306 | L24: 0.13459402 | M24: 0.072961186 | N24: 0.67605901 | O24: 3.080145 | P24: 11.415462 | Q24: 13.486471 | R24: 1.7829542 | S24: 15.731004 | T24: 0.0077362264 | U24: 0.050393138 | V24: 0.023158588 | W24: 0.18265629 | X24: 0.11373244 | Y24: 0.065882411 | Z24: 0.065882411 | AA24: 0.22833283
A25: Drugs (Biotechnology) | B25: 496 | C25: 0.28926778 | D25: 0.08973321 | E25: 0.035253743 | F25: 0.15753957 | G25: 1.0794539 | H25: 1.135265 | I25: 0.09013282 | J25: 0.75679798 | K25: 0.060195 | L25: 0.11535594 | M25: 0.084943352 | N25: 0.81995483 | O25: 7.9180455 | P25: 15.778972 | Q25: 68.971321 | R25: 8.2168638 | S25: 64.275557 | T25: 0.13361481 | U25: 0.032863083 | V25: -0.035741805 | W25: -0.45020504 | X25: -0.056722488 | Y25: 0.0011705552 | Z25: 0.0011705552 | AA25: 0.089533158
A26: Drugs (Pharmaceutical) | B26: 228 | C26: 0.18446775 | D26: 0.295397 | E26: 0.16949548 | F26: 0.16800912 | G26: 0.91513597 | H26: 0.9828331 | I26: 0.083334356 | J26: 0.76644924 | K26: 0.060195 | L26: 0.12692026 | M26: 0.078487512 | N26: 1.1116586 | O26: 6.2393363 | P26: 15.247997 | Q26: 20.323167 | R26: 6.6439639 | S26: 55.667674 | T26: 0.32088501 | U26: 0.055683047 | V26: 0.011179219 | W26: 0.09997397 | X26: 0.240441 | Y26: 0.58634992 | Z26: 0.58634992 | AA26: 0.27245509
A27: Education | B27: 32 | C27: 0.077383125 | D27: 0.14013177 | E27: 0.15944154 | F27: 0.30436626 | G27: 0.71959983 | H27: 0.78090559 | I27: 0.074328389 | J27: 0.47237751 | K27: 0.052913 | L27: 0.1960034 | M27: 0.067538118 | N27: 1.6274535 | O27: 1.9902138 | P27: 9.2612839 | Q27: 14.486878 | R27: 2.6032867 | S27: 26.965785 | T27: 0.10031098 | U27: 0.029724301 | V27: 0.0064850459 | W27: 0.23524496 | X27: 0.15904839 | Y27: 0.13829432 | Z27: 0.13829432 | AA27: 0.13742199
A28: Electrical Equipment | B28: 112 | C28: 0.19174545 | D28: 0.095346671 | E28: 0.15595604 | F28: 0.25179176 | G28: 1.189807 | H28: 1.2511239 | I28: 0.095300124 | J28: 0.7271388 | K28: 0.060195 | L28: 0.1071686 | M28: 0.089925204 | N28: 2.029529 | O28: 4.4207549 | P28: 24.586304 | Q28: 43.193318 | R28: 6.5067316 | S28: 80.039612 | T28: 0.29437246 | U28: 0.047752921 | V28: 0.030839959 | W28: 0.546827 | X28: 0.015254544 | Y28: 2.2968581 | Z28: 2.2968581 | AA28: 0.099508686
A29: Electronics (Consumer & Office) | B29: 8 | C29: -0.03486 | D29: -0.044886216 | E29: -0.083455147 | F29: #DIV/0! | G29: 0.92737661 | H29: 0.86597802 | I29: 0.07812262 | J29: 0.70183613 | K29: 0.060195 | L29: 0.054858953 | M29: 0.076313571 | N29: 5.5665464 | O29: 0.90983349 | P29: 30.697397 | Q29: NA | R29: 3.8520329 | S29: #DIV/0! | T29: 0.11155604 | U29: 0.014296258 | V29: -0.038403388 | W29: NA | X29: -0.2880928 | Y29: #DIV/0! | Z29: #DIV/0! | AA29: -0.062642694
A30: Electronics (General) | B30: 114 | C30: 0.072683026 | D30: 0.10423178 | E30: 0.17911725 | F30: 0.2032218 | G30: 0.93745456 | H30: 0.97147713 | I30: 0.08282788 | J30: 0.51838785 | K30: 0.052913 | L30: 0.099194588 | M30: 0.078548315 | N30: 2.3834943 | O30: 3.2061628 | P30: 19.991142 | Q30: 29.756692 | R30: 4.9689677 | S30: 48.443352 | T30: 0.20917712 | U30: 0.033041882 | V30: 0.056801347 | W30: 0.77176496 | X30: 0.12615731 | Y30: 0.19877481 | Z30: 0.19877481 | AA30: 0.10606522
A31: Engineering/Construction | B31: 48 | C31: 0.11701107 | D31: 0.064877214 | E31: 0.25317603 | F31: 0.23948117 | G31: 1.1374368 | H31: 1.2099723 | I31: 0.093464763 | J31: 0.45923646 | K31: 0.052913 | L31: 0.12289531 | M31: 0.086855452 | N31: 4.3614487 | O31: 1.7350431 | P31: 17.179436 | Q31: 25.171222 | R31: 5.4904687 | S31: 63.332049 | T31: 0.19376595 | U31: 0.022327088 | V31: 0.04846667 | W31: 1.1244005 | X31: 0.261375 | Y31: 0.083295433 | Z31: 0.083295433 | AA31: 0.067570156
A32: Entertainment | B32: 92 | C32: 0.16430788 | D32: 0.10604785 | E32: 0.124206 | F32: 0.12604725 | G32: 0.76284683 | H32: 0.82516964 | I32: 0.076302566 | J32: 0.4870659 | K32: 0.052913 | L32: 0.13729041 | M32: 0.071275291 | N32: 1.3914059 | O32: 4.3338247 | P32: 19.411263 | Q32: 38.919561 | R32: 4.7981015 | S32: 108.63059 | T32: 0.0049050505 | U32: 0.047139528 | V32: -0.012526244 | W32: -0.15551247 | X32: 0.060927631 | Y32: 0.22878758 | Z32: 0.22878758 | AA32: 0.10600218
A33: Environmental & Waste Services | B33: 53 | C33: 0.21702174 | D33: 0.14608556 | E33: 0.31754797 | F33: 0.20916445 | G33: 0.8247691 | H33: 0.9454813 | I33: 0.081668466 | J33: 0.54912717 | K33: 0.052913 | L33: 0.17659871 | M33: 0.074254196 | N33: 2.2998509 | O33: 3.700675 | P33: 15.613079 | Q33: 24.826655 | R33: 6.5854585 | S33: 66.549566 | T33: 0.10038718 | U33: 0.082781748 | V33: 0.13438403 | W33: 1.2140193 | X33: 0.19738296 | Y33: 0.39802383 | Z33: 0.39802383 | AA33: 0.14853081
A34: Farming/Agriculture | B34: 35 | C34: 0.14021952 | D34: 0.054453187 | E34: 0.072779429 | F34: 0.20340963 | G34: 0.84578367 | H34: 1.1291737 | I34: 0.089861149 | J34: 0.50793816 | K34: 0.052913 | L34: 0.34144887 | M34: 0.072728474 | N34: 1.4794346 | O34: 1.3401505 | P34: 16.037699 | Q34: 23.735676 | R34: 2.422867 | S34: 19.115989 | T34: 0.17273412 | U34: 0.038437685 | V34: 0.036581593 | W34: 0.52612189 | X34: 0.12040259 | Y34: 0.41442187 | Z34: 0.41442187 | AA34: 0.056033712
A35: Financial Svcs. (Non-bank & Insurance) | B35: 176 | C35: 0.11297944 | D35: 0.18483867 | E35: NA | F35: 0.1930857 | G35: 0.32770839 | H35: 0.96971324 | I35: 0.082749211 | J35: 0.42469192 | K35: 0.050672 | L35: 0.73127668 | M35: 0.050028082 | N35: 0.070855846 | O35: 18.905905 | P35: 57.52356 | Q35: 69.396371 | R35: 3.6609228 | S35: 26.13839 | T35: 11.859986 | U35: 0.029854629 | V35: 0.023802866 | W35: 0.14141048 | X35: 0.28817318 | Y35: 0.18524081 | Z35: 0.18524081 | AA35: 0.18739294
A36: Food Processing | B36: 78 | C36: 0.071580217 | D36: 0.10630698 | E36: 0.15949707 | F36: 0.22809725 | G36: 0.46942378 | H36: 0.60745304 | I36: 0.066592405 | J36: 0.43467639 | K36: 0.050672 | L36: 0.3042697 | M36: 0.05789382 | N36: 1.709199 | O36: 1.4683157 | P36: 10.011975 | Q36: 13.605211 | R36: 1.7958938 | S36: 47.968126 | T36: 0.066773492 | U36: 0.03300956 | V36: 0.022866939 | W36: 0.32772573 | X36: 0.046041192 | Y36: 1.431111 | Z36: 1.431111 | AA36: 0.10737651
A37: Food Wholesalers | B37: 13 | C37: 0.13276667 | D37: 0.026134886 | E37: 0.17837019 | F37: 0.23676103 | G37: 0.64775981 | H37: 0.86664164 | I37: 0.078152217 | J37: 0.33978224 | K37: 0.050672 | L37: 0.31958232 | M37: 0.065321557 | N37: 7.7129096 | O37: 0.45685205 | P37: 11.075252 | Q37: 17.944483 | R37: 4.8785548 | S37: 26.802893 | T37: 0.05623003 | U37: 0.010065459 | V37: 0.015039536 | W37: 0.8133778 | X37: 0.18220725 | Y37: 0.38074736 | Z37: 0.38074736 | AA37: 0.025456148
A38: Furn/Home Furnishings | B38: 27 | C38: 0.0098738095 | D38: 0.065856619 | E38: 0.10587429 | F38: 0.29077657 | G38: 0.65213037 | H38: 0.82315847 | I38: 0.076212868 | J38: 0.51509863 | K38: 0.052913 | L38: 0.29742409 | M38: 0.065348526 | N38: 1.9585441 | O38: 1.332799 | P38: 11.27382 | Q38: 19.14514 | R38: 2.4531885 | S38: 17.383525 | T38: 0.15730317 | U38: 0.024513854 | V38: 0.058771049 | W38: 1.4006328 | X38: 0.031074151 | Y38: 1.0812222 | Z38: 1.0812222 | AA38: 0.067999744
A39: Green & Renewable Energy | B39: 15 | C39: 0.17102 | D39: 0.19872603 | E39: 0.036367416 | F39: 0 | G39: 0.47228417 | H39: 0.85632952 | I39: 0.077692297 | J39: 0.65143401 | K39: 0.060195 | L39: 0.5307579 | M39: 0.060418225 | N39: 0.19799484 | O39: 7.865693 | P39: 13.443717 | Q39: 42.625568 | R39: 1.262866 | S39: 32.249594 | T39: -1.1429115 | U39: 0.31895685 | V39: 0.090073723 | W39: 0.63819613 | X39: -0.073571372 | Y39: 0.00128998 | Z39: 0.00128998 | AA39: 0.18379737
A40: Healthcare Products | B40: 204 | C40: 0.18410675 | D40: 0.15338997 | E40: 0.16980779 | F40: 0.12774024 | G40: 0.8569478 | H40: 0.90856114 | I40: 0.080021827 | J40: 0.6179059 | K40: 0.052913 | L40: 0.11335852 | M40: 0.075449275 | N40: 1.4769505 | O40: 4.7626008 | P40: 19.778037 | Q40: 29.989275 | R40: 4.4351038 | S40: 43.065163 | T40: 0.25652592 | U40: 0.039885898 | V40: 0.045266301 | W40: 0.45993629 | X40: 0.11260004 | Y40: 0.35640708 | Z40: 0.35640708 | AA40: 0.15829837
A41: Healthcare Support Services | B41: 104 | C41: 0.1312175 | D41: 0.029984059 | E41: 0.31192967 | F41: 0.229954 | G41: 0.74487506 | H41: 0.87195389 | I41: 0.078389143 | J41: 0.47240032 | K41: 0.052913 | L41: 0.26158564 | M41: 0.06826463 | N41: 11.746627 | O41: 0.45778331 | P41: 11.168825 | Q41: 15.02205 | R41: 2.7955722 | S41: 83.766609 | T41: -0.057878368 | U41: 0.0056454074 | V41: 0.0086568477 | W41: 0.50714607 | X41: 0.098917913 | Y41: 0.4936926 | Z41: 0.4936926 | AA41: 0.03005287
A42: Heathcare Information and Technology | B42: 115 | C42: 0.1557353 | D42: 0.14709486 | E42: 0.13716783 | F42: 0.15096665 | G42: 1.016325 | H42: 1.1083339 | I42: 0.088931692 | J42: 0.63780021 | K42: 0.052913 | L42: 0.1360045 | M42: 0.082233886 | N42: 1.2456991 | O42: 5.3091884 | P42: 21.272127 | Q42: 34.762161 | R42: 4.0022386 | S42: 506.54687 | T42: 0.23527586 | U42: 0.038932629 | V42: 0.0092157948 | W42: 0.12116668 | X42: 0.063973637 | Y42: 0.16849319 | Z42: 0.16849319 | AA42: 0.14794312
A43: Homebuilding | B43: 30 | C43: 0.098721739 | D43: 0.12574953 | E43: 0.14908129 | F43: 0.23671664 | G43: 0.85322308 | H43: 0.91061781 | I43: 0.080113554 | J43: 0.32794047 | K43: 0.050672 | L43: 0.17589765 | M43: 0.072706583 | N43: 1.4215189 | O43: 1.1916269 | P43: 8.9181256 | Q43: 9.4319205 | R43: 1.633095 | S43: 11.453496 | T43: 0.61646351 | U43: 0.0048812505 | V43: 0.0068278515 | W43: 0.31028812 | X43: 0.1423143 | Y43: 0.095721886 | Z43: 0.095721886 | AA43: 0.12633856
A44: Hospitals/Healthcare Facilities | B44: 31 | C44: 0.15944588 | D44: 0.13356558 | E44: 0.2216397 | F44: 0.2132822 | G44: 0.56485887 | H44: 0.79967833 | I44: 0.075165654 | J44: 0.56456947 | K44: 0.052913 | L44: 0.37468885 | M44: 0.061871355 | N44: 1.9503085 | O44: 1.688745 | P44: 8.8640214 | Q44: 13.115464 | R44: 5.6227363 | S44: 18.804233 | T44: 0.10483508 | U44: 0.059521581 | V44: 0.029611844 | W44: 0.33909534 | X44: 0.5083628 | Y44: 0.093353832 | Z44: 0.093353832 | AA44: 0.1285532
A45: Hotel/Gaming | B45: 63 | C45: 0.218171 | D45: 0.19387993 | E45: 0.14575119 | F45: 0.16615162 | G45: 0.87568844 | H45: 1.0803676 | I45: 0.087684394 | J45: 0.39653352 | K45: 0.050672 | L45: 0.28443753 | M45: 0.073553425 | N45: 1.0399 | O45: 4.3270761 | P45: 14.932671 | Q45: 25.710682 | R45: 12.303473 | S45: 46.603339 | T45: 0.0076629539 | U45: 0.073417002 | V45: 0.025178245 | W45: 0.25374823 | X45: 0.45383267 | Y45: 0.18280477 | Z45: 0.18280477 | AA45: 0.16594542
A46: Household Products | B46: 110 | C46: 0.08087383 | D46: 0.18624882 | E46: 0.34419838 | F46: 0.20731495 | G46: 0.74107693 | H46: 0.81551583 | I46: 0.075872006 | J46: 0.55463786 | K46: 0.052913 | L46: 0.15360129 | M46: 0.070313597 | N46: 2.2144293 | O46: 3.0594681 | P46: 13.17352 | Q46: 16.254913 | R46: 5.8470901 | S46: 33.071796 | T46: 0.060060838 | U46: 0.037914432 | V46: 0.011319961 | W46: 0.07757641 | X46: 0.27021197 | Y46: 0.67246274 | Z46: 0.67246274 | AA46: 0.18810977
A47: Information Services | B47: 15 | C47: 0.067709091 | D47: 0.11886022 | E47: 0.221743 | F47: 0.21739341 | G47: 0.75635636 | H47: 0.92056732 | I47: 0.080557303 | J47: 0.32375245 | K47: 0.050672 | L47: 0.24907927 | M47: 0.069958157 | N47: 2.5121429 | O47: 2.2125354 | P47: 11.498322 | Q47: 17.766517 | R47: 3.7949389 | S47: 24.917028 | T47: 0.16621255 | U47: 0.019042141 | V47: -0.02871717 | W47: -0.26789021 | X47: 0.1494609 | Y47: 0.32067335 | Z47: 0.32067335 | AA47: 0.12471997
... A50: Insurance (Prop/Cas.) | B50: 57 | C50: 0.087641837 | D50: 0.15254115 | E50: 0.18488979 | F50: 0.215889 | G50: 0.45702349 | H50: 0.48411002 | I50: 0.061091307 | J50: 0.2869688 | K50: 0.047306 | L50: 0.12914203 | M50: 0.057783746 | N50: 1.4802983 | O50: 1.4887819 | P50: 8.4356789 | Q50: 9.6399625 | R50: 2.0238528 | S50: 18.334442 | T50: -0.40478516 | U50: 0.0064639891 | V50: -0.010506217 | W50: 0.020046851 | X50: 0.18714725 | Y50: 0.22485701 | Z50: 0.22485701 | AA50: 0.15300583
A51: Investments & Asset Management | B51: 283 | C51: 0.056888627 | D51: 0.25502482 | E51: 0.14253207 | F51: 0.18511589 | G51: 0.58806403 | H51: 0.65958175 | I51: 0.068917346 | J51: 0.30042257 | K51: 0.050672 | L51: 0.2463534 | M51: 0.061301738 | N51: 0.58941739 | O51: 5.4860456 | P51: 38.028801 | Q51: 20.399919 | R51: 2.489616 | S51: 75.304908 | T51: NA | U51: 0.024442615 | V51: 0.21022998 | W51: 1.3106534 | X51: 0.15880677 | Y51: 0.58240062 | Z51: 0.58240062 | AA51: 0.25257292
A52: Machinery | B52: 105 | C52: 0.10368775 | D52: 0.15864951 | E52: 0.24408326 | F52: 0.21211063 | G52: 0.89403025 | H52: 0.96362079 | I52: 0.082477487 | J52: 0.45034117 | K52: 0.052913 | L52: 0.1281019 | M52: 0.076995656 | N52: 1.9519256 | O52: 3.4261311 | P52: 16.217471 | Q52: 21.03633 | R52: 4.50141 | S52: 35.761036 | T52: 0.24421936 | U52: 0.023903137 | V52: 0.041351046 | W52: 0.34325707 | X52: 0.16423122 | Y52: 0.33425684 | Z52: 0.33425684 | AA52: 0.16121052
A53: Metals & Mining | B53: 73 | C53: 0.086706667 | D53: 0.23854272 | E53: 0.27043618 | F53: 0.34462831 | G53: 1.0104493 | H53: 1.0430315 | I53: 0.086019204 | J53: 0.7756026 | K53: 0.060195 | L53: 0.098973453 | M53: 0.081973866 | N53: 1.1757156 | O53: 4.0344825 | P53: 11.390637 | Q53: 15.721899 | R53: 4.3367655 | S53: 54.117601 | T53: 0.14887154 | U53: 0.11715688 | V53: 0.046138469 | W53: 0.32403218 | X53: 0.17794349 | Y53: 0.51999449 | Z53: 0.51999449 | AA53: 0.23750131
A54: Office Equipment & Services | B54: 14 | C54: 0.0813 | D54: 0.10728305 | E54: 0.1826016 | F54: 0.23759711 | G54: 1.0381902 | H54: 1.334375 | I54: 0.099013127 | J54: 0.39607567 | K54: 0.050672 | L54: 0.32479184 | M54: 0.07919786 | N54: 2.2050307 | O54: 1.4336637 | P54: 8.5948545 | Q54: 13.026289 | R54: 2.924079 | S54: 18.551527 | T54: 0.081389915 | U54: 0.027643414 | V54: 0.01869517 | W54: 0.32291643 | X54: 0.13225662 | Y54: 0.57403612 | Z54: 0.57403612 | AA54: 0.10798293
A55: Oil/Gas (Integrated) | B55: 4 | C55: 0.0462 | D55: 0.11248664 | E55: 0.084490604 | F55: 0.31437215 | G55: 0.27800401 | H55: 0.29938198 | I55: 0.052852436 | J55: 0.20268279 | K55: 0.047306 | L55: 0.12161274 | M55: 0.050739666 | N55: 1.0243113 | O55: 1.7531762 | P55: 8.1630216 | Q55: 15.156704 | R55: 1.7075523 | S55: 16.243905 | T55: 0.039274251 | U55: 0.096389881 | V55: 0.0038903252 | W55: 0.083948921 | X55: 0.099575021 | Y55: 0.67733936 | Z55: 0.67733936 | AA55: 0.11577412
A56: Oil/Gas (Production and Exploration) | B56: 142 | C56: 0.17612521 | D56: 0.2541583 | E56: 0.13731095 | F56: 0.25337214 | G56: 0.57854057 | H56: 0.72140596 | I56: 0.071674706 | J56: 0.42219201 | K56: 0.050672 | L56: 0.27319045 | M56: 0.06247619 | N56: 0.57409944 | O56: 2.6825886 | P56: 5.1458593 | Q56: 10.277444 | R56: 1.3557207 | S56: 30.983413 | T56: 0.0066171271 | U56: 0.38137411 | V56: 0.19048692 | W56: 1.0047519 | X56: 0.12211066 | Y56: 0.41698781 | Z56: 0.41698781 | AA56: 0.25749649
A57: Oil/Gas Distribution | B57: 23 | C57: 0.20128067 | D57: 0.2577811 | E57: 0.12351055 | F57: 0.20388504 | G57: 0.4692563 | H57: 0.66922245 | I57: 0.069347321 | J57: 0.42240372 | K57: 0.050672 | L57: 0.36919318 | M57: 0.057775581 | N57: 0.52193747 | O57: 4.3717838 | P57: 11.562397 | Q57: 16.480577 | R57: 2.882271 | S57: 23.717264 | T57: 0.010570039 | U57: 0.2124111 | V57: 0.19592039 | W57: 0.99633827 | X57: 0.18032702 | Y57: 0.69434856 | Z57: 0.69434856 | AA57: 0.26054683
A58: Oilfield Svcs/Equip. | B58: 97 | C58: 0.10785927 | D58: 0.046496063 | E58: 0.11937951 | F58: 0.18545869 | G58: 0.78705756 | H58: 0.95124187 | I58: 0.081925387 | J58: 0.48316435 | K58: 0.052913 | L58: 0.27198933 | M58: 0.070436385 | N58: 2.7927152 | O58: 0.74135184 | P58: 8.6297607 | Q58: 14.904129 | R58: 1.9183893 | S58: 33.300345 | T58: 0.089263295 | U58: 0.028881308 | V58: 0.0090806707 | W58: 0.32183361 | X58: 0.086460413 | Y58: 0.60075087 | Z58: 0.60075087 | AA58: 0.04815455
A59: Packaging & Container | B59: 19 | C59: 0.04663 | D59: 0.095755765 | E59: 0.14816927 | F59: 0.23575215 | G59: 0.7489918 | H59: 1.0219298 | I59: 0.085078068 | J59: 0.25447909 | K59: 0.047306 | L59: 0.35529454 | M59: 0.067455967 | N59: 1.8403807 | O59: 1.5482237 | P59: 9.7095672 | Q59: 15.77845 | R59: 2.1839676 | S59: 16.428216 | T59: 0.12655973 | U59: 0.054699035 | V59: 0.051378262 | W59: 0.93958507 | X59: 0.12293732 | Y59: 0.55582488 | Z59: 0.55582488 | AA59: 0.097673274
A60: Paper/Forest Products | B60: 6 | C60: -0.0034 | D60: 0.063448389 | E60: 0.10414206 | F60: 0.25842697 | G60: 0.76967515 | H60: 0.95797843 | I60: 0.082225838 | J60: 0.56944502 | K60: 0.052913 | L60: 0.30404851 | M60: 0.069291284 | N60: 1.7317984 | O60: 1.0203986 | P60: 8.1832827 | Q60: 15.510406 | R60: 1.8281319 | S60: 12.850539 | T60: 0.13244522 | U60: 0.062104412 | V60: 0.018007465 | W60: 0.4428777 | X60: 0.0701365 | Y60: 3.3254219 | Z60: 3.3254219 | AA60: 0.066294977
A61: Power | B61: 46 | C61: 0.067353095 | D61: 0.21469957 | E61: 0.069218724 | F61: 0.13013681 | G61: 0.31457841 | H61: 0.48243267 | I61: 0.061016497 | J61: 0.25379989 | K61: 0.047306 | L61: 0.42577792 | M61: 0.050143408 | N61: 0.37173351 | O61: 4.6958065 | P61: 12.38141 | Q61: 21.859086 | R61: 2.275662 | S61: 24.741172 | T61: 0.03079341 | U61: 0.38694615 | V61: 0.24346144 | W61: 1.3095344 | X61: 0.12399094 | Y61: 0.54957892 | Z61: 0.54957892 | AA61: 0.21366596
A62: Precious Metals | B62: 56 | C62: 0.46045455 | D62: 0.40388775 | E62: 0.25451638 | F62: 0.28746597 | G62: 0.83089621 | H62: 0.83656065 | I62: 0.076810605 | J62: 0.69947204 | K62: 0.060195 | L62: 0.067869401 | M62: 0.074661564 | N62: 0.67779617 | O62: 5.981737 | P62: 10.676341 | Q62: 14.284668 | R62: 3.6400987 | S62: 26.798624 | T62: 0.090999514 | U62: 0.18183463 | V62: 0.06119649 | W62: 0.29453368 | X62: 0.23523057 | Y62: 0.25150956 | Z62: 0.25150956 | AA62: 0.40350161
A63: Publishing & Newspapers | B63: 19 | C63: 0.00039916667 | D63: 0.099826889 | E63: 0.17632773 | F63: 0.26800754 | G63: 0.51188407 | H63: 0.56300718 | I63: 0.06461012 | J63: 0.3592531 | K63: 0.050672 | L63: 0.19315716 | M63: 0.059470957 | N63: 2.1648897 | O63: 1.699407 | P63: 11.237818 | Q63: 17.161064 | R63: 2.2839416 | S63: 15.180437 | T63: 0.12891804 | U63: 0.032613426 | V63: -0.0059039318 | W63: 0.024902842 | X63: 0.13834734 | Y63: 0.23088767 | Z63: 0.23088767 | AA63: 0.099232969
... A71: Retail (Automotive) | B71: 34 | C71: 0.15421952 | D71: 0.062439261 | E71: 0.12190476 | F71: 0.22522513 | G71: 0.71324861 | H71: 0.9360152 | I71: 0.081246278 | J71: 0.44582096 | K71: 0.050672 | L71: 0.31203104 | M71: 0.067753345 | N71: 2.3410773 | O71: 1.2705674 | P71: 14.78729 | Q71: 21.726329 | R71: 7.47867 | S71: 54.826415 | T71: 0.11033017 | U71: 0.021234037 | V71: 0.022505842 | W71: 0.4617781 | X71: 0.34384065 | Y71: 0.067783399 | Z71: 0.067783399 | AA71: 0.058382589
A72: Retail (Building Supply) | B72: 14 | C72: 0.0073341667 | D72: 0.1193853 | E72: 0.34946565 | F72: 0.24093993 | G72: 1.3176571 | H72: 1.5353094 | I72: 0.1079748 | J72: 0.45883506 | K72: 0.052913 | L72: 0.18889907 | M72: 0.095074874 | N72: 3.4070573 | O72: 2.2589927 | P72: 14.422182 | Q72: 19.102772 | R72: 132.20441 | S72: 23.465277 | T72: 0.096073802 | U72: 0.024202085 | V72: 0.057548496 | W72: 0.73515548 | X72: NA | Y72: 0.54007474 | Z72: 0.54007474 | AA72: 0.11809039
A73: Retail (Distributors) | B73: 62 | C73: 0.10115167 | D73: 0.10097163 | E73: 0.16113991 | F73: 0.23404244 | G73: 0.80163203 | H73: 0.94843381 | I73: 0.081800148 | J73: 0.39292352 | K73: 0.050672 | L73: 0.22019001 | M73: 0.072156674 | N73: 1.8301306 | O73: 1.8948022 | P73: 13.708307 | Q73: 17.10909 | R73: 4.0417074 | S73: 28.796599 | T73: 0.17428164 | U73: 0.05615462 | V73: 0.11579269 | W73: 1.5220676 | X73: 0.18333732 | Y73: 0.35151399 | Z73: 0.35151399 | AA73: 0.10321021
A74: Retail (General) | B74: 23 | C74: 0.099217647 | D74: 0.068023334 | E74: 0.13590825 | F74: 0.19932835 | G74: 0.78092804 | H74: 0.80524054 | I74: 0.075413728 | J74: 0.43342746 | K74: 0.050672 | L74: 0.073591005 | M74: 0.072660709 | N74: 3.5063184 | O74: 2.1092146 | P74: 17.378503 | Q74: 32.437652 | R74: 7.1927071 | S74: 51.004021 | T74: -0.0010928699 | U74: 0.081751215 | V74: 0.048661673 | W74: 0.93965934 | X74: 0.26052308 | Y74: 0.1172686 | Z74: 0.1172686 | AA74: 0.071164331
A75: Retail (Grocery and Food) | B75: 15 | C75: -0.02634 | D75: 0.022919043 | E75: 0.067632196 | F75: 0.16832508 | G75: 0.84836112 | H75: 1.1183038 | I75: 0.089376349 | J75: 0.49422948 | K75: 0.052913 | L75: 0.34188953 | M75: 0.072387312 | N75: 4.6478966 | O75: 0.49009499 | P75: 8.9415966 | Q75: 26.533289 | R75: 3.9348694 | S75: 20.541451 | T75: 0.00061019594 | U75: -0.0012862785 | V75: -0.019020965 | W75: -0.98609577 | X75: 0.12897574 | Y75: 0.37436918 | Z75: 0.37436918 | AA75: 0.017271129
A76: Retail (REITs) | B76: 26 | C76: 0.131436 | D76: 0.40248289 | E76: 0.051639531 | F76: 0.015307416 | G76: 0.44271597 | H76: 0.62073902 | I76: 0.06718496 | J76: 0.18768911 | K76: 0.047306 | L76: 0.36069481 | M76: 0.055748965 | N76: 0.13581411 | O76: 12.043635 | P76: 16.726861 | Q76: 31.165271 | R76: 2.0756545 | S76: 368.68693 | T76: 0.012444392 | U76: 0.050373093 | V76: -0.22854658 | W76: -0.6131932 | X76: 0.063643754 | Y76: 1.6143339 | Z76: 1.6143339 | AA76: 0.38644409
A77: Retail (Special Lines) | B77: 94 | C77: 0.069604333 | D77: 0.077273545 | E77: 0.21539093 | F77: 0.24414952 | G77: 1.0018776 | H77: 1.0893997 | I77: 0.088087226 | J77: 0.53245167 | K77: 0.052913 | L77: 0.16500348 | M77: 0.080100649 | N77: 2.9884472 | O77: 1.6260839 | P77: 11.467549 | Q77: 20.017796 | R77: 7.2542633 | S77: 314.00976 | T77: 0.098028797 | U77: 0.034673938 | V77: 0.015903179 | W77: 0.38365406 | X77: 0.30115076 | Y77: 0.29933169 | Z77: 0.29933169 | AA77: 0.080751629
A78: Rubber& Tires | B78: 3 | C78: -0.13225 | D78: 0.022423699 | E78: 0.031681473 | F78: #DIV/0! | G78: 0.15435791 | H78: 0.52943016 | I78: 0.063112585 | J78: 0.5076716 | K78: 0.052913 | L78: 0.78188434 | M78: 0.044794728 | N78: 1.3941683 | O78: 0.5884476 | P78: 6.7440247 | Q78: 22.841629 | R78: 0.78914971 | S78: #DIV/0! | T78: 0.12928146 | U78: 0.050502596 | V78: -0.00032632867 | W78: 0.38647251 | X78: -0.36408001 | Y78: #DIV/0! | Z78: #DIV/0! | AA78: 0.024946979
A79: Semiconductor | B79: 66 | C79: 0.1117713 | D79: 0.35327792 | E79: 0.27226967 | F79: 0.15790418 | G79: 1.5046493 | H79: 1.5181994 | I79: 0.10721169 | J79: 0.55827208 | K79: 0.052913 | L79: 0.025256622 | M79: 0.10550619 | N79: 1.2066681 | O79: 15.700649 | P79: 34.753099 | Q79: 44.298631 | R79: 13.312176 | S79: 100.1844 | T79: 0.22617981 | U79: 0.10548971 | V79: 0.044119121 | W79: 0.35285798 | X79: 0.31364716 | Y79: 0.16392167 | Z79: 0.16392167 | AA79: 0.36466718
A80: Semiconductor Equip | B80: 31 | C80: 0.093788077 | D80: 0.26171175 | E80: 0.28404463 | F80: 0.17065978 | G80: 1.3916912 | H80: 1.3972234 | I80: 0.10181616 | J80: 0.50077409 | K80: 0.052913 | L80: 0.046359019 | M80: 0.098935813 | N80: 1.8511087 | O80: 7.607009 | P80: 24.743246 | Q80: 28.810672 | R80: 9.7025936 | S80: 46.825234 | T80: 0.29493567 | U80: 0.06315919 | V80: 0.041368684 | W80: 0.27453102 | X80: 0.35777973 | Y80: 0.19356444 | Z80: 0.19356444 | AA80: 0.268635
A81: Shipbuilding & Marine | B81: 8 | C81: -0.00118 | D81: 0.12602124 | E81: 0.11992333 | F81: 0.20577998 | G81: 0.6607668 | H81: 0.75293254 | I81: 0.073080791 | J81: 0.50086763 | K81: 0.052913 | L81: 0.18400784 | M81: 0.066935658 | N81: 0.93640073 | O81: 1.7362538 | P81: 7.9530075 | Q81: 12.812285 | R81: 1.4992122 | S81: 18.873177 | T81: 0.096277004 | U81: 0.11673422 | V81: 0.048918884 | W81: 0.36708063 | X81: 0.10153625 | Y81: 0.14665103 | Z81: 0.14665103 | AA81: 0.13517329
A82: Shoe | B82: 11 | C82: 0.12427286 | D82: 0.090349319 | E82: 0.20929697 | F82: 0.18953068 | G82: 1.0001868 | H82: 1.0173183 | I82: 0.084872397 | J82: 0.50082762 | K82: 0.052913 | L82: 0.10670202 | M82: 0.080050784 | N82: 2.6221001 | O82: 2.0409765 | P82: 16.86474 | Q82: 22.318822 | R82: 6.0602995 | S82: 24.474828 | T82: 0.16555339 | U82: 0.013260496 | V82: 0.0039925912 | W82: 0.19105787 | X82: 0.19489712 | Y82: 0.64930701 | Z82: 0.64930701 | AA82: 0.091491963
A83: Software (Entertainment) | B83: 77 | C83: 0.16715065 | D83: 0.33849712 | E83: 0.27019166 | F83: 0.22495566 | G83: 1.0206917 | H83: 1.0283112 | I83: 0.085362682 | J83: 0.57061844 | K83: 0.052913 | L83: 0.020036431 | M83: 0.084447459 | N83: 1.3447422 | O83: 9.1276447 | P83: 22.014235 | Q83: 26.976061 | R83: 9.0980952 | S83: 39.340288 | T83: 0.072479518 | U83: 0.22942391 | V83: 0.19521111 | W83: 0.82363942 | X83: 0.36508851 | Y83: 0.083369337 | Z83: 0.083369337 | AA83: 0.3600053
A84: Software (Internet) | B84: 29 | C84: 0.291795 | D84: 0.03686142 | E84: 0.034347802 | F84: 0.17146716 | G84: 1.5905251 | H84: 1.6886761 | I84: 0.11481495 | J84: 0.52612315 | K84: 0.052913 | L84: 0.10951942 | M84: 0.10658674 | N84: 1.3500968 | O84: 9.5610366 | P84: 30.260604 | Q84: 172.98954 | R84: 10.855737 | S84: 67.211437 | T84: 0.14797882 | U84: 0.33668277 | V84: 0.26011127 | W84: 14.142139 | X84: -0.014699622 | Y84: 0.00022003391 | Z84: 0.00022003391 | AA84: 0.047049008
A85: Software (System & Application) | B85: 309 | C85: 0.195645 | D85: 0.32982514 | E85: 0.29318429 | F85: 0.18011183 | G85: 1.2481994 | H85: 1.2766482 | I85: 0.096438509 | J85: 0.56789326 | K85: 0.052913 | L85: 0.052825189 | M85: 0.093440481 | N85: 1.5381716 | O85: 11.408764 | P85: 24.483536 | Q85: 32.412339 | R85: 9.1370897 | S85: 79.174209 | T85: 0.10046216 | U85: 0.17788285 | V85: 0.17820691 | W85: 0.73778745 | X85: 0.29624895 | Y85: 0.20984272 | Z85: 0.20984272 | AA85: 0.34449306
A86: Steel | B86: 19 | C86: 0.11373529 | D86: 0.04095918 | E86: 0.067202592 | F86: 0.20550382 | G86: 0.94494298 | H86: 1.0628462 | I86: 0.086902943 | J86: 0.38509855 | K86: 0.050672 | L86: 0.19036814 | M86: 0.077594142 | N86: 1.8036828 | O86: 1.1692375 | P86: 11.590978 | Q86: 24.559638 | R86: 1.8758163 | S86: 47.57536 | T86: 0.21605213 | U86: 0.065231828 | V86: 0.056934034 | W86: 2.1148871 | X86: 0.036791726 | Y86: 0.65060396 | Z86: 0.65060396 | AA86: 0.041069027
A87: Telecom (Wireless) | B87: 12 | C87: 0.037001429 | D87: 0.20980028 | E87: 0.1037202 | F87: 0.22927245 | G87: 0.39242084 | H87: 0.53813527 | I87: 0.063500833 | J87: 0.40181 | K87: 0.050672 | L87: 0.34187448 | M87: 0.054784117 | N87: 0.54775576 | O87: 3.7170395 | P87: 8.9741751 | Q87: 18.830187 | R87: 3.4718994 | S87: 107.13576 | T87: 0.12071905 | U87: 0.11640848 | V87: 0.0038185464 | W87: 0.16420321 | X87: 0.16061396 | Y87: 0.51447028 | Z87: 0.51447028 | AA87: 0.19749991
A88: Telecom. Equipment | B88: 57 | C88: 0.032719756 | D88: 0.20696765 | E88: 0.25473749 | F88: 0.16541221 | G88: 0.88725121 | H88: 0.92321958 | I88: 0.080675593 | J88: 0.55263055 | K88: 0.052913 | L88: 0.084439813 | M88: 0.077214334 | N88: 2.5677137 | O88: 6.5160941 | P88: 24.073936 | Q88: 30.863293 | R88: 8.3711164 | S88: 84.716084 | T88: 0.22251839 | U88: 0.028107684 | V88: 0.070725573 | W88: 0.46607193 | X88: 0.24956561 | Y88: 0.41449423 | Z88: 0.41449423 | AA88: 0.22011478
A89: Telecom. Services | B89: 39 | C89: 0.135675 | D89: 0.2047122 | E89: 0.12036567 | F89: 0.18485175 | G89: 0.38150036 | H89: 0.62872015 | I89: 0.067540919 | J89: 0.6028776 | K89: 0.052913 | L89: 0.4899604 | M89: 0.053892499 | N89: 0.60287258 | O89: 2.6148006 | P89: 6.5351995 | Q89: 12.21662 | R89: 1.6363123 | S89: 16.787716 | T89: -0.036879814 | U89: 0.16594862 | V89: 0.0090792852 | W89: 0.11954488 | X89: 0.19817526 | Y89: 0.47681709 | Z89: 0.47681709 | AA89: 0.2083637
A90: Tobacco | B90: 10 | C90: 0.02911 | D90: 0.43538236 | E90: 0.63077804 | F90: 0.20903825 | G90: 0.69029777 | H90: 0.79431458 | I90: 0.07492643 | J90: 0.65957987 | K90: 0.060195 | L90: 0.18678363 | M90: 0.06936398 | N90: 1.8241697 | O90: 6.3951929 | P90: 13.460904 | Q90: 14.631781 | R90: NA | S90: 23.208493 | T90: 0.16911807 | U90: 0.025026765 | V90: -0.0091008706 | W90: 0.02380472 | X90: NA | Y90: 0.87604668 | Z90: 0.87604668 | AA90: 0.43786583
A91: Transportation | B91: 19 | C91: 0.091208333 | D91: 0.075672221 | E91: 0.13000798 | F91: 0.15911875 | G91: 0.71152664 | H91: 0.85992193 | I91: 0.077852518 | J91: 0.38132941 | K91: 0.050672 | L91: 0.26712845 | M91: 0.067207845 | N91: 1.9753481 | O91: 1.6396952 | P91: 12.549963 | Q91: 21.450134 | R91: 4.7872604 | S91: 28.867828 | T91: 0.06961478 | U91: 0.049268418 | V91: 0.022045419 | W91: 0.51504794 | X91: 0.36582087 | Y91: 0.29122831 | Z91: 0.29122831 | AA91: 0.077057627
A92: Transportation (Railroads) | B92: 4 | C92: 0.0491 | D92: 0.37410886 | E92: 0.1423696 | F92: 0.22435743 | G92: 0.81372225 | H92: 0.97514575 | I92: 0.0829915 | J92: 0.23898486 | K92: 0.047306 | L92: 0.21747573 | M92: 0.072658793 | N92: 0.45813411 | O92: 6.6655597 | P92: 13.488179 | Q92: 17.8064 | R92: 5.8344576 | S92: 21.529368 | T92: 0.015600287 | U92: 0.17861929 | V92: 0.064676229 | W92: 0.20077787 | X92: 0.29067478 | Y92: 0.42695762 | Z92: 0.42695762 | AA92: 0.37433506
A93: Trucking | B93: 26 | C93: 0.033348824 | D93: 0.068918487 | E93: 0.092994575 | F93: 0.24561206 | G93: 0.86885074 | H93: 1.0113489 | I93: 0.084606162 | J93: 0.35290917 | K93: 0.050672 | L93: 0.20147981 | M93: 0.075216768 | N93: 1.4657207 | O93: 1.7429114 | P93: 10.412601 | Q93: 23.812231 | R93: 2.8578611 | S93: 37.422679 | T93: 0.07993963 | U93: 0.12911005 | V93: 0.050342454 | W93: 0.98712536 | X93: 0.076027212 | Y93: 0.28369762 | Z93: 0.28369762 | AA93: 0.073047483
A94: Utility (General) | B94: 14 | C94: 0.053321429 | D94: 0.23492113 | E94: 0.059946516 | F94: 0.14465964 | G94: 0.14911054 | H94: 0.23943493 | I94: 0.050178798 | J94: 0.14962031 | K94: 0.047306 | L94: 0.44898812 | M94: 0.043578988 | N94: 0.2961333 | O94: 5.2516061 | P94: 13.727015 | Q94: 22.630884 | R94: 1.8101871 | S94: 19.920098 | T94: 0.20049023 | U94: 0.47225699 | V94: 0.33575855 | W94: 1.723011 | X94: 0.10415515 | Y94: 0.65402725 | Z94: 0.65402725 | AA94: 0.23205484
A95: Utility (Water) | B95: 14 | C95: 0.13297417 | D95: 0.33715696 | E95: 0.07250661 | F95: 0.15939529 | G95: 0.28247289 | H95: 0.41268279 | I95: 0.057905653 | J95: 0.29598509 | K95: 0.047306 | L95: 0.38408264 | M95: 0.049292157 | N95: 0.24282144 | O95: 7.1563548 | P95: 14.138004 | Q95: 21.084503 | R95: 1.9952183 | S95: 23.065743 | T95: 0.12542693 | U95: 0.55839554 | V95: 0.43724649 | W95: 1.6217761 | X95: 0.17212373 | Y95: 0.56436244 | Z95: 0.34833424 | AA95: 0.33631528
A96: Total Market | B96: 5994 | C96: 0.12766196 | D96: 0.12817523 | E96: 0.089559104 | F96: 0.19379808 | G96: 0.75571687 | H96: 0.91211094 | I96: 0.080180148 | J96: 0.48066563 | K96: 0.052913 | L96: 0.2601977 | M96: 0.069643338 | N96: 0.82178503 | O96: 3.966336 | P96: 19.731928 | Q96: 29.124354 | R96: 4.605158 | S96: 57.863855 | T96: -0.21855771 | U96: 0.06574602 | V96: 0.042312135 | W96: 0.50822675 | X96: 0.17212373 | Y96: 0.34833424 | Z96: 0.34833424 | AA96: 0.12934935
A97: Total Market (without financials) | B97: 4822 | C97: 0.13745559 | D97: 0.13135589 | E97: 0.15070952 | F97: 0.19415954 | G97: 0.90096753 | H97: 0.99129597 | I97: 0.0837118 | J97: 0.52764819 | K97: 0.052913 | L97: 0.14739762 | M97: 0.077222318 | N97: 1.4337756 | O97: 3.4603093 | P97: 16.954952 | Q97: 25.696739 | R97: 5.4390458 | S97: 61.558599 | T97: 0.093011952 | U97: 0.071769802 | V97: 0.042914511 | W97: 0.4880881 | X97: 0.17602001 | Y97: 0.36652875 | Z97: 0.36652875 | AA97: 0.13262076

Sheet Industry Averages (Global)
A1: Industry Name | B1: Number of firms | C1: Annual Average Revenue growth - Last 5 years | D1: Pre-tax Operating Margin (Unadjusted) | E1: After-tax ROC | F1: Average effective tax rate | G1: Unlevered Beta | H1: Equity (Levered) Beta | I1: Cost of equity | J1: Std deviation in stock prices | K1: Pre-tax cost of debt | L1: Market Debt/Capital | M1: Cost of capital | N1: Sales/Capital | O1: EV/Sales | P1: EV/EBITDA | Q1: EV/EBIT | R1: Price/Book | S1: Trailing PE | T1: Non-cash WC as % of Revenues | U1: Cap Ex as % of Revenues | V1: Net Cap Ex as % of Revenues | W1: Reinvestment Rate | X1: ROE | Y1: Dividend Payout Ratio | Z1: Equity Reinvestment Rate | AA1: Pre-tax Operating Margin (Lease & R&D adjusted)
A2: Advertising | B2: 419 | C2: 0.076745945 | D2: 0.085452191 | E2: 0.17933658 | F2: 0.28222868 | G2: 1.0861161 | H2: 1.2728318 | I2: 0.11116043 | J2: 0.47819716 | K2: 0.060013 | L2: 0.28853432 | M2: 0.092009621 | N2: 2.5909095 | O2: 1.5220187 | P2: 11.079834 | Q2: 16.458569 | R2: 2.4786291 | S2: 41.37644 | T2: -0.0073906326 | U2: 0.01732372 | V2: 0.0057756919 | W2: 0.10941577 | X2: 0.031191241 | Y2: 1.9498371 | Z2: 1.9498371 | AA2: 0.086510348
A3: Aerospace/Defense | B3: 319 | C3: 0.10030114 | D3: 0.091785083 | E3: 0.15462665 | F3: 0.17514058 | G3: 1.1666843 | H3: 1.2309446 | I3: 0.10880218 | J3: 0.46535363 | K3: 0.060013 | L3: 0.11504766 | M3: 0.10143747 | N3: 2.4649199 | O3: 3.3852461 | P3: 22.398823 | Q3: 33.084863 | R3: 6.7223106 | S3: 189.88009 | T3: 0.39306133 | U3: 0.038049228 | V3: 0.01515166 | W3: 0.70152599 | X3: 0.18449738 | Y3: 0.37819312 | Z3: 0.37819312 | AA3: 0.093895757
A4: Air Transport | B4: 150 | C4: 0.20654283 | D4: 0.082094463 | E4: 0.090134673 | F4: 0.21456415 | G4: 0.68406216 | H4: 0.99062514 | I4: 0.095272195 | J4: 0.33634516 | K4: 0.057772 | L4: 0.44098281 | M4: 0.072271876 | N4: 1.3140399 | O4: 1.3978077 | P4: 9.0706373 | Q4: 16.921627 | R4: 2.4821394 | S4: 26.881788 | T4: -0.03529494 | U4: 0.099342115 | V4: 0.033353335 | W4: 0.47696585 | X4: 0.17282238 | Y4: 0.38739412 | Z4: 0.38739412 | AA4: 0.080857456
A5: Apparel | B5: 1207 | C5: 0.096144456 | D5: 0.12594925 | E5: 0.16066581 | F5: 0.2763687 | G5: 0.70526666 | H5: 0.76241742 | I5: 0.0824241 | J5: 0.40912735 | K5: 0.057772 | L5: 0.15757308 | M5: 0.076230083 | N5: 1.5206366 | O5: 2.3109205 | P5: 14.048028 | Q5: 17.703043 | R5: 3.2869237 | S5: 59.310109 | T5: 0.22335673 | U5: 0.043508277 | V5: 0.020751623 | W5: 0.39847495 | X5: 0.13544442 | Y5: 0.49506428 | Z5: 0.49506428 | AA5: 0.12717973
A6: Auto & Truck | B6: 165 | C6: 0.1418665 | D6: 0.043126597 | E6: 0.043290712 | F6: 0.23906736 | G6: 1.1453824 | H6: 1.4059578 | I6: 0.11865543 | J6: 0.46544045 | K6: 0.060013 | L6: 0.32345904 | M6: 0.094762243 | N6: 1.1904804 | O6: 1.5038989 | P6: 17.287729 | Q6: 33.703035 | R6: 2.1101816 | S6: 64.095234 | T6: -0.025209136 | U6: 0.0628766 | V6: 0.035242374 | W6: 0.77772272 | X6: 0.06229174 | Y6: 0.5043075 | Z6: 0.5043075 | AA6: 0.046898863
A7: Auto Parts | B7: 797 | C7: 0.11602434 | D7: 0.054480013 | E7: 0.12916441 | F7: 0.24466346 | G7: 1.3534719 | H7: 1.4498213 | I7: 0.12112494 | J7: 0.38549791 | K7: 0.057772 | L7: 0.21752689 | M7: 0.10415573 | N7: 1.9786936 | O7: 0.96013578 | P7: 9.2345813 | Q7: 16.773405 | R7: 1.7096649 | S7: 84.425729 | T7: 0.11370763 | U7: 0.049106591 | V7: 0.031020237 | W7: 0.88436552 | X7: 0.065575405 | Y7: 0.48556789 | Z7: 0.48556789 | AA7: 0.05854135
A8: Bank (Money Center) | B8: 604 | C8: 0.19201112 | D8: 0.0037641733 | E8: NA | F8: 0.19611446 | G8: 0.36276505 | H8: 0.69749392 | I8: 0.078768908 | J8: 0.24567454 | K8: 0.054406 | L8: 0.67919987 | M8: 0.052846763 | N8: 0.13566891 | O8: 8.9153445 | P8: NA | Q8: NA | R8: 1.1371162 | S8: 23.380454 | T8: NA | U8: 0.037721055 | V8: 0.041410341 | W8: 0.052846763 | X8: 0.11544843 | Y8: 0.38673892 | Z8: 0.38673892 | AA8: 0.0039644354
A9: Banks (Regional) | B9: 825 | C9: 0.083853528 | D9: -1.8435659e-05 | E9: NA | F9: 0.18880322 | G9: 0.30036338 | H9: 0.51348722 | I9: 0.068409331 | J9: 0.23331977 | K9: 0.054406 | L9: 0.66917597 | M9: 0.049802135 | N9: 0.1560153 | O9: 6.8532133 | P9: NA | Q9: NA | R9: 0.85212493 | S9: 27.962829 | T9: NA | U9: 0.028693976 | V9: 0.01112152 | W9: NA | X9: 0.087436368 | Y9: 0.32409425 | Z9: 0.32409425 | AA9: -0.00049850576
A10: Beverage (Alcoholic) | B10: 217 | C10: 0.086233672 | D10: 0.22468694 | E10: 0.15417973 | F10: 0.26136765 | G10: 0.72504434 | H10: 0.79267085 | I10: 0.084127369 | J10: 0.34009242 | K10: 0.057772 | L10: 0.16869941 | M10: 0.077208647 | N10: 0.84291436 | O10: 3.3175622 | P10: 12.21587 | Q10: 14.665541 | R10: 2.7921965 | S10: 46.917794 | T10: 0.10893906 | U10: 0.049423525 | V10: 0.021503715 | W10: 0.13508667 | X10: 0.13685546 | Y10: 0.64822627 | Z10: 0.64822627 | AA10: 0.2240047
A11: Beverage (Soft) | B11: 94 | C11: 0.11468485 | D11: 0.1762373 | E11: 0.25367509 | F11: 0.21506479 | G11: 0.54202266 | H11: 0.59284847 | I11: 0.072877369 | J11: 0.36929595 | K11: 0.057772 | L11: 0.15768331 | M11: 0.068184378 | N11: 1.6840589 | O11: 3.4794285 | P11: 15.969846 | Q11: 19.56847 | R11: 5.7647977 | S11: 25.617474 | T11: -0.042591796 | U11: 0.05084833 | V11: 0.040172242 | W11: 0.32840707 | X11: 0.25987069 | Y11: 0.69256828 | Z11: 0.69256828 | AA11: 0.17694003
A12: Broadcasting | B12: 127 | C12: 0.043784352 | D12: 0.09974561 | E12: 0.095050746 | F12: 0.27392189 | G12: 0.65577076 | H12: 0.83217283 | I12: 0.08635133 | J12: 0.40484514 | K12: 0.057772 | L12: 0.36213202 | M12: 0.070694159 | N12: 1.1246826 | O12: 1.2839663 | P12: 8.4709855 | Q12: 12.461419 | R12: 1.1466147 | S12: 24.090047 | T12: 0.1149106 | U12: 0.030683734 | V12: -0.015735499 | W12: 1.1906895 | X12: 0.04473782 | Y12: 0.69642169 | Z12: 0.69642169 | AA12: 0.099906613
A13: Brokerage & Investment Banking | B13: 623 | C13: 0.20560422 | D13: 0.0093698089 | E13: NA | F13: 0.20657152 | G13: 0.48957376 | H13: 0.98461363 | I13: 0.094933747 | J13: 0.40964257 | K13: 0.057772 | L13: 0.64175212 | M13: 0.061679113 | N13: 0.22058932 | O13: 6.425086 | P13: NA | Q13: NA | R13: 1.8268437 | S13: 53.98422 | T13: -1.3519203 | U13: 0.020559316 | V13: -0.023277605 | W13: -18.278264 | X13: 0.12620582 | Y13: 0.3937462 | Z13: 0.3937462 | AA13: 0.0091983036
A14: Building Materials | B14: 469 | C14: 0.061503544 | D14: 0.10401328 | E14: 0.14189101 | F14: 0.24573049 | G14: 0.90272059 | H14: 1.0048303 | I14: 0.096071946 | J14: 0.34630654 | K14: 0.057772 | L14: 0.18553156 | M14: 0.086246807 | N14: 1.7360449 | O14: 1.8851037 | P14: 12.41049 | Q14: 17.772731 | R14: 2.7929305 | S14: 50.228683 | T14: 0.17644316 | U14: 0.042207216 | V14: 0.038512896 | W14: 0.56785324 | X14: 0.11996231 | Y14: 0.39406338 | Z14: 0.39406338 | AA14: 0.10596457
A15: Business & Consumer Services | B15: 994 | C15: 0.083179853 | D15: 0.10145314 | E15: 0.22092321 | F15: 0.24059858 | G15: 0.90833038 | H15: 0.99214598 | I15: 0.095357818 | J15: 0.39436765 | K15: 0.057772 | L15: 0.17086022 | M15: 0.086431641 | N15: 2.79812 | O15: 2.0384942 | P15: 14.086673 | Q15: 19.477307 | R15: 4.3125071 | S15: 33.30317 | T15: 0.10866958 | U15: 0.024349921 | V15: 0.018476981 | W15: 0.33068335 | X15: 0.1526748 | Y15: 0.50109927 | Z15: 0.50109927 | AA15: 0.10179071
A16: Cable TV | B16: 42 | C16: 0.043443243 | D16: 0.17336966 | E16: 0.11149965 | F16: 0.1902468 | G16: 0.59082963 | H16: 1.0969953 | I16: 0.10126083 | J16: 0.39026855 | K16: 0.057772 | L16: 0.55390186 | M16: 0.069053883 | N16: 0.72895459 | O16: 2.1610559 | P16: 6.5773423 | Q16: 12.474747 | R16: 1.3822539 | S16: 69.657037 | T16: 0.025634574 | U16: 0.12531088 | V16: -0.008462237 | W16: -0.06103698 | X16: 0.081176793 | Y16: 0.42750809 | Z16: 0.42750809 | AA16: 0.17080424
A17: Chemical (Basic) | B17: 909 | C17: 0.10223551 | D17: 0.036835266 | E17: 0.031507248 | F17: 0.1952137 | G17: 1.0021473 | H17: 1.2560258 | I17: 0.11021425 | J17: 0.37696586 | K17: 0.057772 | L17: 0.33545863 | M17: 0.087705309 | N17: 1.026596 | O17: 1.430356 | P17: 13.707313 | Q17: 36.464576 | R17: 1.4473317 | S17: 114.41924 | T17: 0.11984859 | U17: 0.080071672 | V17: 0.042695071 | W17: 1.3872652 | X17: -0.0055737826 | Y17: 0.025793856 | Z17: 0.025793856 | AA17: 0.037706629
A18: Chemical (Diversified) | B18: 63 | C18: 0.086664138 | D18: 0.068293068 | E18: 0.063870085 | F18: 0.26198786 | G18: 0.91005713 | H18: 1.1692025 | I18: 0.1053261 | J18: 0.29763352 | K18: 0.054406 | L18: 0.34434463 | M18: 0.083039118 | N18: 1.2117164 | O18: 1.095332 | P18: 8.6548627 | Q18: 16.003235 | R18: 1.2490654 | S18: 25.310458 | T18: 0.20949169 | U18: 0.071448634 | V18: 0.037655674 | W18: 0.78799215 | X18: 0.046123814 | Y18: 0.94795797 | Z18: 0.94795797 | AA18: 0.071862354
A19: Chemical (Specialty) | B19: 952 | C19: 0.10482979 | D19: 0.10965894 | E19: 0.095119638 | F19: 0.23685845 | G19: 1.0428069 | H19: 1.1536266 | I19: 0.10444918 | J19: 0.39445615 | K19: 0.057772 | L19: 0.19038263 | M19: 0.09277226 | N19: 1.086801 | O19: 2.3691472 | P19: 13.104221 | Q19: 21.132217 | R19: 2.305932 | S19: 71.552482 | T19: 0.18885179 | U19: 0.08356948 | V19: 0.040597436 | W19: 0.57140532 | X19: 0.077549893 | Y19: 0.63229331 | Z19: 0.63229331 | AA19: 0.11140825
A20: Coal & Related Energy | B20: 212 | C20: 0.14176458 | D20: 0.16038093 | E20: 0.14153395 | F20: 0.22533691 | G20: 1.1330049 | H20: 1.1429397 | I20: 0.10384751 | J20: 0.58632036 | K20: 0.060013 | L20: 0.1659934 | M20: 0.09404397 | N20: 1.0181419 | O20: 2.1384941 | P20: 7.9635025 | Q20: 12.448276 | R20: 1.7027591 | S20: 55.838223 | T20: -0.031823864 | U20: 0.1531793 | V20: 0.079806456 | W20: 0.81019142 | X20: 0.10643058 | Y20: 0.14573565 | Z20: 0.14573565 | AA20: 0.16005609
A21: Computer Services | B21: 1225 | C21: 0.13624416 | D21: 0.075597156 | E21: 0.20955306 | F21: 0.24110451 | G21: 1.071577 | H21: 1.1166905 | I21: 0.10236967 | J21: 0.4251425 | K21: 0.057772 | L21: 0.13053619 | M21: 0.094634826 | N21: 3.7546966 | O21: 1.4626915 | P21: 14.621894 | Q21: 18.50679 | R21: 3.9884478 | S21: 57.152492 | T21: 0.2986624 | U21: 0.011275004 | V21: 0.012956213 | W21: 0.32046959 | X21: 0.17122492 | Y21: 0.53088936 | Z21: 0.53088936 | AA21: 0.076996906
A22: Computers/Peripherals | B22: 343 | C22: 0.032691413 | D22: 0.12611613 | E22: 0.19910185 | F22: 0.15211534 | G22: 1.4681983 | H22: 1.4861047 | I22: 0.12316769 | J22: 0.43558637 | K22: 0.057772 | L22: 0.058294054 | M22: 0.11850111 | N22: 2.4835357 | O22: 3.4019645 | P22: 20.176314 | Q22: 26.728442 | R22: 8.1089832 | S22: 72.095691 | T22: 0.046850124 | U22: 0.046586911 | V22: 0.044700951 | W22: 0.56360632 | X22: 0.27703945 | Y22: 0.22782298 | Z22: 0.22782298 | AA22: 0.13089454
A23: Construction Supplies | B23: 804 | C23: 0.10728847 | D23: 0.09709673 | E23: 0.092923831 | F23: 0.21799753 | G23: 0.91667626 | H23: 1.0343956 | I23: 0.097736471 | J23: 0.37316872 | K23: 0.057772 | L23: 0.23237459 | M23: 0.085043886 | N23: 1.2257629 | O23: 1.8011434 | P23: 12.309509 | Q23: 18.066293 | R23: 2.085552 | S23: 113.95372 | T23: 0.17410989 | U23: 0.05039693 | V23: 0.032587182 | W23: 0.50303622 | X23: 0.1231368 | Y23: 0.38082412 | Z23: 0.38082412 | AA23: 0.098755587
A24: Diversified | B24: 329 | C24: 0.15288022 | D24: 0.15113019 | E24: 0.089848677 | F24: 0.18662195 | G24: 0.6525744 | H24: 0.79738817 | I24: 0.084392954 | J24: 0.30019575 | K24: 0.057772 | L24: 0.32661305 | M24: 0.070911115 | N24: 0.71301823 | O24: 2.1426109 | P24: 10.935986 | Q24: 13.877966 | R24: 1.2190832 | S24: 30.903742 | T24: 0.060473079 | U24: 0.050497475 | V24: 0.041189705 | W24: 0.39409375 | X24: 0.089405981 | Y24: 0.22755379 | Z24: 0.22755379 | AA24: 0.15142427
A25: Drugs (Biotechnology) | B25: 1193 | C25: 0.27468802 | D25: 0.074763139 | E25: 0.029942515 | F25: 0.15147359 | G25: 1.1808092 | H25: 1.2307901 | I25: 0.10879348 | J25: 0.65511569 | K25: 0.067295 | L25: 0.10992343 | M25: 0.10235513 | N25: 0.71371067 | O25: 7.9412425 | P25: 16.713926 | Q25: 77.687254 | R25: 6.1699101 | S25: 161.43637 | T25: 0.20611857 | U25: 0.041258812 | V25: -0.0087757114 | W25: 0.28840134 | X25: -0.032409081 | Y25: 0.0030828405 | Z25: 0.0030828405 | AA25: 0.077118143
... A34: Farming/Agriculture | B34: 428 | C34: 0.14780628 | D34: 0.063909443 | E34: 0.067788851 | F34: 0.22874729 | G34: 0.4926715 | H34: 0.66989834 | I34: 0.077215277 | J34: 0.36166808 | K34: 0.057772 | L34: 0.37123 | M34: 0.064556321 | N34: 1.2977622 | O34: 1.2207886 | P34: 12.908282 | Q34: 18.578627 | R34: 1.6966401 | S34: 48.07524 | T34: 0.18536822 | U34: 0.040750088 | V34: 0.027366646 | W34: 0.40680701 | X34: 0.09833823 | Y34: 0.44472078 | Z34: 0.44472078 | AA34: 0.064952775
A35: Financial Svcs. (Non-bank & Insurance) | B35: 1138 | C35: 0.17024585 | D35: 0.14125586 | E35: NA | F35: 0.17404998 | G35: 0.29511483 | H35: 0.82348795 | I35: 0.085862372 | J35: 0.41344469 | K35: 0.057772 | L35: 0.72588807 | M35: 0.054832741 | N35: 0.093708297 | O35: 13.715456 | P35: 43.421409 | Q35: 52.914941 | R35: 2.3783453 | S35: 36.779696 | T35: NA | U35: 0.037714314 | V35: 0.016297813 | W35: 0.17590846 | X35: 0.18825468 | Y35: 0.25599296 | Z35: 0.25599296 | AA35: 0.14288623
A36: Food Processing | B36: 1450 | C36: 0.096518457 | D36: 0.085358248 | E36: 0.1197351 | F36: 0.22517313 | G36: 0.56022535 | H36: 0.67372445 | I36: 0.077430687 | J36: 0.33904801 | K36: 0.057772 | L36: 0.27061921 | M36: 0.068144269 | N36: 1.7085377 | O36: 1.3434508 | P36: 11.072076 | Q36: 15.460106 | R36: 2.1902573 | S36: 39.767228 | T36: 0.10570016 | U36: 0.041010741 | V36: 0.020243842 | W36: 0.37750592 | X36: 0.10543172 | Y36: 0.73326113 | Z36: 0.73326113 | AA36: 0.085970318
A37: Food Wholesalers | B37: 183 | C37: 0.17566223 | D37: 0.025419702 | E37: 0.10674988 | F37: 0.24136111 | G37: 0.49887742 | H37: 0.68481759 | I37: 0.07805523 | J37: 0.3599067 | K37: 0.057772 | L37: 0.36806255 | M37: 0.06519513 | N37: 5.1703357 | O37: 0.40639245 | P37: 10.430922 | Q37: 16.010708 | R37: 2.4876217 | S37: 38.004589 | T37: 0.067598406 | U37: 0.011302319 | V37: 0.010736175 | W37: 1.0489393 | X37: 0.097394054 | Y37: 0.52831597 | Z37: 0.52831597 | AA37: 0.025079007
A38: Furn/Home Furnishings | B38: 383 | C38: 0.058265655 | D38: 0.076458434 | E38: 0.1260785 | F38: 0.17632848 | G38: 0.93838443 | H38: 0.96750967 | I38: 0.093970794 | J38: 0.37311961 | K38: 0.057772 | L38: 0.20462935 | M38: 0.083564256 | N38: 2.2730023 | O38: 1.159142 | P38: 10.626402 | Q38: 14.661645 | R38: 2.1488891 | S38: 46.60816 | T38: 0.060104273 | U38: 0.02833441 | V38: 0.022740232 | W38: 0.32721425 | X38: 0.12494717 | Y38: 0.67468069 | Z38: 0.67468069 | AA38: 0.077763804
A39: Green & Renewable Energy | B39: 258 | C39: 0.15465707 | D39: 0.27720882 | E39: 0.054897204 | F39: 0.16816571 | G39: 0.56680021 | H39: 0.83665283 | I39: 0.086603555 | J39: 0.39025685 | K39: 0.057772 | L39: 0.41667017 | M39: 0.068483272 | N39: 0.22394012 | O39: 7.3845705 | P39: 14.174838 | Q39: 23.765294 | R39: 1.8561252 | S39: 72.000571 | T39: 0.10292914 | U39: 0.57851582 | V39: 0.43682913 | W39: 2.109526 | X39: 0.055770978 | Y39: 1.0941593 | Z39: 1.0941593 | AA39: 0.27635817
A40: Healthcare Products | B40: 842 | C40: 0.14872042 | D40: 0.14274902 | E40: 0.13700397 | F40: 0.1760816 | G40: 1.1165103 | H40: 1.1819539 | I40: 0.10604401 | J40: 0.48390168 | K40: 0.060013 | L40: 0.12173942 | M40: 0.098586699 | N40: 1.2979371 | O40: 4.1721894 | P40: 18.549205 | Q40: 28.097614 | R40: 3.5309571 | S40: 86.012621 | T40: 0.26748557 | U40: 0.048420565 | V40: 0.040250488 | W40: 0.49141192 | X40: 0.090633294 | Y40: 0.47633956 | Z40: 0.47633956 | AA40: 0.14784297
A41: Healthcare Support Services | B41: 478 | C41: 0.099016014 | D41: 0.031032762 | E41: 0.20715331 | F41: 0.23729866 | G41: 0.77867157 | H41: 0.91655887 | I41: 0.091102264 | J41: 0.42402591 | K41: 0.057772 | L41: 0.2760246 | M41: 0.077856666 | N41: 8.0174903 | O41: 0.49023076 | P41: 11.287497 | Q41: 15.306775 | R41: 2.3059157 | S41: 96.39308 | T41: -0.025456123 | U41: 0.0069874459 | V41: 0.0079490355 | W41: 0.51203697 | X41: 0.084916051 | Y41: 0.53884773 | Z41: 0.53884773 | AA41: 0.031139757
A42: Heathcare Information and Technology | B42: 430 | C42: 0.12983553 | D42: 0.14787856 | E42: 0.12540078 | F42: 0.16974673 | G42: 1.2072494 | H42: 1.2899202 | I42: 0.11212251 | J42: 0.54353116 | K42: 0.060013 | L42: 0.1224871 | M42: 0.10387486 | N42: 1.0860178 | O42: 5.3224395 | P42: 20.956994 | Q42: 33.858261 | R42: 3.8670023 | S42: 321.79835 | T42: 0.24363886 | U42: 0.067081032 | V42: 0.036492187 | W42: 0.38425826 | X42: 0.079344508 | Y42: 0.1919091 | Z42: 0.1919091 | AA42: 0.14950916
A43: Homebuilding | B43: 160 | C43: 0.071725865 | D43: 0.10714293 | E43: 0.10363609 | F43: 0.24790571 | G43: 0.8223996 | H43: 0.96023095 | I43: 0.093561003 | J43: 0.32374033 | K43: 0.057772 | L43: 0.28520807 | M43: 0.079173465 | N43: 1.2692986 | O43: 1.1420543 | P43: 9.4297074 | Q43: 11.072665 | R43: 1.3649958 | S43: 23.786707 | T43: 0.67330954 | U43: 0.0057214845 | V43: 0.0057189247 | W43: 0.49894474 | X43: 0.11465151 | Y43: 0.243973 | Z43: 0.243973 | AA43: 0.10190992
A44: Hospitals/Healthcare Facilities | B44: 249 | C44: 0.14257274 | D44: 0.12268 | E44: 0.13209803 | F44: 0.20444742 | G44: 0.58385149 | H44: 0.76017993 | I44: 0.08229813 | J44: 0.36000623 | K44: 0.057772 | L44: 0.31779435 | M44: 0.06984603 | N44: 1.3636038 | O44: 2.133976 | P44: 11.887709 | Q44: 17.798321 | R44: 3.5496561 | S44: 46.055186 | T44: 0.056747386 | U44: 0.06792172 | V44: 0.032702157 | W44: 0.36362106 | X44: 0.17643007 | Y44: 0.27117854 | Z44: 0.27117854 | AA44: 0.11911369
A45: Hotel/Gaming | B45: 656 | C45: 0.18380844 | D45: 0.1666411 | E45: 0.11804603 | F45: 0.18993969 | G45: 0.65622445 | H45: 0.79843024 | I45: 0.084451622 | J45: 0.39273903 | K45: 0.057772 | L45: 0.28693765 | M45: 0.072590659 | N45: 0.94173142 | O45: 3.4487041 | P45: 13.868182 | Q45: 22.122563 | R45: 4.5374402 | S45: 74.501159 | T45: -0.037025643 | U45: 0.070659022 | V45: 0.019420093 | W45: 0.224434 | X45: 0.18953049 | Y45: 0.36702024 | Z45: 0.36702024 | AA45: 0.15597411
A46: Household Products | B46: 588 | C46: 0.082152809 | D46: 0.16171888 | E46: 0.23080676 | F46: 0.23569724 | G46: 0.77414442 | H46: 0.8301059 | I46: 0.086234962 | J46: 0.40417663 | K46: 0.057772 | L46: 0.13550276 | M46: 0.080392121 | N46: 1.7936711 | O46: 2.9023577 | P46: 14.555485 | Q46: 17.738636 | R46: 4.6257308 | S46: 68.847671 | T46: 0.059261117 | U46: 0.038526388 | V46: 0.021917689 | W46: 0.23698494 | X46: 0.18014873 | Y46: 0.72418689 | Z46: 0.72418689 | AA46: 0.16336752
A47: Information Services | B47: 86 | C47: 0.10515932 | D47: 0.11783275 | E47: 0.22813484 | F47: 0.25689126 | G47: 0.87373595 | H47: 1.0237206 | I47: 0.097135469 | J47: 0.38002787 | K47: 0.057772 | L47: 0.24231102 | M47: 0.084045773 | N47: 2.7131089 | O47: 1.8827179 | P47: 10.769732 | Q47: 15.450293 | R47: 3.285101 | S47: 36.746985 | T47: 0.14122948 | U47: 0.018928977 | V47: -0.015897942 | W47: -0.1629085 | X47: 0.14547766 | Y47: 0.3744722 | Z47: 0.3744722 | AA47: 0.11761319
... A50: Insurance (Prop/Cas.) | B50: 248 | C50: 0.12782213 | D50: 0.15264312 | E50: 0.18054615 | F50: 0.20891717 | G50: 0.41237143 | H50: 0.43182655 | I50: 0.063811835 | J50: 0.29536018 | K50: 0.054406 | L50: 0.14042645 | M50: 0.060552728 | N50: 1.465086 | O50: 1.3174858 | P50: 7.8152889 | Q50: 8.5778219 | R50: 1.6744186 | S50: 20.508619 | T50: -0.25821113 | U50: 0.0057689237 | V50: -0.0041756797 | W50: -0.094639355 | X50: 0.17152714 | Y50: 0.26560948 | Z50: 0.26560948 | AA50: 0.15285165
A51: Investments & Asset Management | B51: 1315 | C51: 0.17761107 | D51: 0.2505039 | E51: 0.082955665 | F51: 0.17551747 | G51: 0.56571305 | H51: 0.7483402 | I51: 0.081631554 | J51: 0.36856677 | K51: 0.057772 | L51: 0.3763209 | M51: 0.067137061 | N51: 0.35945157 | O51: 5.4454341 | P51: 19.002309 | Q51: 16.954572 | R51: 1.7488433 | S51: 53.852283 | T51: NA | U51: 0.046574537 | V51: 0.16099299 | W51: 0.97547167 | X51: 0.12013792 | Y51: 0.49503943 | Z51: 0.49503943 | AA51: 0.2495005
A52: Machinery | B52: 1553 | C52: 0.086788978 | D52: 0.1035706 | E52: 0.1183512 | F52: 0.22163071 | G52: 1.3296217 | H52: 1.3694738 | I52: 0.11660137 | J52: 0.40339936 | K52: 0.057772 | L52: 0.11937485 | M52: 0.10782898 | N52: 1.4800813 | O52: 2.6137494 | P52: 16.88409 | Q52: 23.606059 | R52: 3.3723961 | S52: 88.383344 | T52: 0.29122462 | U52: 0.04054885 | V52: 0.033716446 | W52: 0.54506658 | X52: 0.10900842 | Y52: 0.45978918 | Z52: 0.45978918 | AA52: 0.10661971
A53: Metals & Mining | B53: 1874 | C53: 0.2560405 | D53: 0.10725367 | E53: 0.13657806 | F53: 0.29838738 | G53: 1.1256104 | H53: 1.2362712 | I53: 0.10910207 | J53: 0.74739926 | K53: 0.067295 | L53: 0.18727151 | M53: 0.098075559 | N53: 1.3473023 | O53: 1.8438366 | P53: 10.690728 | Q53: 15.978245 | R53: 2.5662226 | S53: 77.31382 | T53: 0.127685 | U53: 0.080352821 | V53: 0.058111349 | W53: 0.92867066 | X53: 0.091323864 | Y53: 0.68474798 | Z53: 0.68474798 | AA53: 0.10886955
A54: Office Equipment & Services | B54: 139 | C54: 0.046683918 | D54: 0.077285023 | E54: 0.12615897 | F54: 0.25463182 | G54: 0.71130139 | H54: 0.75869634 | I54: 0.082214604 | J54: 0.36872238 | K54: 0.057772 | L54: 0.22220736 | M54: 0.073526438 | N54: 2.0880814 | O54: 1.0768467 | P54: 9.1443038 | Q54: 13.485344 | R54: 1.7950847 | S54: 24.584696 | T54: 0.15005817 | U54: 0.032486452 | V54: 0.025494474 | W54: 0.59854907 | X54: 0.087389215 | Y54: 0.65491358 | Z54: 0.65491358 | AA54: 0.078439955
A55: Oil/Gas (Integrated) | B55: 34 | C55: 0.10255882 | D55: 0.1427195 | E55: 0.13876687 | F55: 0.44047647 | G55: 0.63246762 | H55: 0.68873306 | I55: 0.078275671 | J55: 0.29124734 | K55: 0.054406 | L55: 0.17764359 | M55: 0.071583398 | N55: 1.368596 | O55: 1.3261821 | P55: 6.1816709 | Q55: 9.2501824 | R55: 1.7150982 | S55: 15.630274 | T55: 0.025364589 | U55: 0.090393484 | V55: 0.017564475 | W55: 0.24939617 | X55: 0.12207066 | Y55: 0.79868863 | Z55: 0.79868863 | AA55: 0.14343879
A56: Oil/Gas (Production and Exploration) | B56: 539 | C56: 0.22485934 | D56: 0.28507903 | E56: 0.14869476 | F56: 0.35056253 | G56: 0.74638546 | H56: 0.88555547 | I56: 0.089356773 | J56: 0.53918089 | K56: 0.060013 | L56: 0.26371021 | M56: 0.077603454 | N56: 0.57279996 | O56: 2.5887742 | P56: 4.8365686 | Q56: 8.9258907 | R56: 1.3314467 | S56: 28.760501 | T56: 0.011403499 | U56: 0.33688213 | V56: 0.18527236 | W56: 0.92668523 | X56: 0.11803733 | Y56: 0.54791967 | Z56: 0.54791967 | AA56: 0.28666969
A57: Oil/Gas Distribution | B57: 186 | C57: 0.095912556 | D57: 0.17241838 | E57: 0.091910737 | F57: 0.18682801 | G57: 0.46115425 | H57: 0.65347789 | I57: 0.076290805 | J57: 0.33957385 | K57: 0.057772 | L57: 0.38095835 | M57: 0.063652298 | N57: 0.60444368 | O57: 3.0539574 | P57: 11.78253 | Q57: 17.430604 | R57: 2.0987569 | S57: 27.829396 | T57: 0.026151137 | U57: 0.14977795 | V57: 0.10783598 | W57: 0.79162662 | X57: 0.130452 | Y57: 0.81793017 | Z57: 0.81793017 | AA57: 0.17337523
A58: Oilfield Svcs/Equip. | B58: 431 | C58: 0.11601197 | D58: 0.050075117 | E58: 0.09059301 | F58: 0.23026198 | G58: 0.79965087 | H58: 0.948236 | I58: 0.092885687 | J58: 0.42213804 | K58: 0.057772 | L58: 0.28399113 | M58: 0.078751323 | N58: 2.0987906 | O58: 0.75986786 | P58: 8.8303368 | Q58: 14.493305 | R58: 1.5428329 | S58: 41.452063 | T58: 0.054751487 | U58: 0.042127442 | V58: 0.021610463 | W58: 0.28896628 | X58: 0.08264224 | Y58: 0.55553866 | Z58: 0.55553866 | AA58: 0.050896823
A59: Packaging & Container | B59: 438 | C59: 0.078556687 | D59: 0.078360145 | E59: 0.09283257 | F59: 0.23255421 | G59: 0.57555244 | H59: 0.75913513 | I59: 0.082239308 | J59: 0.34411707 | K59: 0.057772 | L59: 0.3448933 | M59: 0.06874568 | N59: 1.4251533 | O59: 1.3795754 | P59: 9.5623667 | Q59: 17.041244 | R59: 1.6186188 | S59: 38.912058 | T59: 0.15662244 | U59: 0.060653474 | V59: 0.039613627 | W59: 0.84282629 | X59: 0.085799385 | Y59: 0.66060121 | Z59: 0.66060121 | AA59: 0.080003259
A60: Paper/Forest Products | B60: 271 | C60: 0.069212857 | D60: 0.042965672 | E60: 0.029128132 | F60: 0.22255766 | G60: 0.61065401 | H60: 0.88869034 | I60: 0.089533266 | J60: 0.36751022 | K60: 0.057772 | L60: 0.43845709 | M60: 0.069180955 | N60: 0.79364887 | O60: 1.3043313 | P60: 10.47905 | Q60: 28.66267 | R60: 0.93524749 | S60: 149.24503 | T60: 0.17554126 | U60: 0.093647048 | V60: 0.043899061 | W60: 1.372987 | X60: 0.017641488 | Y60: 2.0595295 | Z60: 2.0595295 | AA60: 0.042633888
A61: Power | B61: 486 | C61: 0.10156057 | D61: 0.15163536 | E61: 0.070176506 | F61: 0.20324629 | G61: 0.45529283 | H61: 0.71309583 | I61: 0.079647295 | J61: 0.30609406 | K61: 0.057772 | L61: 0.4619773 | M61: 0.062770317 | N61: 0.56560994 | O61: 2.5519559 | P61: 10.100174 | Q61: 16.790848 | R61: 1.4609278 | S61: 62.564808 | T61: 0.027031045 | U61: 0.21456448 | V61: 0.13400709 | W61: 1.1260897 | X61: 0.10274405 | Y61: 0.62002727 | Z61: 0.62002727 | AA61: 0.15159698
A62: Precious Metals | B62: 777 | C62: 0.37462457 | D62: 0.24943598 | E62: 0.21530139 | F62: 0.28078921 | G62: 1.3739382 | H62: 1.3975027 | I62: 0.1181794 | J62: 0.79893711 | K62: 0.067295 | L62: 0.083037579 | M62: 0.11253641 | N62: 0.91764344 | O62: 4.7533815 | P62: 12.736513 | Q62: 17.837739 | R62: 3.8046573 | S62: 116.98436 | T62: 0.080279241 | U62: 0.16035755 | V62: 0.11788558 | W62: 0.71585187 | X62: 0.16901958 | Y62: 0.29564179 | Z62: 0.29564179 | AA62: 0.24974338
A63: Publishing & Newspapers | B63: 307 | C63: 0.030572471 | D63: 0.073815904 | E63: 0.093221906 | F63: 0.26540696 | G63: 0.77878896 | H63: 0.81662806 | I63: 0.08547616 | J63: 0.36176808 | K63: 0.057772 | L63: 0.2186823 | M63: 0.076212577 | N63: 1.5592006 | O63: 1.2980664 | P63: 10.231798 | Q63: 16.492231 | R63: 1.5238708 | S63: 71.364921 | T63: 0.072361189 | U63: 0.034508684 | V63: 0.018952713 | W63: 0.59410599 | X63: 0.070289364 | Y63: 0.48492949 | Z63: 0.48492949 | AA63: 0.0742854
... A97: Total Market (without financials) | B97: 43056 | C97: 0.11344442 | D97: 0.10747662 | E97: 0.10623043 | F97: 0.22670483 | G97: 0.95536368 | H97: 1.077443 | I97: 0.10016004 | J97: 0.4302452 | K97: 0.057772 | L97: 0.20602952 | M97: 0.088407129 | N97: 1.2214305 | O97: 2.3303941 | P97: 13.697249 | Q97: 20.826401 | R97: 2.9224213 | S97: 74.106269 | T97: 0.11657112 | U97: 0.068727451 | V97: 0.038685709 | W97: 0.54393809 | X97: 0.11519475 | Y97: 0.69052367 | Z97: 0.69052367 | AA97: 0.10913799

Sheet Input Stat Distributioons
C1: Revenue Growth Rate = Last 3 years | F1: Pre-tax Operating Margin | I1: Sales to Invested Capital | L1: Cost of Capital | P1: Beta | R1: Debt to Capital Ratio
A2: Industry Group | B2: count | C2: First Quartlie | D2: Median | E2: Third Quartile | F2: First Quartlie | G2: Median | H2: Third Quartile | I2: First Quartlie | J2: Median | K2: Third Quartile | L2: First Quartlie | M2: Median | N2: Third Quartile | O2: First Quartlie | P2: Median | Q2: Third Quartile | R2: First Quartlie | S2: Median | T2: Third Quartile
A3: Advertising | B3: 419 | C3: 0.0105 | D3: 0.0593 | E3: 0.158 | F3: -0.06551619 | G3: 0.036951501 | H3: 0.097777666 | I3: 0.96385542 | J3: 2.4075501 | K3: 6.0298507 | L3: 0.087683684 | M3: 0.093126865 | N3: 0.095025701 | O3: 0.5600358 | P3: 1.1380437 | Q3: 1.8348243 | R3: 0.016105884 | S3: 0.11567878 | T3: 0.34722222
A4: Aerospace/Defense | B4: 319 | C4: 0.0798 | D4: 0.143 | E4: 0.284 | F4: -0.028982843 | G4: 0.071171171 | H4: 0.143 | I4: 0.52196642 | J4: 1.189582 | K4: 2.2013322 | L4: 0.090536263 | M4: 0.096128738 | N4: 0.099354713 | O4: 0.75929921 | P4: 1.1704108 | Q4: 1.6706775 | R4: 0.0070339271 | S4: 0.052912702 | T4: 0.1594113
A5: Air Transport | B5: 150 | C5: 0.0354 | D5: 0.0633 | E5: 0.104 | F5: 0.01688127 | G5: 0.089610475 | H5: 0.17780674 | I5: 0.66490106 | J5: 1.0207227 | K5: 2.0479378 | L5: 0.068489284 | M5: 0.073008265 | N5: 0.084513318 | O5: 0.5607257 | P5: 0.9879906 | Q5: 1.3345367 | R5: 0.14449891 | S5: 0.40188525 | T5: 0.61462232
A6: Apparel | B6: 1207 | C6: 0.0239 | D6: 0.0653 | E6: 0.118 | F6: -0.016271552 | G6: 0.03966725 | H6: 0.086104438 | I6: 0.58473101 | J6: 1.2038601 | K6: 2.0410868 | L6: 0.074640025 | M6: 0.085413022 | N6: 0.089427586 | O6: 0.1988114 | P6: 0.71547838 | Q6: 1.2547219 | R6: 0.032099373 | S6: 0.18847656 | T6: 0.46681835
A7: Auto & Truck | B7: 165 | C7: 0.0159 | D7: 0.0669 | E7: 0.186 | F7: -0.22283516 | G7: 0.018811881 | H7: 0.067819551 | I7: 0.63265451 | J7: 1.4801374 | K7: 2.7371917 | L7: 0.090843689 | M7: 0.097285406 | N7: 0.11451945 | O7: 0.88581339 | P7: 1.4002653 | Q7: 1.8609099 | R7: 0.013826069 | S7: 0.15163608 | T7: 0.47980656
A8: Auto Parts | B8: 797 | C8: 0.0177 | D8: 0.0726 | E8: 0.176 | F8: 0.020165394 | G8: 0.050746797 | H8: 0.090620015 | I8: 0.9825752 | J8: 1.536157 | K8: 2.2719209 | L8: 0.10084516 | M8: 0.10706323 | N8: 0.11371136 | O8: 0.80921022 | P8: 1.3407934 | Q8: 2.0768976 | R8: 0.032986691 | S8: 0.13795278 | T8: 0.40616
A9: Bank (Money Center) | B9: 604 | C9: 0.0282 | D9: 0.0558 | E9: 0.11 | F9: 0 | G9: 0 | H9: 0 | I9: 0.15079021 | J9: 0.2834183 | K9: 0.53726308 | L9: 0.057500791 | M9: 0.064632123 | N9: 0.082652948 | O9: 0.23366346 | P9: 0.6477726 | Q9: 1.1391272 | R9: 0.16862933 | S9: 0.42266583 | T9: 0.63166667
A10: Banks (Regional) | B10: 825 | C10: 0.0537 | D10: 0.095 | E10: 0.161 | F10: -0.00010768468 | G10: 0 | H10: 0.00091216257 | I10: 0.17958067 | J10: 0.3293019 | K10: 0.59921304 | L10: 0.050514582 | M10: 0.051755263 | N10: 0.052807513 | O10: 0.12409569 | P10: 0.5040346 | Q10: 0.75998532 | R10: 0.087241553 | S10: 0.28151757 | T10: 0.5664475
A11: Beverage (Alcoholic) | B11: 217 | C11: -0.0113 | D11: 0.0232 | E11: 0.0573 | F11: 0.01687529 | G11: 0.097674419 | H11: 0.16863588 | I11: 0.47220999 | J11: 1.0584074 | K11: 2.1244263 | L11: 0.071741711 | M11: 0.076576061 | N11: 0.088699339 | O11: 0.17958924 | P11: 0.63178585 | Q11: 1.2744436 | R11: 0.0093212732 | S11: 0.082903464 | T11: 0.312947
A12: Beverage (Soft) | B12: 94 | C12: 0.0266 | D12: 0.055 | E12: 0.122 | F12: 0.0095238095 | G12: 0.095829992 | H12: 0.15529945 | I12: 0.96072541 | J12: 1.6391533 | K12: 2.5066215 | L12: 0.063673948 | M12: 0.066612756 | N12: 0.074277173 | O12: 0.16063626 | P12: 0.43396301 | Q12: 0.86953897 | R12: 0.0053982436 | S12: 0.070130712 | T12: 0.22186357
A13: Broadcasting | B13: 127 | C13: -0.019 | D13: 0.0131 | E13: 0.0356 | F13: -0.056 | G13: 0.059143969 | H13: 0.11553857 | I13: 0.51487482 | J13: 0.80349091 | K13: 1.5222955 | L13: 0.068690292 | M13: 0.0730343 | N13: 0.084330611 | O13: 0.41067162 | P13: 0.74809421 | Q13: 1.1761603 | R13: 0.043875073 | S13: 0.22394822 | T13: 0.56070288
A14: Brokerage & Investment Banking | B14: 623 | C14: 0.0321 | D14: 0.0922 | E14: 0.146 | F14: 0 | G14: 0 | H14: 0.00025443717 | I14: 0.091779729 | J14: 0.23887042 | K14: 0.92079208 | L14: 0.06255798 | M14: 0.071414964 | N14: 0.07371942 | O14: 0.2706804 | P14: 0.85785836 | Q14: 1.6737555 | R14: 0.0075278951 | S14: 0.15926893 | T14: 0.5215964
... A53: Machinery | B53: 1553 | C53: 0.0311 | D53: 0.0797 | E53: 0.161 | F53: -0.00014534884 | G53: 0.064594072 | H53: 0.12549329 | I53: 0.71822589 | J53: 1.1772598 | K53: 1.7824195 | L53: 0.10046228 | M53: 0.10599628 | N53: 0.10790268 | O53: 0.70061555 | P53: 1.285268 | Q53: 2.0069068 | R53: 0.017421603 | S53: 0.094104029 | T53: 0.24615007
A54: Metals & Mining | B54: 1874 | C54: 0.0608 | D54: 0.124 | E54: 0.236 | F54: NA | G54: 0.002173913 | H54: 0.088348416 | I54: 0 | J54: 0 | K54: 0.55867613 | L54: 0.086819561 | M54: 0.086836918 | N54: 0.092136016 | O54: 0.4817159 | P54: 1.153442 | Q54: 1.8290792 | R54: 0 | S54: 0.0052951947 | T54: 0.12631514
A55: Office Equipment & Services | B55: 139 | C55: 0.0282 | D55: 0.0461 | E55: 0.0936 | F55: 0.00042585942 | G55: 0.050969435 | H55: 0.092341168 | I55: 0.81833061 | J55: 1.5027356 | K55: 2.3792487 | L55: 0.072618677 | M55: 0.075820564 | N55: 0.088048514 | O55: 0.32277389 | P55: 0.67933298 | Q55: 1.0815321 | R55: 0.012900704 | S55: 0.12710934 | T55: 0.31388187
A56: Oil/Gas (Integrated) | B56: 34 | C56: -0.0468 | D56: -0.0312 | E56: -0.0181 | F56: 0.050958749 | G56: 0.10407715 | H56: 0.15507488 | I56: 0.77987251 | J56: 1.3097944 | K56: 1.7826395 | L56: 0.066790875 | M56: 0.070851303 | N56: 0.080928587 | O56: 0.24707811 | P56: 0.61537499 | Q56: 0.90003969 | R56: 0.12031367 | S56: 0.31042146 | T56: 0.4144784
A57: Oil/Gas (Production and Exploration) | B57: 539 | C57: -0.0437 | D57: 0.048 | E57: 0.233 | F57: -0.32763158 | G57: 0.12131148 | H57: 0.30812325 | I57: 0.080155453 | J57: 0.39806078 | K57: 0.69527363 | L57: 0.069637357 | M57: 0.0712255 | N57: 0.07552113 | O57: 0.2672335 | P57: 0.6883683 | Q57: 1.2492449 | R57: 0 | S57: 0.095292767 | T57: 0.35477178
A58: Oil/Gas Distribution | B58: 186 | C58: 0.00865 | D58: 0.0573 | E58: 0.111 | F58: 0.013795675 | G58: 0.10943972 | H58: 0.24878049 | I58: 0.33318419 | J58: 0.79857302 | K58: 2.9392265 | L58: 0.058910461 | M58: 0.065254624 | N58: 0.07159978 | O58: 0.28873686 | P58: 0.62248404 | Q58: 1.0538646 | R58: 0.072761002 | S58: 0.26194008 | T58: 0.496
A59: Oilfield Svcs/Equip. | B59: 431 | C59: -0.0372 | D59: 0.0184 | E59: 0.109 | F59: 0.0024869888 | G59: 0.033487833 | H59: 0.10511055 | I59: 0.78661207 | J59: 1.5778617 | K59: 3.1213069 | L59: 0.071851996 | M59: 0.077134682 | N59: 0.088105453 | O59: 0.3913905 | P59: 0.87834339 | Q59: 1.3310634 | R59: 0.039205788 | S59: 0.1901757 | T59: 0.45007541
A60: Packaging & Container | B60: 438 | C60: 0.00209 | D60: 0.0571 | E60: 0.104 | F60: 0.013578186 | G60: 0.051260504 | H60: 0.093700787 | I60: 0.81492288 | J60: 1.2088673 | K60: 1.7706093 | L60: 0.067591935 | M60: 0.07539462 | N60: 0.079752915 | O60: 0.22752569 | P60: 0.6719177 | Q60: 1.2356532 | R60: 0.049268668 | S60: 0.22133905 | T60: 0.44812362
A61: Paper/Forest Products | B61: 271 | C61: -0.00868 | D61: 0.0246 | E61: 0.0709 | F61: -0.017109964 | G61: 0.027083333 | H61: 0.062194511 | I61: 0.57120003 | J61: 0.89539295 | K61: 1.3926989 | L61: 0.067235649 | M61: 0.071129648 | N61: 0.081213474 | O61: 0.33013112 | P61: 0.87244352 | Q61: 1.4561978 | R61: 0.073240589 | S61: 0.29740135 | T61: 0.53995902
A62: Power | B62: 486 | C62: -0.00362 | D62: 0.0358 | E62: 0.0792 | F62: 0.054893837 | G62: 0.11715686 | H62: 0.20732876 | I62: 0.37198213 | J62: 0.65158955 | K62: 1.3229449 | L62: 0.059867059 | M62: 0.062927108 | N62: 0.071747353 | O62: 0.26860222 | P62: 0.65917826 | Q62: 1.1191914 | R62: 0.089009288 | S62: 0.36301434 | T62: 0.55
A63: Precious Metals | B63: 777 | C63: 0.257 | D63: 0.375 | E63: 0.638 | F63: NA | G63: 0.062106454 | H63: 0.32639405 | I63: 0 | J63: 0 | K63: 0.41071429 | L63: 0.097508233 | M63: 0.097598996 | N63: 0.097788609 | O63: 0.73056049 | P63: 1.3264039 | Q63: 1.9939439 | R63: 0 | S63: 0.0013902547 | T63: 0.053206003
A64: Publishing & Newspapers | B64: 307 | C64: -0.00617 | D64: 0.0338 | E64: 0.0592 | F64: -0.050903901 | G64: 0.040438596 | H64: 0.10309216 | I64: 0.67296252 | J64: 1.3024523 | K64: 2.3071948 | L64: 0.076072846 | M64: 0.079135958 | N64: 0.088681784 | O64: 0.27954385 | P64: 0.66870763 | Q64: 1.2169011 | R64: 0.0097946559 | S64: 0.10646304 | T64: 0.34971098
A65: R.E.I.T. | B65: 643 | C65: -0.012 | D65: 0.0302 | E65: 0.0873 | F65: 0.18584552 | G65: 0.5 | H65: 0.6478003 | I65: 0.063293199 | J65: 0.089949302 | K65: 0.13501039 | L65: 0.053288282 | M65: 0.055380241 | N65: 0.062609559 | O65: 0.22924379 | P65: 0.52892681 | Q65: 0.81049025 | R65: 0.17741859 | S65: 0.39564492 | T65: 0.54730251
A66: Real Estate (Development) | B66: 895 | C66: -0.0411 | D66: 0.0573 | E66: 0.198 | F66: -0.09605741 | G66: 0.083850043 | H66: 0.22321429 | I66: 0.11235647 | J66: 0.25417867 | K66: 0.58491306 | L66: 0.061643943 | M66: 0.067719866 | N66: 0.070977069 | O66: 0.27812661 | P66: 0.78013907 | Q66: 1.4366425 | R66: 0.088927637 | S66: 0.34108849 | T66: 0.66811034
A67: Real Estate (General/Diversified) | B67: 312 | C67: 0.0316 | D67: 0.0835 | E67: 0.166 | F67: 0.038744316 | G67: 0.16743738 | H67: 0.33873366 | I67: 0.078800036 | J67: 0.19328349 | K67: 0.4524207 | L67: 0.066928932 | M67: 0.070118232 | N67: 0.079901081 | O67: 0.29266218 | P67: 0.76293905 | Q67: 1.4537474 | R67: 0.041118764 | S67: 0.32348112 | T67: 0.56649284
A68: Real Estate (Operations & Services) | B68: 752 | C68: 0.0235 | D68: 0.0689 | E68: 0.143 | F68: 0.047268501 | G68: 0.27278477 | H68: 0.57703081 | I68: 0.069533914 | J68: 0.12830516 | K68: 0.53719452 | L68: 0.060788021 | M68: 0.065221485 | N68: 0.073620353 | O68: 0.19583174 | P68: 0.66851731 | Q68: 1.2682345 | R68: 0.021427592 | S68: 0.26315789 | T68: 0.54089219
A69: Recreation | B69: 332 | C69: 0.0219 | D69: 0.0622 | E69: 0.104 | F69: -0.0014563737 | G69: 0.065944645 | H69: 0.14398422 | I69: 0.61027049 | J69: 1.1327892 | K69: 1.9286351 | L69: 0.078521896 | M69: 0.082940846 | N69: 0.085153474 | O69: 0.47234658 | P69: 0.96445201 | Q69: 1.4545087 | R69: 0.022707424 | S69: 0.14532589 | T69: 0.39711842
A70: Reinsurance | B70: 32 | C70: 0.00042 | D70: 0.0294 | E70: 0.088 | F70: 0.072340281 | G70: 0.15026222 | H70: 0.1961326 | I70: 0.84018639 | J70: 1.0557223 | K70: 2.0136121 | L70: 0.087151558 | M70: 0.092901234 | N70: 0.10322952 | O70: 0.47122846 | P70: 0.91024552 | Q70: 1.1499132 | R70: 0.0014698677 | S70: 0.11549645 | T70: 0.21598686
A71: Restaurant/Dining | B71: 410 | C71: 0.0356 | D71: 0.0749 | E71: 0.13 | F71: -0.004481982 | G71: 0.044109034 | H71: 0.087618312 | I71: 1.1942609 | J71: 2.055336 | K71: 3.5432689 | L71: 0.068036011 | M71: 0.07129058 | N71: 0.072926693 | O71: 0.29214947 | P71: 0.6534691 | Q71: 1.0995172 | R71: 0.085987924 | S71: 0.25372692 | T71: 0.44432133
A72: Retail (Automotive) | B72: 212 | C72: 0.0133 | D72: 0.0506 | E72: 0.115 | F72: 0.0079478094 | G72: 0.030208771 | H72: 0.054897472 | I72: 1.2634561 | J72: 2.5489582 | K72: 4.2379277 | L72: 0.066657354 | M72: 0.07035075 | N72: 0.081691492 | O72: 0.35910711 | P72: 0.7490808 | Q72: 1.1905846 | R72: 0.10060447 | S72: 0.30848675 | T72: 0.57398274
A73: Retail (Building Supply) | B73: 121 | C73: 0.0259 | D73: 0.0552 | E73: 0.0892 | F73: 0.01128069 | G73: 0.042495127 | H73: 0.10966813 | I73: 1.1721261 | J73: 1.8502149 | K73: 3.4286806 | L73: 0.0730169 | M73: 0.078076451 | N73: 0.089194208 | O73: 0.45318522 | P73: 0.86682912 | Q73: 1.4258182 | R73: 0.10411965 | S73: 0.26184311 | T73: 0.5017338
A74: Retail (Distributors) | B74: 1079 | C74: 0.0225 | D74: 0.0507 | E74: 0.0968 | F74: 0.0011340206 | G74: 0.032154296 | H74: 0.081809641 | I74: 0.69949495 | J74: 1.746888 | K74: 3.3643264 | L74: 0.06868662 | M74: 0.072556795 | N74: 0.083875241 | O74: 0.21884242 | P74: 0.73955367 | Q74: 1.3171939 | R74: 0.022680412 | S74: 0.15425532 | T74: 0.41054496
A75: Retail (General) | B75: 252 | C75: 0.0275 | D75: 0.0629 | E75: 0.104 | F75: 0.002519084 | G75: 0.041809102 | H75: 0.086407966 | I75: 0.67627095 | J75: 1.7213483 | K75: 3.1832884 | L75: 0.080213136 | M75: 0.084502462 | N75: 0.08767329 | O75: 0.52273338 | P75: 0.8825847 | Q75: 1.4353817 | R75: 0.072451562 | S75: 0.28691889 | T75: 0.55808568
... A96: Utility (Water) | B96: 106 | C96: 0.0243 | D96: 0.0677 | E96: 0.144 | F96: 0.053398058 | G96: 0.22417778 | H96: 0.29970012 | I96: 0.22060203 | J96: 0.32630968 | K96: 0.61309152 | L96: 0.058779817 | M96: 0.061600651 | N96: 0.065032802 | O96: 0.22613192 | P96: 0.57371494 | Q96: 1.0854336 | R96: 0.11598303 | S96: 0.3499608 | T96: 0.61848497

Sheet Trailing 12 month Worskheet
A1: If you are midway through a year, and want to compute updated trailing twelve month numbers, this worksheet may help. You will need your most recent quartely financials (or 10Q) as well as your most recent annual (or 10K).
B6: Last Annual | C6: First X months: Last year | D6: First X months: Current year | E6: Trailing 12 month
A7: Revenues | B7: 15794.34 | C7: 7608.13 | D7: 9444.11 | E7: =B7-C7+D7
A8: Technology & Content | B8: 1221.81 | C8: 581.41 | D8: 756 | E8: =B8-C8+D8
A9: Operating income or EBIT | B9: 1605.23 | C9: 908.79 | D9: 1165.5 | E9: =B9-C9+D9
A10: Interest expenses | B10: 420.49 | C10: 182.82 | D10: 287.56 | E10: =B10-C10+D10
A11: Book value of equity | B11: 5238.77 | D11: 6105.55
A12: Book value of debt | B12: 10360 | D12: 12594.14
A13: Do you have operating lease commitments?
A14: Cash and cross holdings | B14: 3794.48 | D14: 5004.25
A15: Non-operating assets | B15: 0 | D15: 0
A16: Minority interests | B16: 0 | D16: 0
A17: Number of shares outstanding =
A18: Current stock price =
A19: Effective tax rate = | B19: =15885/61372 | C19: =6965/27030 | D19: =3941/23906
A20: Marginal tax rate =
A21: Lease commitments
A22: Year 1 | B22: 172.47 | D22: NA
A23: Year 2 | B23: 139.4 | C23: Copy into operating lease worksheet | D23: NA
A24: Year 3 | B24: 145.18 | D24: NA
A25: Year 4 | B25: 156.53 | D25: NA
A26: Year 5 | B26: 151.2 | D26: NA
A27: Beyond year 5 | B27: 943.63 | D27: NA
A30: Current year's lease expense | B30: 107
D34: 75872
D35: 2404
D36: 24171
D37: 276
A41: G&A | B41: 630.29 | C41: 286.14 | D41: 426.61 | E41: =B41-C41+D41
A42: Marketing Costs | B42: 2369.47 | C42: 1128.78 | D42: 1219.73 | E42: =B42-C42+D42
A43: Content Costs | B43: 9967.54 | C43: 4703.01 | D43: 5876.21 | E43: =B43-C43+D43
A45: Content Costs (Cash Flows) | B45: 13043 | C45: 6020.47 | D45: 6322.85 | E45: =B45-C45+D45

Sheet Answer keys
A1: Yes/No | B1: Book or Market Value | C1: ERP choices | D1: Cost of debt | E1: Synthetic rating | F1: Beta | G1: Rating is | H1: Region | I1: Cost of Capital Approach | J1: Reinvestment lag
A2: Yes | B2: B | C2: Will input | D2: Direct input | E2: 1 | F2: Direct input | G2: Aaa/AAA | H2: First Decile | I2: I will input | J2: 0
A3: No | B3: V | C3: Country of incorporation | D3: Synthetic rating | E3: 2 | F3: Single Business(US) | G3: Aa2/AA | H3: First Quartile | I3: Detailed | J3: 1
C4: Operating countries | D4: Actual rating | F4: Single Business(Global) | G4: A1/A+ | H4: Median | I4: Industry Average | J4: 2
C5: Operating regions | F5: Multibusiness(US) | G5: A2/A | H5: Third Quartile | I5: Distribution | J5: 3
F6: Multibusiness(Global) | G6: A3/A- | H6: Ninth Decile
G7: Baa2/BBB
G8: Ba1/BB+
G9: Ba2/BB
G10: B1/B+
G11: B2/B
G12: B3/B-
G13: C2/C
G14: Ca2/CC
G15: Caa/CCC
G16: D2/D
